Workbook

Sheet 1. Executive Dashboard
A1: BlueAlly × AEA AI Portfolio Value Acceleration Dashboard
A2: Generated: 1/29/2026, 12:41:18 PM
A4: PORTFOLIO OVERVIEW
A5: Total Companies | B5: 54
A6: Total Use Cases | B6: 540
A7: Total Annual Value | B7: 388.99362
A8: Average Value/Company | B8: 7.2035856
A10: BENEFIT DISTRIBUTION
A11: Cost Savings | B11: 169.05149
A12: Revenue Growth | B12: 148.10122
A13: Risk Reduction | B13: 65.960392
A14: Cash Flow Acceleration | B14: 57.370511
A16: PRIORITY BREAKDOWN
A17: Critical Priority | B17: 111
A18: High Priority | B18: 247
A19: Medium Priority | B19: 182
A21: TOP 10 USE CASES BY VALUE
A22: Company | B22: Use Case | C22: Total Value ($M) | D22: Priority | E22: Phase
A23: The Lifetime Value Co | B23: Churn Prediction & Intervention Engine | C23: 32.5 | D23: High | E23: Q1
A24: Splash Car Wash | B24: Predictive Member Churn Intervention | C24: 17.4 | D24: High | E24: Q2
A25: Bespoke Partners | B25: Due Diligence Document Analyzer | C25: 17.2 | D25: Critical | E25: Q2
A26: Bespoke Partners | B26: Intelligent CRM Relationship Mapper | C26: 14.7 | D26: High | E26: Q3
A27: Traeger Pellet Grills | B27: Predictive Demand Planning Engine | C27: 12.7 | D27: High | E27: Q2
A28: Splash Car Wash | B28: Single-Wash Membership Conversion Assistant | C28: 12.6 | D28: High | E28: Q2
A29: Splash Car Wash | B29: Equipment Predictive Maintenance Advisor | C29: 11.6 | D29: Medium | E29: Q3
A30: Bespoke Partners | B30: Regulatory Compliance Intelligence System | C30: 10.7 | D30: High | E30: Q3
A31: Traeger Pellet Grills | B31: Customer Feedback Intelligence Platform | C31: 10.7 | D31: High | E31: Q2
A32: Splash Car Wash | B32: Site Selection Decision Support | C32: 10 | D32: Medium | E32: Q3

Sheet 2. Company Master
A1: Rank | B1: Company | C1: Revenue ($M) | D1: Est. EBITDA ($M) | E1: Employees | F1: Total Use Cases | G1: Total Annual Value ($M) | H1: Cost Benefit ($M) | I1: Revenue Benefit ($M) | J1: Risk Benefit ($M) | K1: Cash Flow Benefit ($M) | L1: Value/Token Ratio | M1: Top Priority Count
A2: 1 | B2: AmeriVet Partners | C2: 850 | D2: 85 | E2: 0 | F2: 10 | G2: 200.4 | H2: 98.2 | I2: 82.5 | J2: 12.6 | K2: 7 | L2: 4417 | M2: 3
A3: 2 | B3: Chemtron RiverBend | C3: 892 | D3: 89.2 | E3: 1850 | F3: 10 | G3: 171.1 | H3: 80.5 | I3: 32.1 | J3: 37.3 | K3: 21.2 | L3: 12.58 | M3: 2
A4: 3 | B4: Monroe Engineering | C4: 847 | D4: 84.7 | E4: 3200 | F4: 10 | G4: 166.3 | H4: 71.1 | I4: 13.6 | J4: 24.9 | K4: 56.7 | L4: 15700 | M4: 3
A5: 4 | B5: NES Fircroft | C5: 850 | D5: 85 | E5: 4000 | F5: 10 | G5: 154.5 | H5: 73.9 | I5: 39.6 | J5: 23.5 | K5: 17.5 | L5: 32870 | M5: 9
A6: 5 | B6: American Dental | C6: 450 | D6: 45 | E6: 0 | F6: 10 | G6: 153.8 | H6: 47.3 | I6: 76.8 | J6: 9.4 | K6: 21.3 | L6: 5542 | M6: 3
A7: 6 | B7: Polygon Group | C7: 890 | D7: 89 | E7: 1850 | F7: 10 | G7: 153.8 | H7: 92.3 | I7: 28.5 | J7: 13.6 | K7: 19.4 | L7: 1203000 | M7: 4
A8: 7 | B8: Numotion | C8: 1800 | D8: 180 | E8: 3500 | F8: 10 | G8: 126.9 | H8: 56.6 | I8: 13.2 | J8: 9.9 | K8: 48.5 | L8: 10.9 | M8: 1
A9: 8 | B9: Rees Scientific | C9: 890 | D9: 89 | E9: 3200 | F9: 10 | G9: 124.8 | H9: 23.6 | I9: 72.7 | J9: 13.6 | K9: 14.9 | L9: 3208 | M9: 4
A10: 9 | B10: WorldWide Electric | C10: 2800 | D10: 280 | E10: 6200 | F10: 10 | G10: 118.7 | H10: 56.8 | I10: 28.1 | J10: 10.4 | K10: 23.4 | L10: 227400 | M10: 0
A11: 10 | B11: RED Global | C11: 2800 | D11: 280 | E11: 6200 | F11: 10 | G11: 116.8 | H11: 69.3 | I11: 30.7 | J11: 5.5 | K11: 11.3 | L11: 4441 | M11: 1
A12: 11 | B12: Impetus Wellness | C12: 180 | D12: 18 | E12: 850 | F12: 10 | G12: 115.2 | H12: 45.1 | I12: 51.4 | J12: 6.8 | K12: 11.9 | L12: 6867 | M12: 4
A13: 12 | B13: Nations Roof | C13: 0 | D13: 0 | E13: 0 | F13: 10 | G13: 114.9 | H13: 59.2 | I13: 27.9 | J13: 11.3 | K13: 16.5 | L13: 24691 | M13: 1
... A35: 34 | B35: Spectrum Control | C35: 180 | D35: 18 | E35: 850 | F35: 10 | G35: 49.8 | H35: 16.6 | I35: 15.3 | J35: 15.2 | K35: 2.7 | L35: 54400 | M35: 2
A36: 35 | B36: Cimsense | C36: NaN | D36: NaN | E36: 450 | F36: 10 | G36: 47.5 | H36: 21.1 | I36: 14.4 | J36: 2.3 | K36: 7.5 | L36: 3045 | M36: 0
A37: 36 | B37: Traeger Pellet Grills | C37: 600 | D37: 60 | E37: 800 | F37: 10 | G37: 46.53 | H37: 13.5 | I37: 19.9 | J37: 1.58 | K37: 11.55 | L37: 111 | M37: 3
A38: 37 | B38: Visual Comfort | C38: 800 | D38: 80 | E38: 2000 | F38: 10 | G38: 45.3 | H38: 17.3 | I38: 6.8 | J38: 2.2 | K38: 18.3 | L38: 11830 | M38: 0
A39: 38 | B39: Singer Industrial | C39: 847 | D39: 84.7 | E39: 0 | F39: 10 | G39: 42.7 | H39: 16.5 | I39: 13.4 | J39: 3.8 | K39: 9 | L39: 3405 | M39: 2
A40: 39 | B40: Excelitas Technologies | C40: 900 | D40: 90 | E40: 6500 | F40: 10 | G40: 40.4 | H40: 15.2 | I40: 10 | J40: 10.5 | K40: 4.7 | L40: 8624 | M40: 5
A41: 40 | B41: Huge | C41: 300 | D41: 30 | E41: 0 | F41: 10 | G41: 39.2 | H41: 26.2 | I41: 3.8 | J41: 5.1 | K41: 4.1 | L41: 26308 | M41: 0
A42: 41 | B42: Verdesian Life Sciences | C42: 450 | D42: 45 | E42: 850 | F42: 10 | G42: 39.1 | H42: 16.1 | I42: 8.9 | J42: 5.8 | K42: 8.2 | L42: 42117 | M42: 3
A43: 42 | B43: P&B Intermodal | C43: 380 | D43: 38 | E43: 850 | F43: 10 | G43: 37 | H43: 11.9 | I43: 19.2 | J43: 0.2 | K43: 5.6 | L43: 7120 | M43: 2
A44: 43 | B44: AS Software | C44: 127 | D44: 12.7 | E44: 890 | F44: 10 | G44: 35 | H44: 12.2 | I44: 17.7 | J44: 4.7 | K44: 1.2 | L44: 11800 | M44: 4
A45: 44 | B45: 50 Floor | C45: 180 | D45: 18 | E45: 0 | F45: 10 | G45: 34.4 | H45: 13.6 | I45: 14.2 | J45: 2.8 | K45: 3.8 | L45: 38600 | M45: 1
A46: 45 | B46: Hero Digital | C46: 45 | D46: 4.5 | E46: 280 | F46: 10 | G46: 33.7 | H46: 19.8 | I46: 7.5 | J46: 3.8 | K46: 3.3 | L46: 2300 | M46: 0
A47: 46 | B47: ROI CX Solutions | C47: 47 | D47: 4.7 | E47: 285 | F47: 10 | G47: 27.3 | H47: 13.2 | I47: 10.2 | J47: 2.9 | K47: 1 | L47: 88400 | M47: 1
A48: 47 | B48: Veseris | C48: 850 | D48: 85 | E48: 1400 | F48: 10 | G48: 24.7 | H48: 5.3 | I48: 10.6 | J48: 3.1 | K48: 5.6 | L48: 28073 | M48: 0
... A51: 50 | B51: TileBar | C51: 85 | D51: 8.5 | E51: 0 | F51: 10 | G51: 20.4 | H51: 7.6 | I51: 9.4 | J51: 1.1 | K51: 2.3 | L51: 13300 | M51: 1
A52: 51 | B52: Commonwealth Pain | C52: NaN | D52: NaN | E52: 0 | F52: 10 | G52: 14.7 | H52: 5.9 | I52: 4.1 | J52: 1.3 | K52: 3.4 | L52: 3519 | M52: 2
A53: 52 | B53: Meritus Gas Partners | C53: 340 | D53: 34 | E53: 520 | F53: 10 | G53: 13.9 | H53: 6 | I53: 0.3 | J53: 3.6 | K53: 4 | L53: 29500 | M53: 2
A54: 53 | B54: American Expediting | C54: 28 | D54: 2.8 | E54: 45 | F54: 10 | G54: 4.1 | H54: 0.6 | I54: 3.1 | J54: 0.2 | K54: 0.2 | L54: 2874 | M54: 1
A55: 54 | B55: American Oncology Network | C55: NaN | D55: NaN | E55: 0 | F55: 10 | G55: 0.0001134 | H55: 4.09e-05 | I55: 3.77e-05 | J55: 7.7e-06 | K55: 2.71e-05 | L55: 272 | M55: 1

Sheet 3. Use Cases Catalog
A1: Company | B1: Use Case ID | C1: Use Case Name | D1: Function | E1: Sub-Function | F1: AI Primitives | G1: Priority Tier | H1: Recommended Phase | I1: Cost Benefit ($M) | J1: Revenue Benefit ($M) | K1: Risk Benefit ($M) | L1: Cash Flow Benefit ($M) | M1: Total Annual Value ($M) | N1: Probability of Success | O1: Time-to-Value (mo) | P1: Effort Score | Q1: Data Readiness | R1: Integration Complexity | S1: Monthly Tokens (K) | T1: Annual Token Cost ($K) | U1: Cost Formula | V1: Revenue Formula | W1: Risk Formula | X1: Cash Flow Formula | Y1: Human Checkpoint | Z1: Adjusted Cost ($M) | AA1: Adjusted Revenue ($M) | AB1: Adjusted Risk ($M) | AC1: Adjusted Cash Flow ($M) | AD1: Total Adjusted Impact ($M) | AE1: Risk-Weighted Value ($M)
A2: 50 Floor | B2: UC-02 | C2: AI-Powered Customer Service Assistant | D2: Customer Service | E2: Inquiry Resolution | F2: Conversational Interfaces, Research & Information Retrieval | G2: High | H2: Q1 | I2: 4.1e-06 | J2: 0 | K2: 0 | L2: 0 | M2: 4.1e-06 | N2: 0.85 | O2: 6 | P2: 3 | Q2: 4 | R2: 3 | S2: 23400 | T2: 351 | U2: 43,200 hours × $85/hour × 60% deflection × 0.90 × 0.75 = $2.5M rounded down | V2: No direct revenue impact | W2: No direct risk impact | X2: No direct cash flow impact | Y2: Customer service representatives handle all escalated inquiries and approve any schedule changes or | Z2: =I2*'Dynamic Analysis Dashboard'!$B$8*'Dynamic Analysis Dashboard'!$B$9*'Dynamic Analysis Dashboard'!$B$21 -> 2.7675e-06 | AA2: =J2*'Dynamic Analysis Dashboard'!$B$8*'Dynamic Analysis Dashboard'!$B$9*'Dynamic Analysis Dashboard'!$B$21 -> 0 | AB2: =K2*'Dynamic Analysis Dashboard'!$B$10*'Dynamic Analysis Dashboard'!$B$9*'Dynamic Analysis Dashboard'!$B$21 -> 0 | AC2: =L2*'Dynamic Analysis Dashboard'!$B$11*'Dynamic Analysis Dashboard'!$B$9*'Dynamic Analysis Dashboard'!$B$21 -> 0 | AD2: =SUM(Z2:AC2) -> 2.7675e-06 | AE2: =AD2*N2 -> 2.352375e-06
A3: 50 Floor | B3: UC-04 | C3: Automated Lead Nurture Orchestration | D3: Sales Operations | E3: Lead Nurture | F3: Workflow Automation, Content Creation, Conversational Interfaces | G3: High | H3: Q2 | I3: 0.8 | J3: 8.5e-06 | K3: 0 | L3: 0 | M3: 9.3e-06 | N3: 0.7 | O3: 9 | P3: 4 | Q3: 3 | R3: 4 | S3: 11040 | T3: 189 | U3: 15 reps × 1,500 hours × $125/hour × 0.90 × 0.75 = $1.9M × 50% capacity = $900K rounded down | V3: 45,000 appointments × 32% non-close × 25% recovery × $4,800 × 0.95 × 0.75 = $12.3M rounded down | W3: No direct risk impact | X3: No direct cash flow impact | Y3: Sales representatives approve messaging templates and handle all direct phone conversations with re- | Z3: =I3*'Dynamic Analysis Dashboard'!$B$8*'Dynamic Analysis Dashboard'!$B$9*'Dynamic Analysis Dashboard'!$B$21 -> 0.54 | AA3: =J3*'Dynamic Analysis Dashboard'!$B$8*'Dynamic Analysis Dashboard'!$B$9*'Dynamic Analysis Dashboard'!$B$21 -> 5.7375e-06 | AB3: =K3*'Dynamic Analysis Dashboard'!$B$10*'Dynamic Analysis Dashboard'!$B$9*'Dynamic Analysis Dashboard'!$B$21 -> 0 | AC3: =L3*'Dynamic Analysis Dashboard'!$B$11*'Dynamic Analysis Dashboard'!$B$9*'Dynamic Analysis Dashboard'!$B$21 -> 0 | AD3: =SUM(Z3:AC3) -> 0.54000574 | AE3: =AD3*N3 -> 0.37800402
A4: 50 Floor | B4: UC-01 | C4: Intelligent Measurement Validation System | D4: Installation Coordination | E4: Measurement Validation | F4: Data Analysis, Workflow Automation | G4: Medium | H4: Q2 | I4: 5.2e-06 | J4: 0 | K4: 0.9 | L4: 0 | M4: 6.1e-06 | N4: 0.8 | O4: 9 | P4: 4 | Q4: 3 | R4: 4 | S4: 12375 | T4: 185 | U4: 13,500 hours × $125/hour × 0.90 × 0.75 = $1.1M labor + $3.5M waste × 60% reduction × 0.90 × 0.75 = $ | V4: No direct revenue impact | W4: $2.1M rework cost × 45% reduction × 0.80 × 0.75 = $500K rounded down | X4: No direct cash flow impact | Y4: Regional manager reviews all measurements flagged for >3% discrepancy before material procurement au | Z4: =I4*'Dynamic Analysis Dashboard'!$B$8*'Dynamic Analysis Dashboard'!$B$9*'Dynamic Analysis Dashboard'!$B$21 -> 3.51e-06 | AA4: =J4*'Dynamic Analysis Dashboard'!$B$8*'Dynamic Analysis Dashboard'!$B$9*'Dynamic Analysis Dashboard'!$B$21 -> 0 | AB4: =K4*'Dynamic Analysis Dashboard'!$B$10*'Dynamic Analysis Dashboard'!$B$9*'Dynamic Analysis Dashboard'!$B$21 -> 0.54 | AC4: =L4*'Dynamic Analysis Dashboard'!$B$11*'Dynamic Analysis Dashboard'!$B$9*'Dynamic Analysis Dashboard'!$B$21 -> 0 | AD4: =SUM(Z4:AC4) -> 0.54000351 | AE4: =AD4*N4 -> 0.43200281
A5: 50 Floor | B5: UC-03 | C5: Dynamic Sales Proposal Generator | D5: Sales Operations | E5: Proposal Generation | F5: Content Creation, Workflow Automation | G5: Critical | H5: Q1 | I5: 1.6e-06 | J5: 5.7e-06 | K5: 0 | L5: 0 | M5: 7.3e-06 | N5: 0.75 | O5: 6 | P5: 3 | Q5: 3 | R5: 3 | S5: 11250 | T5: 236 | U5: 300 reps × 200 hours × $125/hour × 0.90 × 0.75 = $5M × 25% time savings = $1.2M rounded down | V5: 45,000 appointments × 25 min saved × $125/hour × 0.95 × 0.75 = $1M + 45,000 appointments × 3% lift × | W5: No direct risk impact | X5: No direct cash flow impact | Y5: Sales representatives review all AI-generated proposals and adjust pricing or product recommendation | Z5: =I5*'Dynamic Analysis Dashboard'!$B$8*'Dynamic Analysis Dashboard'!$B$9*'Dynamic Analysis Dashboard'!$B$21 -> 1.08e-06 | AA5: =J5*'Dynamic Analysis Dashboard'!$B$8*'Dynamic Analysis Dashboard'!$B$9*'Dynamic Analysis Dashboard'!$B$21 -> 3.8475e-06 | AB5: =K5*'Dynamic Analysis Dashboard'!$B$10*'Dynamic Analysis Dashboard'!$B$9*'Dynamic Analysis Dashboard'!$B$21 -> 0 | AC5: =L5*'Dynamic Analysis Dashboard'!$B$11*'Dynamic Analysis Dashboard'!$B$9*'Dynamic Analysis Dashboard'!$B$21 -> 0 | AD5: =SUM(Z5:AC5) -> 4.9275e-06 | AE5: =AD5*N5 -> 3.695625e-06
A6: 50 Floor | B6: UC-05 | C6: Supplier Communication Automation Hub | D6: Procurement | E6: Supplier Communication | F6: Workflow Automation, Content Creation | G6: Medium | H6: Q3 | I6: 0.9 | J6: 0 | K6: 0 | L6: 1.7e-06 | M6: 2.6e-06 | N6: 0.75 | O6: 12 | P6: 4 | Q6: 2 | R6: 4 | S6: 2700 | T6: 46 | U6: $1.4M friction cost × 75% automation × 0.90 × 0.75 = $700K rounded down | V6: No direct revenue impact | W6: No direct risk impact | X6: 5 days × $350K daily revenue × 0.85 × 0.75 = $1.1M rounded down | Y6: Procurement specialists approve all purchase order changes exceeding $5,000 and handle supplier rela | Z6: =I6*'Dynamic Analysis Dashboard'!$B$8*'Dynamic Analysis Dashboard'!$B$9*'Dynamic Analysis Dashboard'!$B$21 -> 0.6075 | AA6: =J6*'Dynamic Analysis Dashboard'!$B$8*'Dynamic Analysis Dashboard'!$B$9*'Dynamic Analysis Dashboard'!$B$21 -> 0 | AB6: =K6*'Dynamic Analysis Dashboard'!$B$10*'Dynamic Analysis Dashboard'!$B$9*'Dynamic Analysis Dashboard'!$B$21 -> 0 | AC6: =L6*'Dynamic Analysis Dashboard'!$B$11*'Dynamic Analysis Dashboard'!$B$9*'Dynamic Analysis Dashboard'!$B$21 -> 1.08375e-06 | AD6: =SUM(Z6:AC6) -> 0.60750108 | AE6: =AD6*N6 -> 0.45562581
A7: 50 Floor | B7: UC-06 | C7: Intelligent Invoice Processing System | D7: Finance | E7: Accounts Payable | F7: Data Analysis, Workflow Automation | G7: Medium | H7: Q2 | I7: 0.6 | J7: 0 | K7: 0.2 | L7: 1.5e-06 | M7: 2.3e-06 | N7: 0.8 | O7: 6 | P7: 3 | Q7: 3 | R7: 3 | S7: 5280 | T7: 84 | U7: $890K friction cost × 80% automation × 0.90 × 0.75 = $400K rounded down | V7: No direct revenue impact | W7: $500K duplicate payment exposure × 50% reduction × 0.80 × 0.75 = $100K rounded down | X7: 6 days × $350K daily cash × 0.85 × 0.75 = $1.3M rounded down | Y7: Accounts payable specialists review all invoices with discrepancies and approve payments exceeding $ | Z7: =I7*'Dynamic Analysis Dashboard'!$B$8*'Dynamic Analysis Dashboard'!$B$9*'Dynamic Analysis Dashboard'!$B$21 -> 0.405 | AA7: =J7*'Dynamic Analysis Dashboard'!$B$8*'Dynamic Analysis Dashboard'!$B$9*'Dynamic Analysis Dashboard'!$B$21 -> 0 | AB7: =K7*'Dynamic Analysis Dashboard'!$B$10*'Dynamic Analysis Dashboard'!$B$9*'Dynamic Analysis Dashboard'!$B$21 -> 0.12 | AC7: =L7*'Dynamic Analysis Dashboard'!$B$11*'Dynamic Analysis Dashboard'!$B$9*'Dynamic Analysis Dashboard'!$B$21 -> 9.5625e-07 | AD7: =SUM(Z7:AC7) -> 0.52500096 | AE7: =AD7*N7 -> 0.42000076
A8: 50 Floor | B8: UC-07 | C8: Predictive Installation Quality Validator | D8: Quality Assurance | E8: Installation Review | F8: Data Analysis, Workflow Automation | G8: Medium | H8: Q3 | I8: 0 | J8: 0 | K8: 1.2e-06 | L8: 0 | M8: 1.2e-06 | N8: 0.75 | O8: 9 | P8: 3 | Q8: 3 | R8: 3 | S8: 6750 | T8: 106 | U8: No direct cost reduction beyond risk mitigation | V8: No direct revenue impact | W8: $2.1M rework cost × 75% prevention × 0.80 × 0.75 = $900K rounded down | X8: No direct cash flow impact | Y8: Quality managers conduct enhanced pre-installation reviews on all AI-flagged high-risk jobs before m | Z8: =I8*'Dynamic Analysis Dashboard'!$B$8*'Dynamic Analysis Dashboard'!$B$9*'Dynamic Analysis Dashboard'!$B$21 -> 0 | AA8: =J8*'Dynamic Analysis Dashboard'!$B$8*'Dynamic Analysis Dashboard'!$B$9*'Dynamic Analysis Dashboard'!$B$21 -> 0 | AB8: =K8*'Dynamic Analysis Dashboard'!$B$10*'Dynamic Analysis Dashboard'!$B$9*'Dynamic Analysis Dashboard'!$B$21 -> 7.2e-07 | AC8: =L8*'Dynamic Analysis Dashboard'!$B$11*'Dynamic Analysis Dashboard'!$B$9*'Dynamic Analysis Dashboard'!$B$21 -> 0 | AD8: =SUM(Z8:AC8) -> 7.2e-07 | AE8: =AD8*N8 -> 5.4e-07
A9: 50 Floor | B9: UC-08 | C9: Product Content Generation Engine | D9: Marketing | E9: Content Creation | F9: Content Creation, Research & Information Retrieval | G9: Medium | H9: Q1 | I9: 0.2 | J9: 0 | K9: 0 | L9: 0 | M9: 0.2 | N9: 0.85 | O9: 4 | P9: 2 | Q9: 4 | R9: 2 | S9: 600 | T9: 13 | U9: 3,600 hours × $100/hour × 75% time savings × 0.90 × 0.75 = $182K rounded down | V9: No direct revenue impact | W9: No direct risk impact | X9: No direct cash flow impact | Y9: Marketing specialists review and approve all AI-generated product content before publication | Z9: =I9*'Dynamic Analysis Dashboard'!$B$8*'Dynamic Analysis Dashboard'!$B$9*'Dynamic Analysis Dashboard'!$B$21 -> 0.135 | AA9: =J9*'Dynamic Analysis Dashboard'!$B$8*'Dynamic Analysis Dashboard'!$B$9*'Dynamic Analysis Dashboard'!$B$21 -> 0 | AB9: =K9*'Dynamic Analysis Dashboard'!$B$10*'Dynamic Analysis Dashboard'!$B$9*'Dynamic Analysis Dashboard'!$B$21 -> 0 | AC9: =L9*'Dynamic Analysis Dashboard'!$B$11*'Dynamic Analysis Dashboard'!$B$9*'Dynamic Analysis Dashboard'!$B$21 -> 0 | AD9: =SUM(Z9:AC9) -> 0.135 | AE9: =AD9*N9 -> 0.11475
A10: 50 Floor | B10: UC-09 | C10: Installer Training Content Generator | D10: Human Resources | E10: Training Development | F10: Content Creation, Coding Assistance | G10: Medium | H10: Q2 | I10: 0.06 | J10: 0 | K10: 0.1 | L10: 0 | M10: 0.16 | N10: 0.8 | O10: 4 | P10: 2 | Q10: 4 | R10: 2 | S10: 200 | T10: 5 | U10: 720 hours × $125/hour × 75% time savings × 0.90 × 0.75 = $54K rounded down | V10: No direct revenue impact | W10: $300K training gap exposure × 40% reduction × 0.80 × 0.75 = $72K rounded down | X10: No direct cash flow impact | Y10: HR training specialists review all generated content and validate technical accuracy before deployme | Z10: =I10*'Dynamic Analysis Dashboard'!$B$8*'Dynamic Analysis Dashboard'!$B$9*'Dynamic Analysis Dashboard'!$B$21 -> 0.0405 | AA10: =J10*'Dynamic Analysis Dashboard'!$B$8*'Dynamic Analysis Dashboard'!$B$9*'Dynamic Analysis Dashboard'!$B$21 -> 0 | AB10: =K10*'Dynamic Analysis Dashboard'!$B$10*'Dynamic Analysis Dashboard'!$B$9*'Dynamic Analysis Dashboard'!$B$21 -> 0.06 | AC10: =L10*'Dynamic Analysis Dashboard'!$B$11*'Dynamic Analysis Dashboard'!$B$9*'Dynamic Analysis Dashboard'!$B$21 -> 0 | AD10: =SUM(Z10:AC10) -> 0.1005 | AE10: =AD10*N10 -> 0.0804
A11: 50 Floor | B11: UC-10 | C11: Contract Review Acceleration System | D11: Legal | E11: Contract Management | F11: Research & Information Retrieval, Data Analysis, Content Creation | G11: Medium | H11: Q3 | I11: 0.2 | J11: 0 | K11: 0.3 | L11: 0.6 | M11: 1.1e-06 | N11: 0.75 | O11: 6 | P11: 3 | Q11: 3 | R11: 3 | S11: 900 | T11: 16 | U11: $340K friction cost × 70% time reduction × 0.90 × 0.75 = $161K rounded down | V11: No direct revenue impact | W11: $800K compliance exposure × 50% reduction × 0.80 × 0.75 = $240K rounded down | X11: 4 days × $350K daily cash × 0.85 × 0.75 × 50% contracts = $446K rounded down | Y11: Legal counsel reviews all AI-flagged contract provisions and approves final agreement terms before e | Z11: =I11*'Dynamic Analysis Dashboard'!$B$8*'Dynamic Analysis Dashboard'!$B$9*'Dynamic Analysis Dashboard'!$B$21 -> 0.135 | AA11: =J11*'Dynamic Analysis Dashboard'!$B$8*'Dynamic Analysis Dashboard'!$B$9*'Dynamic Analysis Dashboard'!$B$21 -> 0 | AB11: =K11*'Dynamic Analysis Dashboard'!$B$10*'Dynamic Analysis Dashboard'!$B$9*'Dynamic Analysis Dashboard'!$B$21 -> 0.18 | AC11: =L11*'Dynamic Analysis Dashboard'!$B$11*'Dynamic Analysis Dashboard'!$B$9*'Dynamic Analysis Dashboard'!$B$21 -> 0.3825 | AD11: =SUM(Z11:AC11) -> 0.6975 | AE11: =AD11*N11 -> 0.523125
A12: American Dental | B12: UC-03 | C12: Predictive Patient Engagement & No-Show Prevention | D12: Patient Services | E12: Appointment Scheduling | F12: Data Analysis, Conversational Interfaces, Workflow Automation | G12: High | H12: Q2 2026 | I12: 2.4e-06 | J12: 1.18e-05 | K12: 0 | L12: 0 | M12: 1.42e-05 | N12: 0.85 | O12: 7 | P12: 3 | Q12: 3 | R12: 3 | S12: 259200 | T12: 0.0397 | U12: 8,400 hours deflected from manual confirmation calls × $50/hour admin rate × 0.90 × 0.75 = $2.4M | V12: 11 percentage point no-show reduction × 180 practices × 12,000 visits × $285 average revenue × 0.95 | W12: Not applicable - no direct risk reduction | X12: Not applicable - no direct cash flow impact | Y12: Front desk staff reviews AI-flagged high-risk appointments each morning and makes personal confirmat | Z12: =I12*'Dynamic Analysis Dashboard'!$B$8*'Dynamic Analysis Dashboard'!$B$9*'Dynamic Analysis Dashboard'!$B$21 -> 1.62e-06 | AA12: =J12*'Dynamic Analysis Dashboard'!$B$8*'Dynamic Analysis Dashboard'!$B$9*'Dynamic Analysis Dashboard'!$B$21 -> 7.965e-06 | AB12: =K12*'Dynamic Analysis Dashboard'!$B$10*'Dynamic Analysis Dashboard'!$B$9*'Dynamic Analysis Dashboard'!$B$21 -> 0 | AC12: =L12*'Dynamic Analysis Dashboard'!$B$11*'Dynamic Analysis Dashboard'!$B$9*'Dynamic Analysis Dashboard'!$B$21 -> 0 | AD12: =SUM(Z12:AC12) -> 9.585e-06 | AE12: =AD12*N12 -> 8.14725e-06
A13: American Dental | B13: UC-05 | C13: Intelligent Patient Inquiry Router & Response System | D13: Patient Services | E13: Patient Communication | F13: Conversational Interfaces, Research & Information Retrieval, Workflow Automation | G13: High | H13: Q1 2026 | I13: 3.6e-06 | J13: 8.1e-06 | K13: 0 | L13: 0 | M13: 1.17e-05 | N13: 0.8 | O13: 6 | P13: 2 | Q13: 3 | R13: 3 | S13: 25920 | T13: 0.0065 | U13: 22,000 hours deflected from manual inquiry handling × $100/hour patient services rate × 0.90 × 0.75 | V13: 14 percentage point conversion improvement × 180 practices × 1,200 monthly inquiries × 12 months × $ | W13: Not applicable - no direct risk reduction | X13: Not applicable - no direct cash flow impact | Y13: Patient services supervisor reviews all AI-scheduled new patient appointments within 4 hours to veri | Z13: =I13*'Dynamic Analysis Dashboard'!$B$8*'Dynamic Analysis Dashboard'!$B$9*'Dynamic Analysis Dashboard'!$B$21 -> 2.43e-06 | AA13: =J13*'Dynamic Analysis Dashboard'!$B$8*'Dynamic Analysis Dashboard'!$B$9*'Dynamic Analysis Dashboard'!$B$21 -> 5.4675e-06 | AB13: =K13*'Dynamic Analysis Dashboard'!$B$10*'Dynamic Analysis Dashboard'!$B$9*'Dynamic Analysis Dashboard'!$B$21 -> 0 | AC13: =L13*'Dynamic Analysis Dashboard'!$B$11*'Dynamic Analysis Dashboard'!$B$9*'Dynamic Analysis Dashboard'!$B$21 -> 0 | AD13: =SUM(Z13:AC13) -> 7.8975e-06 | AE13: =AD13*N13 -> 6.318e-06
... A187: EZ Texting | B187: UC-02 | C187: Proactive Campaign Performance Advisor | D187: Customer Success | E187: Account Management | F187: Data Analysis, Content Creation | G187: Critical | H187: Q1 | I187: 3.4e-06 | J187: 5.7e-06 | K187: 0 | L187: 0 | M187: 9.1e-06 | N187: 0.75 | O187: 5 | P187: 2 | Q187: 4 | R187: 2 | S187: 32500 | T187: 6.9 | U187: 11,250 deflected QBR hours × $150/hour × 0.90 × 0.75 = $3.4M | V187: 7% retention rate improvement × $45M revenue × 0.95 × 0.75 = $5.7M | W187: N/A | X187: N/A | Y187: Customer Success Manager validates performance insights and recommendation priorities before custome | Z187: =I187*'Dynamic Analysis Dashboard'!$B$8*'Dynamic Analysis Dashboard'!$B$9*'Dynamic Analysis Dashboard'!$B$21 -> 2.295e-06 | AA187: =J187*'Dynamic Analysis Dashboard'!$B$8*'Dynamic Analysis Dashboard'!$B$9*'Dynamic Analysis Dashboard'!$B$21 -> 3.8475e-06 | AB187: =K187*'Dynamic Analysis Dashboard'!$B$10*'Dynamic Analysis Dashboard'!$B$9*'Dynamic Analysis Dashboard'!$B$21 -> 0 | AC187: =L187*'Dynamic Analysis Dashboard'!$B$11*'Dynamic Analysis Dashboard'!$B$9*'Dynamic Analysis Dashboard'!$B$21 -> 0 | AD187: =SUM(Z187:AC187) -> 6.1425e-06 | AE187: =AD187*N187 -> 4.606875e-06
A188: EZ Texting | B188: UC-03 | C188: Carrier Compliance Intelligence Platform | D188: Product Management | E188: Compliance | G188: Medium | H188: Q3 | I188: 2.7e-06 | J188: 0 | K188: 1.6e-06 | L188: 0 | M188: 4.3e-06 | N188: 0.7 | O188: 9 | P188: 4 | Q188: 2 | R188: 4 | S188: 5610 | T188: 1.2 | U188: 14,500 deflected compliance monitoring hours × $185/hour × 0.90 × 0.75 = $2.7M | V188: N/A | W188: 75% reduction × $180K annual penalties × 12-year horizon × 0.80 × 0.75 = $1.6M | X188: N/A | Y188: Product Manager reviews AI-generated impact assessment and feature recommendations before roadmap pr | Z188: =I188*'Dynamic Analysis Dashboard'!$B$8*'Dynamic Analysis Dashboard'!$B$9*'Dynamic Analysis Dashboard'!$B$21 -> 1.8225e-06 | AA188: =J188*'Dynamic Analysis Dashboard'!$B$8*'Dynamic Analysis Dashboard'!$B$9*'Dynamic Analysis Dashboard'!$B$21 -> 0 | AB188: =K188*'Dynamic Analysis Dashboard'!$B$10*'Dynamic Analysis Dashboard'!$B$9*'Dynamic Analysis Dashboard'!$B$21 -> 9.6e-07 | AC188: =L188*'Dynamic Analysis Dashboard'!$B$11*'Dynamic Analysis Dashboard'!$B$9*'Dynamic Analysis Dashboard'!$B$21 -> 0 | AD188: =SUM(Z188:AC188) -> 2.7825e-06 | AE188: =AD188*N188 -> 1.94775e-06
A189: EZ Texting | B189: UC-05 | C189: Intelligent Sales Research Assistant | D189: Sales | E189: Lead Qualification | F189: Research & Information Retrieval, Data Analysis, Content Creation | G189: Critical | H189: Q1 | I189: 1.9e-06 | J189: 6.8e-06 | K189: 0 | L189: 0 | M189: 8.7e-06 | N189: 0.75 | O189: 6 | P189: 3 | Q189: 2 | R189: 3 | S189: 9240 | T189: 2 | U189: 7,200 deflected research hours × $150/hour × 0.90 × 0.75 = $1.9M | V189: 9% conversion rate improvement × 18% baseline conversion × $45M revenue × 1.35 growth multiplier × 0 | W189: N/A | X189: N/A | Y189: Sales representative reviews AI-generated prospect profile and validates recommended use cases again | Z189: =I189*'Dynamic Analysis Dashboard'!$B$8*'Dynamic Analysis Dashboard'!$B$9*'Dynamic Analysis Dashboard'!$B$21 -> 1.2825e-06 | AA189: =J189*'Dynamic Analysis Dashboard'!$B$8*'Dynamic Analysis Dashboard'!$B$9*'Dynamic Analysis Dashboard'!$B$21 -> 4.59e-06 | AB189: =K189*'Dynamic Analysis Dashboard'!$B$10*'Dynamic Analysis Dashboard'!$B$9*'Dynamic Analysis Dashboard'!$B$21 -> 0 | AC189: =L189*'Dynamic Analysis Dashboard'!$B$11*'Dynamic Analysis Dashboard'!$B$9*'Dynamic Analysis Dashboard'!$B$21 -> 0 | AD189: =SUM(Z189:AC189) -> 5.8725e-06 | AE189: =AD189*N189 -> 4.404375e-06
A190: EZ Texting | B190: UC-08 | C190: Automated Knowledge Base Maintenance | D190: Customer Support | E190: Documentation | F190: Data Analysis, Content Creation | G190: Medium | H190: Q4 | I190: 0.8 | J190: 0 | K190: 0.9 | L190: 0 | M190: 1.7e-06 | N190: 0.75 | O190: 4 | P190: 2 | Q190: 4 | R190: 2 | S190: 2320 | T190: 0.5 | U190: 3,600 deflected documentation hours × $125/hour × 0.90 × 0.75 = $800K | V190: N/A | W190: 40% reduction × $200K annual customer confusion cost × 8-year horizon × 0.80 × 0.75 = $900K | X190: N/A | Y190: Technical writer reviews AI-generated article updates for technical accuracy and brand voice consist | Z190: =I190*'Dynamic Analysis Dashboard'!$B$8*'Dynamic Analysis Dashboard'!$B$9*'Dynamic Analysis Dashboard'!$B$21 -> 0.54 | AA190: =J190*'Dynamic Analysis Dashboard'!$B$8*'Dynamic Analysis Dashboard'!$B$9*'Dynamic Analysis Dashboard'!$B$21 -> 0 | AB190: =K190*'Dynamic Analysis Dashboard'!$B$10*'Dynamic Analysis Dashboard'!$B$9*'Dynamic Analysis Dashboard'!$B$21 -> 0.54 | AC190: =L190*'Dynamic Analysis Dashboard'!$B$11*'Dynamic Analysis Dashboard'!$B$9*'Dynamic Analysis Dashboard'!$B$21 -> 0 | AD190: =SUM(Z190:AC190) -> 1.08 | AE190: =AD190*N190 -> 0.81
A191: EZ Texting | B191: UC-10 | C191: API Documentation Automation | D191: Engineering | E191: API Documentation | F191: Coding Assistance, Content Creation | G191: Medium | H191: Q4 | I191: 1.2e-06 | J191: 1.8e-06 | K191: 0 | L191: 0 | M191: 3e-06 | N191: 0.75 | O191: 5 | P191: 3 | Q191: 3 | R191: 3 | S191: 1440 | T191: 0.3 | U191: 4,200 deflected documentation hours × $185/hour × 0.90 × 0.75 = $1.2M | V191: 28% documentation coverage improvement × 5% developer adoption impact × $45M revenue × 1.35 growth m | W191: N/A | X191: N/A | Y191: Senior engineer reviews generated documentation for technical accuracy and validates code examples e | Z191: =I191*'Dynamic Analysis Dashboard'!$B$8*'Dynamic Analysis Dashboard'!$B$9*'Dynamic Analysis Dashboard'!$B$21 -> 8.1e-07 | AA191: =J191*'Dynamic Analysis Dashboard'!$B$8*'Dynamic Analysis Dashboard'!$B$9*'Dynamic Analysis Dashboard'!$B$21 -> 1.215e-06 | AB191: =K191*'Dynamic Analysis Dashboard'!$B$10*'Dynamic Analysis Dashboard'!$B$9*'Dynamic Analysis Dashboard'!$B$21 -> 0 | AC191: =L191*'Dynamic Analysis Dashboard'!$B$11*'Dynamic Analysis Dashboard'!$B$9*'Dynamic Analysis Dashboard'!$B$21 -> 0 | AD191: =SUM(Z191:AC191) -> 2.025e-06 | AE191: =AD191*N191 -> 1.51875e-06
A192: Hero Digital | B192: UC-01 | C192: Intelligent Proposal Assembly System | D192: Business Development | E192: Proposal Development | F192: Research & Information Retrieval, Content Creation, Workflow Automation | G192: High | H192: Q2 | I192: 3.5e-06 | J192: 1.9e-06 | K192: 0 | L192: 0.8 | M192: 6.2e-06 | N192: 0.8 | O192: 9 | P192: 4 | Q192: 3 | R192: 4 | S192: 3600 | T192: 2592 | U192: 14,200 hours × $185/hr × 0.90 × 0.75 = $1.8M proposal time + 8,400 hours × $285/hr × 0.90 × 0.75 = $ | V192: 120 incremental pursuits × $375K avg value × 6% win rate lift × 0.95 × 0.75 = $1.9M | W192: No material risk reduction | X192: 12 days acceleration × $123K daily revenue × 0.85 × 0.75 = $940K rounded to $800K | Y192: Senior strategist reviews and approves all AI-assembled proposal sections, customizes strategic posi | Z192: =I192*'Dynamic Analysis Dashboard'!$B$8*'Dynamic Analysis Dashboard'!$B$9*'Dynamic Analysis Dashboard'!$B$21 -> 2.3625e-06 | AA192: =J192*'Dynamic Analysis Dashboard'!$B$8*'Dynamic Analysis Dashboard'!$B$9*'Dynamic Analysis Dashboard'!$B$21 -> 1.2825e-06 | AB192: =K192*'Dynamic Analysis Dashboard'!$B$10*'Dynamic Analysis Dashboard'!$B$9*'Dynamic Analysis Dashboard'!$B$21 -> 0 | AC192: =L192*'Dynamic Analysis Dashboard'!$B$11*'Dynamic Analysis Dashboard'!$B$9*'Dynamic Analysis Dashboard'!$B$21 -> 0.51 | AD192: =SUM(Z192:AC192) -> 0.51000365 | AE192: =AD192*N192 -> 0.40800292
A193: Hero Digital | B193: UC-03 | C193: Adaptive Content Brief Generator | D193: Content Production | E193: Content Briefing | F193: Research & Information Retrieval, Content Creation | G193: High | H193: Q2 | I193: 1.8e-06 | J193: 0 | K193: 1.3e-06 | L193: 0 | M193: 3.1e-06 | N193: 0.75 | O193: 6 | P193: 3 | Q193: 3 | R193: 3 | S193: 3360 | T193: 2419.2 | U193: 18 hours × 280 projects × $185/hr × 0.90 × 0.75 = $1.7M rounded to $1.8M | V193: No direct revenue impact | W193: 28% reduction in rework × $6.2M annual rework cost × 0.80 × 0.75 = $1.3M | X193: No material cash flow impact | Y193: Content strategist reviews AI-generated brief for creative accuracy, validates brand guideline compl | Z193: =I193*'Dynamic Analysis Dashboard'!$B$8*'Dynamic Analysis Dashboard'!$B$9*'Dynamic Analysis Dashboard'!$B$21 -> 1.215e-06 | AA193: =J193*'Dynamic Analysis Dashboard'!$B$8*'Dynamic Analysis Dashboard'!$B$9*'Dynamic Analysis Dashboard'!$B$21 -> 0 | AB193: =K193*'Dynamic Analysis Dashboard'!$B$10*'Dynamic Analysis Dashboard'!$B$9*'Dynamic Analysis Dashboard'!$B$21 -> 7.8e-07 | AC193: =L193*'Dynamic Analysis Dashboard'!$B$11*'Dynamic Analysis Dashboard'!$B$9*'Dynamic Analysis Dashboard'!$B$21 -> 0 | AD193: =SUM(Z193:AC193) -> 1.995e-06 | AE193: =AD193*N193 -> 1.49625e-06
A194: Hero Digital | B194: UC-04 | C194: Multi-Stage Content Quality Assistant | D194: Content Production | E194: Quality Review | F194: Data Analysis, Content Creation | G194: High | H194: Q2 | I194: 2.4e-06 | J194: 0 | K194: 0.9 | L194: 0 | M194: 3.3e-06 | N194: 0.8 | O194: 7 | P194: 3 | Q194: 4 | R194: 3 | S194: 5040 | T194: 6048 | U194: 12 hours × 280 projects × $125/hr × 0.90 × 0.75 = $2.3M rounded to $2.4M | V194: No direct revenue impact | W194: 16% reduction in client dissatisfaction × $7.4M client retention risk × 0.80 × 0.75 = $890K rounded | X194: No material cash flow impact | Y194: Senior content reviewer validates AI quality findings, makes final judgment on creative execution an | Z194: =I194*'Dynamic Analysis Dashboard'!$B$8*'Dynamic Analysis Dashboard'!$B$9*'Dynamic Analysis Dashboard'!$B$21 -> 1.62e-06 | AA194: =J194*'Dynamic Analysis Dashboard'!$B$8*'Dynamic Analysis Dashboard'!$B$9*'Dynamic Analysis Dashboard'!$B$21 -> 0 | AB194: =K194*'Dynamic Analysis Dashboard'!$B$10*'Dynamic Analysis Dashboard'!$B$9*'Dynamic Analysis Dashboard'!$B$21 -> 0.54 | AC194: =L194*'Dynamic Analysis Dashboard'!$B$11*'Dynamic Analysis Dashboard'!$B$9*'Dynamic Analysis Dashboard'!$B$21 -> 0 | AD194: =SUM(Z194:AC194) -> 0.54000162 | AE194: =AD194*N194 -> 0.4320013
A195: Hero Digital | B195: UC-05 | C195: Intelligent Pitch Deck Composer | D195: Business Development | E195: Pitch Preparation | F195: Research & Information Retrieval, Content Creation, Data Analysis | G195: High | H195: Q1 | I195: 3.2e-06 | J195: 1.6e-06 | K195: 0 | L195: 0 | M195: 4.8e-06 | N195: 0.75 | O195: 6 | P195: 3 | Q195: 3 | R195: 3 | S195: 2880 | T195: 2073.6 | U195: 24 hours × 180 pitches × $285/hr × 0.90 × 0.75 = $3.1M rounded to $3.2M | V195: 90 incremental pitches × $375K avg value × 5% win rate lift × 0.95 × 0.75 = $1.5M rounded to $1.6M | W195: No material risk reduction | X195: No material cash flow impact | Y195: Business development director reviews AI-composed pitch deck, customizes strategic positioning based | Z195: =I195*'Dynamic Analysis Dashboard'!$B$8*'Dynamic Analysis Dashboard'!$B$9*'Dynamic Analysis Dashboard'!$B$21 -> 2.16e-06 | AA195: =J195*'Dynamic Analysis Dashboard'!$B$8*'Dynamic Analysis Dashboard'!$B$9*'Dynamic Analysis Dashboard'!$B$21 -> 1.08e-06 | AB195: =K195*'Dynamic Analysis Dashboard'!$B$10*'Dynamic Analysis Dashboard'!$B$9*'Dynamic Analysis Dashboard'!$B$21 -> 0 | AC195: =L195*'Dynamic Analysis Dashboard'!$B$11*'Dynamic Analysis Dashboard'!$B$9*'Dynamic Analysis Dashboard'!$B$21 -> 0 | AD195: =SUM(Z195:AC195) -> 3.24e-06 | AE195: =AD195*N195 -> 2.43e-06
A196: Hero Digital | B196: UC-07 | C196: Project Onboarding Packet Assembler | D196: Client Management | E196: Onboarding Documentation | F196: Research & Information Retrieval, Content Creation, Workflow Automation | G196: High | H196: Q1 | I196: 0.9 | J196: 0 | K196: 0 | L196: 1.4e-06 | M196: 2.3e-06 | N196: 0.8 | O196: 5 | P196: 2 | Q196: 4 | R196: 2 | S196: 1400 | T196: 1008 | U196: 8 hours × 140 projects × $125/hr × 0.90 × 0.75 = $850K rounded to $900K | V196: No direct revenue impact | W196: No material risk reduction | X196: 11 days × $123K daily revenue × 0.85 × 0.75 = $1.3M rounded to $1.4M | Y196: Account manager reviews AI-assembled onboarding packet, validates project-specific details, customiz | Z196: =I196*'Dynamic Analysis Dashboard'!$B$8*'Dynamic Analysis Dashboard'!$B$9*'Dynamic Analysis Dashboard'!$B$21 -> 0.6075 | AA196: =J196*'Dynamic Analysis Dashboard'!$B$8*'Dynamic Analysis Dashboard'!$B$9*'Dynamic Analysis Dashboard'!$B$21 -> 0 | AB196: =K196*'Dynamic Analysis Dashboard'!$B$10*'Dynamic Analysis Dashboard'!$B$9*'Dynamic Analysis Dashboard'!$B$21 -> 0 | AC196: =L196*'Dynamic Analysis Dashboard'!$B$11*'Dynamic Analysis Dashboard'!$B$9*'Dynamic Analysis Dashboard'!$B$21 -> 8.925e-07 | AD196: =SUM(Z196:AC196) -> 0.60750089 | AE196: =AD196*N196 -> 0.48600071
A197: Hero Digital | B197: UC-10 | C197: AI-Enhanced Invoice Narrative System | D197: Finance | E197: Invoicing Operations | F197: Research & Information Retrieval, Content Creation | G197: High | H197: Q1 | I197: 0.7 | J197: 0 | K197: 0 | L197: 1.1e-06 | M197: 1.8e-06 | N197: 0.8 | O197: 4 | P197: 2 | Q197: 4 | R197: 2 | S197: 9240 | T197: 6652.8 | U197: 2.5 hours × 140 clients × 12 months × $125/hr × 0.90 × 0.75 = $660K rounded to $700K | V197: No direct revenue impact | W197: No material risk reduction | X197: 7 days × $123K daily revenue × 0.85 × 0.75 = $1.0M rounded to $1.1M | Y197: Finance manager validates AI-generated invoice narratives against actual work performed, adjusts lan | Z197: =I197*'Dynamic Analysis Dashboard'!$B$8*'Dynamic Analysis Dashboard'!$B$9*'Dynamic Analysis Dashboard'!$B$21 -> 0.4725 | AA197: =J197*'Dynamic Analysis Dashboard'!$B$8*'Dynamic Analysis Dashboard'!$B$9*'Dynamic Analysis Dashboard'!$B$21 -> 0 | AB197: =K197*'Dynamic Analysis Dashboard'!$B$10*'Dynamic Analysis Dashboard'!$B$9*'Dynamic Analysis Dashboard'!$B$21 -> 0 | AC197: =L197*'Dynamic Analysis Dashboard'!$B$11*'Dynamic Analysis Dashboard'!$B$9*'Dynamic Analysis Dashboard'!$B$21 -> 7.0125e-07 | AD197: =SUM(Z197:AC197) -> 0.4725007 | AE197: =AD197*N197 -> 0.37800056
A198: Hero Digital | B198: UC-02 | C198: AI-Powered Research Synthesis Engine | D198: Strategy Consulting | E198: Market Research | G198: Medium | H198: Q3 | I198: 2.5e-06 | J198: 2.8e-06 | K198: 0 | L198: 0 | M198: 5.3e-06 | N198: 0.75 | O198: 12 | P198: 4 | Q198: 2 | R198: 4 | S198: 8400 | T198: 18144 | U198: 32 hours × 140 engagements × $285/hr × 0.90 × 0.75 = $2.4M rounded to $2.5M | V198: 32 hours saved × 140 engagements × $285/hr converted to billable × 0.95 × 0.75 = $900K + strategic d | W198: No material risk reduction | X198: No material cash flow impact | Y198: Strategy consultant validates all synthesized research findings, verifies source accuracy, adds indu | Z198: =I198*'Dynamic Analysis Dashboard'!$B$8*'Dynamic Analysis Dashboard'!$B$9*'Dynamic Analysis Dashboard'!$B$21 -> 1.6875e-06 | AA198: =J198*'Dynamic Analysis Dashboard'!$B$8*'Dynamic Analysis Dashboard'!$B$9*'Dynamic Analysis Dashboard'!$B$21 -> 1.89e-06 | AB198: =K198*'Dynamic Analysis Dashboard'!$B$10*'Dynamic Analysis Dashboard'!$B$9*'Dynamic Analysis Dashboard'!$B$21 -> 0 | AC198: =L198*'Dynamic Analysis Dashboard'!$B$11*'Dynamic Analysis Dashboard'!$B$9*'Dynamic Analysis Dashboard'!$B$21 -> 0 | AD198: =SUM(Z198:AC198) -> 3.5775e-06 | AE198: =AD198*N198 -> 2.683125e-06
A199: Hero Digital | B199: UC-06 | C199: Automated Competitive Intelligence Monitor | D199: Strategy Consulting | E199: Competitive Analysis | F199: Research & Information Retrieval, Data Analysis, Workflow Automation | G199: Medium | H199: Q4 | I199: 1.4e-06 | J199: 1.2e-06 | K199: 0 | L199: 0 | M199: 2.6e-06 | N199: 0.7 | O199: 10 | P199: 4 | Q199: 2 | R199: 4 | S199: 18480 | T199: 16934.4 | U199: 8 hours × 140 engagements × $185/hr × 0.90 × 0.75 = $1.3M rounded to $1.4M | V199: Competitive insights enabling 3% win rate lift × 45 pursuits/qtr × 4 qtrs × $375K avg × 0.95 × 0.75 | W199: No material risk reduction | X199: No material cash flow impact | Y199: Strategy consultant validates AI-identified competitive insights, assesses strategic significance fo | Z199: =I199*'Dynamic Analysis Dashboard'!$B$8*'Dynamic Analysis Dashboard'!$B$9*'Dynamic Analysis Dashboard'!$B$21 -> 9.45e-07 | AA199: =J199*'Dynamic Analysis Dashboard'!$B$8*'Dynamic Analysis Dashboard'!$B$9*'Dynamic Analysis Dashboard'!$B$21 -> 8.1e-07 | AB199: =K199*'Dynamic Analysis Dashboard'!$B$10*'Dynamic Analysis Dashboard'!$B$9*'Dynamic Analysis Dashboard'!$B$21 -> 0 | AC199: =L199*'Dynamic Analysis Dashboard'!$B$11*'Dynamic Analysis Dashboard'!$B$9*'Dynamic Analysis Dashboard'!$B$21 -> 0 | AD199: =SUM(Z199:AC199) -> 1.755e-06 | AE199: =AD199*N199 -> 1.2285e-06
A200: Hero Digital | B200: UC-08 | C200: Intelligent Status Report Generator | D200: Client Management | E200: Status Reporting | F200: Data Analysis, Content Creation, Workflow Automation | G200: Medium | H200: Q3 | I200: 1.6e-06 | J200: 0 | K200: 0.6 | L200: 0 | M200: 2.2e-06 | N200: 0.8 | O200: 6 | P200: 3 | Q200: 4 | R200: 3 | S200: 19600 | T200: 14112 | U200: 3 hours × 140 projects × 52 weeks × $125/hr × 0.90 × 0.75 = $1.5M rounded to $1.6M | V200: No direct revenue impact | W200: 12% improvement in client satisfaction × $6.8M retention risk × 0.80 × 0.75 = $650K rounded to $600K | X200: No material cash flow impact | Y200: Account manager validates AI-generated status narrative, adds strategic context for delays or risks, | Z200: =I200*'Dynamic Analysis Dashboard'!$B$8*'Dynamic Analysis Dashboard'!$B$9*'Dynamic Analysis Dashboard'!$B$21 -> 1.08e-06 | AA200: =J200*'Dynamic Analysis Dashboard'!$B$8*'Dynamic Analysis Dashboard'!$B$9*'Dynamic Analysis Dashboard'!$B$21 -> 0 | AB200: =K200*'Dynamic Analysis Dashboard'!$B$10*'Dynamic Analysis Dashboard'!$B$9*'Dynamic Analysis Dashboard'!$B$21 -> 0.36 | AC200: =L200*'Dynamic Analysis Dashboard'!$B$11*'Dynamic Analysis Dashboard'!$B$9*'Dynamic Analysis Dashboard'!$B$21 -> 0 | AD200: =SUM(Z200:AC200) -> 0.36000108 | AE200: =AD200*N200 -> 0.28800086
A201: Hero Digital | B201: UC-09 | C201: Semantic Knowledge Retrieval System | D201: Operations | E201: Knowledge Management | F201: Research & Information Retrieval, Data Analysis | G201: Medium | H201: Q4 | I201: 2.1e-06 | J201: 0 | K201: 0 | L201: 0 | M201: 2.1e-06 | N201: 0.85 | O201: 10 | P201: 4 | Q201: 2 | R201: 4 | S201: 49280 | T201: 35481.6 | U201: 12 minutes × 280 consultants × 220 workdays × $185/hr × 0.90 × 0.75 = $2.0M rounded to $2.1M | V201: No direct revenue impact | W201: No material risk reduction | X201: No material cash flow impact | Y201: Consultant validates relevance of AI-retrieved prior work for current engagement context, adapts reu | Z201: =I201*'Dynamic Analysis Dashboard'!$B$8*'Dynamic Analysis Dashboard'!$B$9*'Dynamic Analysis Dashboard'!$B$21 -> 1.4175e-06 | AA201: =J201*'Dynamic Analysis Dashboard'!$B$8*'Dynamic Analysis Dashboard'!$B$9*'Dynamic Analysis Dashboard'!$B$21 -> 0 | AB201: =K201*'Dynamic Analysis Dashboard'!$B$10*'Dynamic Analysis Dashboard'!$B$9*'Dynamic Analysis Dashboard'!$B$21 -> 0 | AC201: =L201*'Dynamic Analysis Dashboard'!$B$11*'Dynamic Analysis Dashboard'!$B$9*'Dynamic Analysis Dashboard'!$B$21 -> 0 | AD201: =SUM(Z201:AC201) -> 1.4175e-06 | AE201: =AD201*N201 -> 1.204875e-06
A202: Huge | B202: UC-01 | C202: Pitch Intelligence Assistant | D202: Business Development | E202: Pitch Preparation | F202: Research & Information Retrieval, Content Creation | G202: High | H202: Q1 | I202: 4.4e-06 | J202: 3.8e-06 | K202: 0 | L202: 0 | M202: 8.2e-06 | N202: 0.75 | O202: 9 | P202: 3 | Q202: 2 | R202: 3 | S202: 10260 | T202: 46.8 | U202: No cost impact | V202: 7% win rate lift × $190M annual pitch pipeline × 0.95 × 0.75 = $9.4M × 0.40 adoption = $3.8M | W202: N/A | X202: N/A | Y202: Strategy directors review and validate all market insights before inclusion in client-facing pitch m | Z202: =I202*'Dynamic Analysis Dashboard'!$B$8*'Dynamic Analysis Dashboard'!$B$9*'Dynamic Analysis Dashboard'!$B$21 -> 2.97e-06 | AA202: =J202*'Dynamic Analysis Dashboard'!$B$8*'Dynamic Analysis Dashboard'!$B$9*'Dynamic Analysis Dashboard'!$B$21 -> 2.565e-06 | AB202: =K202*'Dynamic Analysis Dashboard'!$B$10*'Dynamic Analysis Dashboard'!$B$9*'Dynamic Analysis Dashboard'!$B$21 -> 0 | AC202: =L202*'Dynamic Analysis Dashboard'!$B$11*'Dynamic Analysis Dashboard'!$B$9*'Dynamic Analysis Dashboard'!$B$21 -> 0 | AD202: =SUM(Z202:AC202) -> 5.535e-06 | AE202: =AD202*N202 -> 4.15125e-06
A203: Huge | B203: UC-06 | C203: Knowledge Discovery Engine | D203: Knowledge Management | E203: Case Study Retrieval | F203: Research & Information Retrieval, Conversational Interfaces | G203: High | H203: Q1 | I203: 2.2e-06 | J203: 0 | K203: 0 | L203: 0 | M203: 2.2e-06 | N203: 0.85 | O203: 6 | P203: 2 | Q203: 2 | R203: 2 | S203: 19740 | T203: 32.76 | U203: No cost impact | V203: N/A | W203: N/A | X203: N/A | Y203: Account strategists review retrieved case studies for relevance to current client context and approv | Z203: =I203*'Dynamic Analysis Dashboard'!$B$8*'Dynamic Analysis Dashboard'!$B$9*'Dynamic Analysis Dashboard'!$B$21 -> 1.485e-06 | AA203: =J203*'Dynamic Analysis Dashboard'!$B$8*'Dynamic Analysis Dashboard'!$B$9*'Dynamic Analysis Dashboard'!$B$21 -> 0 | AB203: =K203*'Dynamic Analysis Dashboard'!$B$10*'Dynamic Analysis Dashboard'!$B$9*'Dynamic Analysis Dashboard'!$B$21 -> 0 | AC203: =L203*'Dynamic Analysis Dashboard'!$B$11*'Dynamic Analysis Dashboard'!$B$9*'Dynamic Analysis Dashboard'!$B$21 -> 0 | AD203: =SUM(Z203:AC203) -> 1.485e-06 | AE203: =AD203*N203 -> 1.26225e-06
A204: Huge | B204: UC-08 | C204: Code Quality Assessment System | D204: Technology Delivery | E204: Code Review | F204: Coding Assistance, Data Analysis | G204: High | H204: Q1 | I204: 1.5e-06 | J204: 0 | K204: 1.2e-06 | L204: 0 | M204: 2.7e-06 | N204: 0.75 | O204: 6 | P204: 2 | Q204: 4 | R204: 2 | S204: 11780 | T204: 59.76 | U204: No cost impact | V204: N/A | W204: 35% defect reduction × $4.8M post-launch remediation × 0.80 × 0.75 = $1.0M rounded to $1.2M | X204: N/A | Y204: Technical leads review all critical and high-severity findings for business impact assessment before | Z204: =I204*'Dynamic Analysis Dashboard'!$B$8*'Dynamic Analysis Dashboard'!$B$9*'Dynamic Analysis Dashboard'!$B$21 -> 1.0125e-06 | AA204: =J204*'Dynamic Analysis Dashboard'!$B$8*'Dynamic Analysis Dashboard'!$B$9*'Dynamic Analysis Dashboard'!$B$21 -> 0 | AB204: =K204*'Dynamic Analysis Dashboard'!$B$10*'Dynamic Analysis Dashboard'!$B$9*'Dynamic Analysis Dashboard'!$B$21 -> 7.2e-07 | AC204: =L204*'Dynamic Analysis Dashboard'!$B$11*'Dynamic Analysis Dashboard'!$B$9*'Dynamic Analysis Dashboard'!$B$21 -> 0 | AD204: =SUM(Z204:AC204) -> 1.7325e-06 | AE204: =AD204*N204 -> 1.299375e-06
A205: Huge | B205: UC-02 | C205: Creative Asset Versioning Engine | D205: Creative Services | E205: Asset Production | F205: Content Creation, Workflow Automation | G205: Medium | H205: Q3 | I205: 3.4e-06 | J205: 0 | K205: 0 | L205: 1.3e-06 | M205: 4.7e-06 | N205: 0.8 | O205: 12 | P205: 3 | Q205: 3 | R205: 4 | S205: 26400 | T205: 36 | U205: No cost impact | V205: N/A | W205: N/A | X205: 7 days campaign acceleration × $52K daily revenue × 30 campaigns × 0.85 × 0.75 = $7.0M × 0.19 margin | Y205: Art directors review randomized samples of 15% of generated variants for brand compliance and qualit | Z205: =I205*'Dynamic Analysis Dashboard'!$B$8*'Dynamic Analysis Dashboard'!$B$9*'Dynamic Analysis Dashboard'!$B$21 -> 2.295e-06 | AA205: =J205*'Dynamic Analysis Dashboard'!$B$8*'Dynamic Analysis Dashboard'!$B$9*'Dynamic Analysis Dashboard'!$B$21 -> 0 | AB205: =K205*'Dynamic Analysis Dashboard'!$B$10*'Dynamic Analysis Dashboard'!$B$9*'Dynamic Analysis Dashboard'!$B$21 -> 0 | AC205: =L205*'Dynamic Analysis Dashboard'!$B$11*'Dynamic Analysis Dashboard'!$B$9*'Dynamic Analysis Dashboard'!$B$21 -> 8.2875e-07 | AD205: =SUM(Z205:AC205) -> 3.12375e-06 | AE205: =AD205*N205 -> 2.499e-06
A206: Huge | B206: UC-03 | C206: Scope Change Documentation System | D206: Project Management | E206: Scope Documentation | G206: Medium | H206: Q3 | I206: 2.8e-06 | J206: 0 | K206: 1.1e-06 | L206: 1.7e-06 | M206: 5.6e-06 | N206: 0.7 | O206: 12 | P206: 4 | Q206: 2 | R206: 4 | S206: 13600 | T206: 81.6 | U206: No cost impact | V206: N/A | W206: 12% reduction × $12M scope dispute exposure × 0.80 × 0.75 = $0.9M rounded to $1.1M | X206: 7 days change order acceleration × $41K daily revenue × 85 changes × 0.85 × 0.75 = $1.7M | Y206: Project managers review all AI-flagged scope changes for accuracy and business impact before initiat | Z206: =I206*'Dynamic Analysis Dashboard'!$B$8*'Dynamic Analysis Dashboard'!$B$9*'Dynamic Analysis Dashboard'!$B$21 -> 1.89e-06 | AA206: =J206*'Dynamic Analysis Dashboard'!$B$8*'Dynamic Analysis Dashboard'!$B$9*'Dynamic Analysis Dashboard'!$B$21 -> 0 | AB206: =K206*'Dynamic Analysis Dashboard'!$B$10*'Dynamic Analysis Dashboard'!$B$9*'Dynamic Analysis Dashboard'!$B$21 -> 6.6e-07 | AC206: =L206*'Dynamic Analysis Dashboard'!$B$11*'Dynamic Analysis Dashboard'!$B$9*'Dynamic Analysis Dashboard'!$B$21 -> 1.08375e-06 | AD206: =SUM(Z206:AC206) -> 3.63375e-06 | AE206: =AD206*N206 -> 2.543625e-06
A207: Huge | B207: UC-04 | C207: Consumer Insights Synthesis Platform | D207: Strategy & Planning | E207: Consumer Insights | F207: Research & Information Retrieval, Data Analysis | G207: Medium | H207: Q2 | I207: 4.1e-06 | J207: 0 | K207: 0 | L207: 0 | M207: 4.1e-06 | N207: 0.75 | O207: 9 | P207: 3 | Q207: 2 | R207: 3 | S207: 11280 | T207: 51.84 | U207: No cost impact | V207: N/A | W207: N/A | X207: N/A | Y207: Strategy leads validate statistical significance of identified patterns and assess cultural context | Z207: =I207*'Dynamic Analysis Dashboard'!$B$8*'Dynamic Analysis Dashboard'!$B$9*'Dynamic Analysis Dashboard'!$B$21 -> 2.7675e-06 | AA207: =J207*'Dynamic Analysis Dashboard'!$B$8*'Dynamic Analysis Dashboard'!$B$9*'Dynamic Analysis Dashboard'!$B$21 -> 0 | AB207: =K207*'Dynamic Analysis Dashboard'!$B$10*'Dynamic Analysis Dashboard'!$B$9*'Dynamic Analysis Dashboard'!$B$21 -> 0 | AC207: =L207*'Dynamic Analysis Dashboard'!$B$11*'Dynamic Analysis Dashboard'!$B$9*'Dynamic Analysis Dashboard'!$B$21 -> 0 | AD207: =SUM(Z207:AC207) -> 2.7675e-06 | AE207: =AD207*N207 -> 2.075625e-06
A208: Huge | B208: UC-05 | C208: Brand Compliance Guardian | D208: Creative Services | E208: Brand Compliance | F208: Data Analysis, Conversational Interfaces | G208: Medium | H208: Q2 | I208: 2.5e-06 | J208: 0 | K208: 8e-07 | L208: 0 | M208: 3.3e-06 | N208: 0.8 | O208: 6 | P208: 3 | Q208: 3 | R208: 3 | S208: 14400 | T208: 37.8 | U208: No cost impact | V208: N/A | W208: 18% reduction × $7M brand compliance incidents × 0.80 × 0.75 = $0.8M | X208: N/A | Y208: Creative directors review all flagged violations for severity assessment and make final determinatio | Z208: =I208*'Dynamic Analysis Dashboard'!$B$8*'Dynamic Analysis Dashboard'!$B$9*'Dynamic Analysis Dashboard'!$B$21 -> 1.6875e-06 | AA208: =J208*'Dynamic Analysis Dashboard'!$B$8*'Dynamic Analysis Dashboard'!$B$9*'Dynamic Analysis Dashboard'!$B$21 -> 0 | AB208: =K208*'Dynamic Analysis Dashboard'!$B$10*'Dynamic Analysis Dashboard'!$B$9*'Dynamic Analysis Dashboard'!$B$21 -> 4.8e-07 | AC208: =L208*'Dynamic Analysis Dashboard'!$B$11*'Dynamic Analysis Dashboard'!$B$9*'Dynamic Analysis Dashboard'!$B$21 -> 0 | AD208: =SUM(Z208:AC208) -> 2.1675e-06 | AE208: =AD208*N208 -> 1.734e-06
A209: Huge | B209: UC-07 | C209: Project Margin Forecasting Model | D209: Project Management | E209: Budget Forecasting | F209: Data Analysis, Workflow Automation | G209: Medium | H209: Q3 | I209: 1.8e-06 | J209: 0 | K209: 1.4e-06 | L209: 0 | M209: 3.2e-06 | N209: 0.7 | O209: 9 | P209: 3 | Q209: 3 | R209: 3 | S209: 7820 | T209: 43.92 | U209: No cost impact | V209: N/A | W209: 20% reduction × $9.3M margin variance exposure × 0.80 × 0.75 = $1.1M rounded to $1.4M | X209: N/A | Y209: Finance business partners review margin predictions for reasonableness and validate recommended inte | Z209: =I209*'Dynamic Analysis Dashboard'!$B$8*'Dynamic Analysis Dashboard'!$B$9*'Dynamic Analysis Dashboard'!$B$21 -> 1.215e-06 | AA209: =J209*'Dynamic Analysis Dashboard'!$B$8*'Dynamic Analysis Dashboard'!$B$9*'Dynamic Analysis Dashboard'!$B$21 -> 0 | AB209: =K209*'Dynamic Analysis Dashboard'!$B$10*'Dynamic Analysis Dashboard'!$B$9*'Dynamic Analysis Dashboard'!$B$21 -> 8.4e-07 | AC209: =L209*'Dynamic Analysis Dashboard'!$B$11*'Dynamic Analysis Dashboard'!$B$9*'Dynamic Analysis Dashboard'!$B$21 -> 0 | AD209: =SUM(Z209:AC209) -> 2.055e-06 | AE209: =AD209*N209 -> 1.4385e-06
A210: Huge | B210: UC-09 | C210: Onboarding Knowledge Assistant | D210: Talent Development | E210: Onboarding | F210: Research & Information Retrieval, Conversational Interfaces, Content Creation | G210: Medium | H210: Q2 | I210: 2.6e-06 | J210: 0 | K210: 0 | L210: 0 | M210: 2.6e-06 | N210: 0.7 | O210: 9 | P210: 2 | Q210: 2 | R210: 2 | S210: 6600 | T210: 30.6 | U210: No cost impact | V210: N/A | W210: N/A | X210: N/A | Y210: Talent development managers review AI-generated learning paths for role appropriateness and monitor | Z210: =I210*'Dynamic Analysis Dashboard'!$B$8*'Dynamic Analysis Dashboard'!$B$9*'Dynamic Analysis Dashboard'!$B$21 -> 1.755e-06 | AA210: =J210*'Dynamic Analysis Dashboard'!$B$8*'Dynamic Analysis Dashboard'!$B$9*'Dynamic Analysis Dashboard'!$B$21 -> 0 | AB210: =K210*'Dynamic Analysis Dashboard'!$B$10*'Dynamic Analysis Dashboard'!$B$9*'Dynamic Analysis Dashboard'!$B$21 -> 0 | AC210: =L210*'Dynamic Analysis Dashboard'!$B$11*'Dynamic Analysis Dashboard'!$B$9*'Dynamic Analysis Dashboard'!$B$21 -> 0 | AD210: =SUM(Z210:AC210) -> 1.755e-06 | AE210: =AD210*N210 -> 1.2285e-06
A211: Huge | B211: UC-10 | C211: Contract Intelligence Platform | D211: Legal & Compliance | E211: Contract Redlining | F211: Research & Information Retrieval, Data Analysis, Content Creation | G211: Medium | H211: Q2 | I211: 9e-07 | J211: 0 | K211: 6e-07 | L211: 1.1e-06 | M211: 2.6e-06 | N211: 0.75 | O211: 6 | P211: 3 | Q211: 3 | R211: 2 | S211: 2688 | T211: 20.736 | U211: No cost impact | V211: N/A | W211: 14% reduction × $6.2M contract dispute exposure × 0.80 × 0.75 = $0.5M rounded to $0.6M | X211: 5 days contract acceleration × $37K daily revenue × 48 new clients × 0.85 × 0.75 = $1.1M | Y211: Legal counsel reviews all AI-suggested contract language before client submission and approves risk | Z211: =I211*'Dynamic Analysis Dashboard'!$B$8*'Dynamic Analysis Dashboard'!$B$9*'Dynamic Analysis Dashboard'!$B$21 -> 6.075e-07 | AA211: =J211*'Dynamic Analysis Dashboard'!$B$8*'Dynamic Analysis Dashboard'!$B$9*'Dynamic Analysis Dashboard'!$B$21 -> 0 | AB211: =K211*'Dynamic Analysis Dashboard'!$B$10*'Dynamic Analysis Dashboard'!$B$9*'Dynamic Analysis Dashboard'!$B$21 -> 3.6e-07 | AC211: =L211*'Dynamic Analysis Dashboard'!$B$11*'Dynamic Analysis Dashboard'!$B$9*'Dynamic Analysis Dashboard'!$B$21 -> 7.0125e-07 | AD211: =SUM(Z211:AC211) -> 1.66875e-06 | AE211: =AD211*N211 -> 1.2515625e-06
A212: Impetus Wellness | B212: UC-01 | C212: Biometric Data Normalization Engine | D212: Clinical Operations | E212: Biometric Data Processing | F212: Data Analysis, Workflow Automation | G212: High | H212: Q1 | I212: 1.7e-05 | J212: 0 | K212: 1.8e-06 | L212: 0 | M212: 1.88e-05 | N212: 0.85 | O212: 9 | P212: 4 | Q212: 3 | R212: 4 | S212: 420000 | T212: 228.6 | U212: 18,500 hours × $125/hour × 75% time reduction × 0.90 × 0.75 = $17.0M | V212: No direct revenue impact | W212: 15% reduction × $15M data quality exposure × 0.80 × 0.75 = $1.8M | X212: No direct cash flow impact | Y212: Clinical quality assurance specialists review and approve all flagged data anomalies and outlier val | Z212: =I212*'Dynamic Analysis Dashboard'!$B$8*'Dynamic Analysis Dashboard'!$B$9*'Dynamic Analysis Dashboard'!$B$21 -> 1.1475e-05 | AA212: =J212*'Dynamic Analysis Dashboard'!$B$8*'Dynamic Analysis Dashboard'!$B$9*'Dynamic Analysis Dashboard'!$B$21 -> 0 | AB212: =K212*'Dynamic Analysis Dashboard'!$B$10*'Dynamic Analysis Dashboard'!$B$9*'Dynamic Analysis Dashboard'!$B$21 -> 1.08e-06 | AC212: =L212*'Dynamic Analysis Dashboard'!$B$11*'Dynamic Analysis Dashboard'!$B$9*'Dynamic Analysis Dashboard'!$B$21 -> 0 | AD212: =SUM(Z212:AC212) -> 1.2555e-05 | AE212: =AD212*N212 -> 1.067175e-05
A213: Impetus Wellness | B213: UC-02 | C213: Real-Time Health Insight Generator | D213: Clinical Operations | E213: Health Risk Assessment | F213: Data Analysis, Content Creation, Research & Information Retrieval | G213: High | H213: Q2 | I213: 0 | J213: 1.21e-05 | K213: 2.7e-06 | L213: 0 | M213: 1.48e-05 | N213: 0.75 | O213: 12 | P213: 4 | Q213: 3 | R213: 4 | S213: 299600 | T213: 611.28 | U213: No direct cost impact | V213: 14 percentage point engagement lift × $180M revenue × 0.48 revenue correlation × 0.95 × 0.75 = $12.1 | W213: 25% reduction × $18M undetected high-risk exposure × 0.80 × 0.75 = $2.7M | X213: No direct cash flow impact | Y213: Licensed health coaches review and approve all clinical recommendations and member-facing health gui | Z213: =I213*'Dynamic Analysis Dashboard'!$B$8*'Dynamic Analysis Dashboard'!$B$9*'Dynamic Analysis Dashboard'!$B$21 -> 0 | AA213: =J213*'Dynamic Analysis Dashboard'!$B$8*'Dynamic Analysis Dashboard'!$B$9*'Dynamic Analysis Dashboard'!$B$21 -> 8.1675e-06 | AB213: =K213*'Dynamic Analysis Dashboard'!$B$10*'Dynamic Analysis Dashboard'!$B$9*'Dynamic Analysis Dashboard'!$B$21 -> 1.62e-06 | AC213: =L213*'Dynamic Analysis Dashboard'!$B$11*'Dynamic Analysis Dashboard'!$B$9*'Dynamic Analysis Dashboard'!$B$21 -> 0 | AD213: =SUM(Z213:AC213) -> 9.7875e-06 | AE213: =AD213*N213 -> 7.340625e-06
A214: Impetus Wellness | B214: UC-04 | C214: Intelligent Member Support Assistant | D214: Customer Support | E214: Contact Center Operations | F214: Conversational Interfaces, Research & Information Retrieval, Workflow Automation | G214: High | H214: Q2 | I214: 7.3e-06 | J214: 0 | K214: 0 | L214: 0 | M214: 7.3e-06 | N214: 0.8 | O214: 6 | P214: 3 | Q214: 4 | R214: 3 | S214: 46960 | T214: 259.416 | U214: 285,000 contacts × 68% tier-one × 60% deflection × 8.4 min × $65/hour ÷ 60 min × 0.90 × 0.75 = $7.3M | V214: No direct revenue impact | W214: No direct risk impact | X214: No direct cash flow impact | Y214: Support specialists monitor AI conversations in real-time and intervene on escalated cases or member | Z214: =I214*'Dynamic Analysis Dashboard'!$B$8*'Dynamic Analysis Dashboard'!$B$9*'Dynamic Analysis Dashboard'!$B$21 -> 4.9275e-06 | AA214: =J214*'Dynamic Analysis Dashboard'!$B$8*'Dynamic Analysis Dashboard'!$B$9*'Dynamic Analysis Dashboard'!$B$21 -> 0 | AB214: =K214*'Dynamic Analysis Dashboard'!$B$10*'Dynamic Analysis Dashboard'!$B$9*'Dynamic Analysis Dashboard'!$B$21 -> 0 | AC214: =L214*'Dynamic Analysis Dashboard'!$B$11*'Dynamic Analysis Dashboard'!$B$9*'Dynamic Analysis Dashboard'!$B$21 -> 0 | AD214: =SUM(Z214:AC214) -> 4.9275e-06 | AE214: =AD214*N214 -> 3.942e-06
A215: Impetus Wellness | B215: UC-06 | C215: Personalized Engagement Recommendation Engine | D215: Member Engagement | E215: Program Personalization | F215: Data Analysis, Research & Information Retrieval, Workflow Automation | G215: High | H215: Q2 | I215: 0 | J215: 9.7e-06 | K215: 0 | L215: 0 | M215: 9.7e-06 | N215: 0.7 | O215: 12 | P215: 3 | Q215: 2 | R215: 4 | S215: 697000 | T215: 1263.6 | U215: No direct cost impact | V215: 10 percentage point engagement lift × $180M revenue × 0.36 revenue correlation × 0.95 × 0.75 = $9.7M | W215: No direct risk impact | X215: No direct cash flow impact | Y215: Wellness program managers review and approve recommended interventions for high-risk members or sens | Z215: =I215*'Dynamic Analysis Dashboard'!$B$8*'Dynamic Analysis Dashboard'!$B$9*'Dynamic Analysis Dashboard'!$B$21 -> 0 | AA215: =J215*'Dynamic Analysis Dashboard'!$B$8*'Dynamic Analysis Dashboard'!$B$9*'Dynamic Analysis Dashboard'!$B$21 -> 6.5475e-06 | AB215: =K215*'Dynamic Analysis Dashboard'!$B$10*'Dynamic Analysis Dashboard'!$B$9*'Dynamic Analysis Dashboard'!$B$21 -> 0 | AC215: =L215*'Dynamic Analysis Dashboard'!$B$11*'Dynamic Analysis Dashboard'!$B$9*'Dynamic Analysis Dashboard'!$B$21 -> 0 | AD215: =SUM(Z215:AC215) -> 6.5475e-06 | AE215: =AD215*N215 -> 4.58325e-06
A216: Impetus Wellness | B216: UC-07 | C216: HIPAA Audit Documentation Assistant | D216: Compliance & Legal | E216: Regulatory Documentation | F216: Research & Information Retrieval, Content Creation, Workflow Automation | G216: High | H216: Q3 | I216: 2.7e-06 | J216: 0 | K216: 1.4e-06 | L216: 0 | M216: 4.1e-06 | N216: 0.85 | O216: 6 | P216: 2 | Q216: 3 | R216: 2 | S216: 120 | T216: 2.52 | U216: 32 annual audits × 124 hours × 70% time reduction × $125/hour × 0.90 × 0.75 = $2.7M | V216: No direct revenue impact | W216: 20% reduction × $12M compliance penalty exposure × 0.80 × 0.75 = $1.4M | X216: No direct cash flow impact | Y216: Privacy counsel reviews and approves all audit response content and legal assertions before regulato | Z216: =I216*'Dynamic Analysis Dashboard'!$B$8*'Dynamic Analysis Dashboard'!$B$9*'Dynamic Analysis Dashboard'!$B$21 -> 1.8225e-06 | AA216: =J216*'Dynamic Analysis Dashboard'!$B$8*'Dynamic Analysis Dashboard'!$B$9*'Dynamic Analysis Dashboard'!$B$21 -> 0 | AB216: =K216*'Dynamic Analysis Dashboard'!$B$10*'Dynamic Analysis Dashboard'!$B$9*'Dynamic Analysis Dashboard'!$B$21 -> 8.4e-07 | AC216: =L216*'Dynamic Analysis Dashboard'!$B$11*'Dynamic Analysis Dashboard'!$B$9*'Dynamic Analysis Dashboard'!$B$21 -> 0 | AD216: =SUM(Z216:AC216) -> 2.6625e-06 | AE216: =AD216*N216 -> 2.263125e-06
A217: Impetus Wellness | B217: UC-09 | C217: Product Development Documentation Accelerator | D217: Product Development | E217: Feature Delivery | F217: Coding Assistance, Content Creation | G217: High | H217: Q4 | I217: 4e-06 | J217: 0 | K217: 0 | L217: 0 | M217: 4e-06 | N217: 0.75 | O217: 6 | P217: 2 | Q217: 4 | R217: 2 | S217: 864 | T217: 5.184 | U217: 24 features/year × 34 days × 60% time reduction × 6 hours/day × $125/hour × 0.90 × 0.75 = $4.0M | V217: No direct revenue impact | W217: No direct risk impact | X217: No direct cash flow impact | Y217: Engineering leads review and approve all technical documentation for accuracy, completeness, and sec | Z217: =I217*'Dynamic Analysis Dashboard'!$B$8*'Dynamic Analysis Dashboard'!$B$9*'Dynamic Analysis Dashboard'!$B$21 -> 2.7e-06 | AA217: =J217*'Dynamic Analysis Dashboard'!$B$8*'Dynamic Analysis Dashboard'!$B$9*'Dynamic Analysis Dashboard'!$B$21 -> 0 | AB217: =K217*'Dynamic Analysis Dashboard'!$B$10*'Dynamic Analysis Dashboard'!$B$9*'Dynamic Analysis Dashboard'!$B$21 -> 0 | AC217: =L217*'Dynamic Analysis Dashboard'!$B$11*'Dynamic Analysis Dashboard'!$B$9*'Dynamic Analysis Dashboard'!$B$21 -> 0 | AD217: =SUM(Z217:AC217) -> 2.7e-06 | AE217: =AD217*N217 -> 2.025e-06
A218: Impetus Wellness | B218: UC-03 | C218: Predictive Churn Intelligence System | D218: Account Management | E218: Client Retention | F218: Data Analysis, Workflow Automation | G218: Critical | H218: Q1 | I218: 0 | J218: 2.28e-05 | K218: 0 | L218: 0 | M218: 2.28e-05 | N218: 0.7 | O218: 9 | P218: 3 | Q218: 2 | R218: 3 | S218: 7290 | T218: 37.908 | U218: No direct cost impact | V218: 4 percentage point retention lift × $180M revenue × 0.85 revenue at risk × 0.95 × 0.75 = $22.8M | W218: No direct risk impact | X218: No direct cash flow impact | Y218: Client success directors review churn risk scores and approve recommended intervention strategies be | Z218: =I218*'Dynamic Analysis Dashboard'!$B$8*'Dynamic Analysis Dashboard'!$B$9*'Dynamic Analysis Dashboard'!$B$21 -> 0 | AA218: =J218*'Dynamic Analysis Dashboard'!$B$8*'Dynamic Analysis Dashboard'!$B$9*'Dynamic Analysis Dashboard'!$B$21 -> 1.539e-05 | AB218: =K218*'Dynamic Analysis Dashboard'!$B$10*'Dynamic Analysis Dashboard'!$B$9*'Dynamic Analysis Dashboard'!$B$21 -> 0 | AC218: =L218*'Dynamic Analysis Dashboard'!$B$11*'Dynamic Analysis Dashboard'!$B$9*'Dynamic Analysis Dashboard'!$B$21 -> 0 | AD218: =SUM(Z218:AC218) -> 1.539e-05 | AE218: =AD218*N218 -> 1.0773e-05
... A438: The Lifetime Value Co | B438: UC-02 | C438: Automated Client Insight Reports | D438: Client Success | E438: Reporting | F438: Data Analysis, Content Creation, Research & Information Retrieval | G438: Critical | H438: Q1 | I438: 6.6 | J438: 0 | K438: 2.4 | L438: 0 | M438: 9 | N438: 0.75 | O438: 6 | P438: 3 | Q438: 3 | R438: 3 | S438: 4760 | T438: 9.792 | U438: 13 hours saved × 340 clients × 12 months × $145/hour × 0.90 × 0.75 = $6,622K → $6,600K | V438: No direct revenue impact | W438: 0.23 × $76M churn × 0.14 risk reduction × 0.80 × 0.75 = $2,362K → $2,400K | X438: No material cash flow impact | Y438: Client success manager reviews generated report for accuracy, edits narrative tone, and approves bef | Z438: =I438*'Dynamic Analysis Dashboard'!$B$8*'Dynamic Analysis Dashboard'!$B$9*'Dynamic Analysis Dashboard'!$B$21 -> 4.455 | AA438: =J438*'Dynamic Analysis Dashboard'!$B$8*'Dynamic Analysis Dashboard'!$B$9*'Dynamic Analysis Dashboard'!$B$21 -> 0 | AB438: =K438*'Dynamic Analysis Dashboard'!$B$10*'Dynamic Analysis Dashboard'!$B$9*'Dynamic Analysis Dashboard'!$B$21 -> 1.44 | AC438: =L438*'Dynamic Analysis Dashboard'!$B$11*'Dynamic Analysis Dashboard'!$B$9*'Dynamic Analysis Dashboard'!$B$21 -> 0 | AD438: =SUM(Z438:AC438) -> 5.895 | AE438: =AD438*N438 -> 4.42125
A439: The Lifetime Value Co | B439: UC-03 | C439: Model Documentation Assistant | D439: Data Science | E439: Model Documentation | G439: Critical | H439: Q2 | I439: 2.9 | J439: 0 | K439: 0.8 | L439: 0 | M439: 3.7 | N439: 0.7 | O439: 6 | P439: 2 | Q439: 3 | R439: 2 | S439: 1944 | T439: 4.536 | U439: 19 hours saved × 216 models × 4 quarters × $215/hour × 0.90 × 0.75 = $2,983K → $2,900K | V439: No direct revenue impact | W439: 0.08 × $15M regulatory penalty × 0.85 risk reduction × 0.80 × 0.75 = $816K → $800K | X439: No material cash flow impact | Y439: Senior data scientist reviews generated documentation for statistical accuracy and regulatory comple | Z439: =I439*'Dynamic Analysis Dashboard'!$B$8*'Dynamic Analysis Dashboard'!$B$9*'Dynamic Analysis Dashboard'!$B$21 -> 1.9575 | AA439: =J439*'Dynamic Analysis Dashboard'!$B$8*'Dynamic Analysis Dashboard'!$B$9*'Dynamic Analysis Dashboard'!$B$21 -> 0 | AB439: =K439*'Dynamic Analysis Dashboard'!$B$10*'Dynamic Analysis Dashboard'!$B$9*'Dynamic Analysis Dashboard'!$B$21 -> 0.48 | AC439: =L439*'Dynamic Analysis Dashboard'!$B$11*'Dynamic Analysis Dashboard'!$B$9*'Dynamic Analysis Dashboard'!$B$21 -> 0 | AD439: =SUM(Z439:AC439) -> 2.4375 | AE439: =AD439*N439 -> 1.70625
A440: The Lifetime Value Co | B440: UC-06 | C440: Pre-Sales ROI Calculator | D440: Sales Engineering | E440: Pre-Sales Analysis | F440: Data Analysis, Content Creation, Research & Information Retrieval | G440: Critical | H440: Q1 | I440: 0.3 | J440: 8.5 | K440: 0 | L440: 0 | M440: 8.8 | N440: 0.7 | O440: 6 | P440: 3 | Q440: 2 | R440: 3 | S440: 192 | T440: 0.432 | U440: 14 hours saved × 186 demos × $165/hour × 0.90 × 0.75 = $348K → $300K | V440: 14 hours saved × 186 demos × $165/hour enabling 4 additional deals × $2.1M ACV × 0.95 × 0.75 = $8,48 | W440: No material risk reduction | X440: No material cash flow impact | Y440: Sales engineer reviews ROI assumptions, validates industry benchmark applicability, and approves dem | Z440: =I440*'Dynamic Analysis Dashboard'!$B$8*'Dynamic Analysis Dashboard'!$B$9*'Dynamic Analysis Dashboard'!$B$21 -> 0.2025 | AA440: =J440*'Dynamic Analysis Dashboard'!$B$8*'Dynamic Analysis Dashboard'!$B$9*'Dynamic Analysis Dashboard'!$B$21 -> 5.7375 | AB440: =K440*'Dynamic Analysis Dashboard'!$B$10*'Dynamic Analysis Dashboard'!$B$9*'Dynamic Analysis Dashboard'!$B$21 -> 0 | AC440: =L440*'Dynamic Analysis Dashboard'!$B$11*'Dynamic Analysis Dashboard'!$B$9*'Dynamic Analysis Dashboard'!$B$21 -> 0 | AD440: =SUM(Z440:AC440) -> 5.94 | AE440: =AD440*N440 -> 4.158
A441: The Lifetime Value Co | B441: UC-08 | C441: Customer Feedback Synthesis Platform | D441: Product Management | E441: Feature Prioritization | F441: Research & Information Retrieval, Data Analysis, Content Creation | G441: Critical | H441: Q2 | I441: 0.5 | J441: 4.3 | K441: 0 | L441: 0 | M441: 4.8 | N441: 0.75 | O441: 6 | P441: 3 | Q441: 2 | R441: 3 | S441: 336 | T441: 0.864 | U441: 12 days saved × 12 cycles × 8 hours × $145/hour × 0.90 × 0.75 = $559K → $500K | V441: 12 days accelerated × 6 releases × $350K opportunity cost × 0.95 × 0.75 = $4,284K → $4,300K | W441: No material risk reduction | X441: No material cash flow impact | Y441: Product manager reviews clustered themes, validates customer impact estimates, and approves feature | Z441: =I441*'Dynamic Analysis Dashboard'!$B$8*'Dynamic Analysis Dashboard'!$B$9*'Dynamic Analysis Dashboard'!$B$21 -> 0.3375 | AA441: =J441*'Dynamic Analysis Dashboard'!$B$8*'Dynamic Analysis Dashboard'!$B$9*'Dynamic Analysis Dashboard'!$B$21 -> 2.9025 | AB441: =K441*'Dynamic Analysis Dashboard'!$B$10*'Dynamic Analysis Dashboard'!$B$9*'Dynamic Analysis Dashboard'!$B$21 -> 0 | AC441: =L441*'Dynamic Analysis Dashboard'!$B$11*'Dynamic Analysis Dashboard'!$B$9*'Dynamic Analysis Dashboard'!$B$21 -> 0 | AD441: =SUM(Z441:AC441) -> 3.24 | AE441: =AD441*N441 -> 2.43
A442: ThreeSixty Group | B442: UC-01 | C442: Intelligent Pitch Assembly Engine | D442: New Business Development | E442: Pitch & Proposal | F442: Research & Information Retrieval, Content Creation, Data Analysis | G442: High | H442: Q2 | I442: 3e-06 | J442: 9.5e-06 | K442: 0 | L442: 0 | M442: 1.18e-05 | N442: 0.75 | O442: 9 | P442: 3 | Q442: 2 | R442: 3 | S442: 900 | T442: 1.944 | U442: 28,000 hours saved × $125/hour × 0.90 × 0.75 = $2.3M | V442: 10% win rate lift × $133M annual pitch pipeline × 0.95 × 0.75 = $9.5M | W442: No risk mitigation impact | X442: No cash flow impact | Y442: Senior strategist reviews and approves all auto-generated pitch sections before client presentation, | Z442: =I442*'Dynamic Analysis Dashboard'!$B$8*'Dynamic Analysis Dashboard'!$B$9*'Dynamic Analysis Dashboard'!$B$21 -> 2.025e-06 | AA442: =J442*'Dynamic Analysis Dashboard'!$B$8*'Dynamic Analysis Dashboard'!$B$9*'Dynamic Analysis Dashboard'!$B$21 -> 6.4125e-06 | AB442: =K442*'Dynamic Analysis Dashboard'!$B$10*'Dynamic Analysis Dashboard'!$B$9*'Dynamic Analysis Dashboard'!$B$21 -> 0 | AC442: =L442*'Dynamic Analysis Dashboard'!$B$11*'Dynamic Analysis Dashboard'!$B$9*'Dynamic Analysis Dashboard'!$B$21 -> 0 | AD442: =SUM(Z442:AC442) -> 8.4375e-06 | AE442: =AD442*N442 -> 6.328125e-06
A443: ThreeSixty Group | B443: UC-05 | C443: AI Onboarding Assistant | D443: Talent Development | E443: Onboarding | F443: Conversational Interfaces, Research & Information Retrieval, Content Creation | G443: High | H443: Q1 | I443: 5.8e-06 | J443: 0 | K443: 2.1e-06 | L443: 0 | M443: 3.3e-06 | N443: 0.7 | O443: 6 | P443: 2 | Q443: 2 | R443: 2 | S443: 1575 | T443: 3.402 | U443: 45 days × 180 new hires × $165/day × 0.90 × 0.75 = $1.8M | V443: No revenue impact | W443: 7% attrition reduction × 850 employees × $42K replacement cost × 0.80 × 0.75 = $1.5M | X443: No cash flow impact | Y443: Department heads review and approve all knowledge base content monthly and validate learning path ef | Z443: =I443*'Dynamic Analysis Dashboard'!$B$8*'Dynamic Analysis Dashboard'!$B$9*'Dynamic Analysis Dashboard'!$B$21 -> 3.915e-06 | AA443: =J443*'Dynamic Analysis Dashboard'!$B$8*'Dynamic Analysis Dashboard'!$B$9*'Dynamic Analysis Dashboard'!$B$21 -> 0 | AB443: =K443*'Dynamic Analysis Dashboard'!$B$10*'Dynamic Analysis Dashboard'!$B$9*'Dynamic Analysis Dashboard'!$B$21 -> 1.26e-06 | AC443: =L443*'Dynamic Analysis Dashboard'!$B$11*'Dynamic Analysis Dashboard'!$B$9*'Dynamic Analysis Dashboard'!$B$21 -> 0 | AD443: =SUM(Z443:AC443) -> 5.175e-06 | AE443: =AD443*N443 -> 3.6225e-06
A444: ThreeSixty Group | B444: UC-08 | C444: Contract Intelligence Platform | D444: Legal & Compliance | E444: Contract Management | F444: Research & Information Retrieval, Data Analysis, Content Creation | G444: High | H444: Q2 | I444: 1.3e-06 | J444: 0 | K444: 1.8e-06 | L444: 2.1e-06 | M444: 4.5e-06 | N444: 0.7 | O444: 6 | P444: 2 | Q444: 2 | R444: 2 | S444: 765 | T444: 1.652 | U444: 3,200 hours contract review × $165/hour × 60% time saved × 0.90 × 0.75 = $0.2M | V444: No revenue impact | W444: 25% risk reduction × $12M contract dispute exposure × 0.80 × 0.75 = $1.8M | X444: 8 days cycle reduction × $495K daily revenue × 0.85 × 0.75 = $2.5M | Y444: General counsel reviews all flagged contract deviations and approves AI-suggested redlines before cl | Z444: =I444*'Dynamic Analysis Dashboard'!$B$8*'Dynamic Analysis Dashboard'!$B$9*'Dynamic Analysis Dashboard'!$B$21 -> 8.775e-07 | AA444: =J444*'Dynamic Analysis Dashboard'!$B$8*'Dynamic Analysis Dashboard'!$B$9*'Dynamic Analysis Dashboard'!$B$21 -> 0 | AB444: =K444*'Dynamic Analysis Dashboard'!$B$10*'Dynamic Analysis Dashboard'!$B$9*'Dynamic Analysis Dashboard'!$B$21 -> 1.08e-06 | AC444: =L444*'Dynamic Analysis Dashboard'!$B$11*'Dynamic Analysis Dashboard'!$B$9*'Dynamic Analysis Dashboard'!$B$21 -> 1.33875e-06 | AD444: =SUM(Z444:AC444) -> 3.29625e-06 | AE444: =AD444*N444 -> 2.307375e-06
A445: ThreeSixty Group | B445: UC-10 | C445: Client Sentiment Early Warning System | D445: Client Services | E445: Account Planning | F445: Data Analysis, Conversational Interfaces, Research & Information Retrieval | G445: High | H445: Q1 | I445: 0 | J445: 8.5e-06 | K445: 4.3e-06 | L445: 0 | M445: 1.28e-05 | N445: 0.7 | O445: 9 | P445: 3 | Q445: 3 | R445: 3 | S445: 1920 | T445: 4.147 | U445: No cost reduction impact | V445: 8% churn reduction × $149M retention revenue × 0.95 × 0.75 = $8.5M | W445: 40% early detection × $18M churn risk × 0.80 × 0.75 = $4.3M | X445: No cash flow impact | Y445: Account directors review all at-risk client alerts and approve intervention strategies before execut | Z445: =I445*'Dynamic Analysis Dashboard'!$B$8*'Dynamic Analysis Dashboard'!$B$9*'Dynamic Analysis Dashboard'!$B$21 -> 0 | AA445: =J445*'Dynamic Analysis Dashboard'!$B$8*'Dynamic Analysis Dashboard'!$B$9*'Dynamic Analysis Dashboard'!$B$21 -> 5.7375e-06 | AB445: =K445*'Dynamic Analysis Dashboard'!$B$10*'Dynamic Analysis Dashboard'!$B$9*'Dynamic Analysis Dashboard'!$B$21 -> 2.58e-06 | AC445: =L445*'Dynamic Analysis Dashboard'!$B$11*'Dynamic Analysis Dashboard'!$B$9*'Dynamic Analysis Dashboard'!$B$21 -> 0 | AD445: =SUM(Z445:AC445) -> 8.3175e-06 | AE445: =AD445*N445 -> 5.82225e-06
A446: ThreeSixty Group | B446: UC-02 | C446: Enterprise Knowledge Graph | D446: Knowledge Management | E446: Asset Discovery | F446: Research & Information Retrieval, Data Analysis | G446: Medium | H446: Q4 | I446: 6.9e-06 | J446: 0 | K446: 0 | L446: 0 | M446: 4.5e-06 | N446: 0.8 | O446: 15 | P446: 4 | Q446: 2 | R446: 5 | S446: 38250 | T446: 8.262 | U446: 68,000 hours × $125/hour × 80% time saved × 0.90 × 0.75 = $4.5M | V446: No revenue impact | W446: No risk mitigation impact | X446: No cash flow impact | Y446: Creative directors validate metadata accuracy during quarterly audits and approve relevance scoring | Z446: =I446*'Dynamic Analysis Dashboard'!$B$8*'Dynamic Analysis Dashboard'!$B$9*'Dynamic Analysis Dashboard'!$B$21 -> 4.6575e-06 | AA446: =J446*'Dynamic Analysis Dashboard'!$B$8*'Dynamic Analysis Dashboard'!$B$9*'Dynamic Analysis Dashboard'!$B$21 -> 0 | AB446: =K446*'Dynamic Analysis Dashboard'!$B$10*'Dynamic Analysis Dashboard'!$B$9*'Dynamic Analysis Dashboard'!$B$21 -> 0 | AC446: =L446*'Dynamic Analysis Dashboard'!$B$11*'Dynamic Analysis Dashboard'!$B$9*'Dynamic Analysis Dashboard'!$B$21 -> 0 | AD446: =SUM(Z446:AC446) -> 4.6575e-06 | AE446: =AD446*N446 -> 3.726e-06
A447: ThreeSixty Group | B447: UC-03 | C447: Automated Performance Reporting Suite | D447: Client Services | E447: Performance Reporting | F447: Data Analysis, Content Creation, Research & Information Retrieval | G447: Medium | H447: Q3 | I447: 3.4e-06 | J447: 4.8e-06 | K447: 3.2e-06 | L447: 0 | M447: 1.01e-05 | N447: 0.7 | O447: 12 | P447: 3 | Q447: 3 | R447: 4 | S447: 4480 | T447: 9.676 | U447: 34,000 hours × $125/hour × 75% time saved × 0.90 × 0.75 = $2.1M | V447: 5% revenue retention lift × $135M at-risk revenue × 0.95 × 0.75 = $4.8M | W447: 30% reduction × $18M client churn risk × 0.80 × 0.75 = $3.2M | X447: No cash flow impact | Y447: Account directors review all auto-generated insights before client delivery and approve anomaly inte | Z447: =I447*'Dynamic Analysis Dashboard'!$B$8*'Dynamic Analysis Dashboard'!$B$9*'Dynamic Analysis Dashboard'!$B$21 -> 2.295e-06 | AA447: =J447*'Dynamic Analysis Dashboard'!$B$8*'Dynamic Analysis Dashboard'!$B$9*'Dynamic Analysis Dashboard'!$B$21 -> 3.24e-06 | AB447: =K447*'Dynamic Analysis Dashboard'!$B$10*'Dynamic Analysis Dashboard'!$B$9*'Dynamic Analysis Dashboard'!$B$21 -> 1.92e-06 | AC447: =L447*'Dynamic Analysis Dashboard'!$B$11*'Dynamic Analysis Dashboard'!$B$9*'Dynamic Analysis Dashboard'!$B$21 -> 0 | AD447: =SUM(Z447:AC447) -> 7.455e-06 | AE447: =AD447*N447 -> 5.2185e-06
A448: ThreeSixty Group | B448: UC-04 | C448: Predictive Creative Testing Platform | D448: Creative Services | E448: Campaign Development | F448: Data Analysis, Content Creation | G448: Medium | H448: Q4 | I448: 5e-06 | J448: 0 | K448: 0 | L448: 1.8e-06 | M448: 3.7e-06 | N448: 0.65 | O448: 12 | P448: 3 | Q448: 2 | R448: 3 | S448: 1440 | T448: 3.11 | U448: $8.4M rework costs × 40% reduction × 0.90 × 0.75 = $2.2M | V448: No revenue impact | W448: No risk mitigation impact | X448: 13 days cycle reduction × $190K daily operating cash × 0.85 × 0.75 = $1.5M | Y448: Executive creative director validates AI predictions against brand strategy and approves recommended | Z448: =I448*'Dynamic Analysis Dashboard'!$B$8*'Dynamic Analysis Dashboard'!$B$9*'Dynamic Analysis Dashboard'!$B$21 -> 3.375e-06 | AA448: =J448*'Dynamic Analysis Dashboard'!$B$8*'Dynamic Analysis Dashboard'!$B$9*'Dynamic Analysis Dashboard'!$B$21 -> 0 | AB448: =K448*'Dynamic Analysis Dashboard'!$B$10*'Dynamic Analysis Dashboard'!$B$9*'Dynamic Analysis Dashboard'!$B$21 -> 0 | AC448: =L448*'Dynamic Analysis Dashboard'!$B$11*'Dynamic Analysis Dashboard'!$B$9*'Dynamic Analysis Dashboard'!$B$21 -> 1.1475e-06 | AD448: =SUM(Z448:AC448) -> 4.5225e-06 | AE448: =AD448*N448 -> 2.939625e-06
A449: ThreeSixty Group | B449: UC-06 | C449: Competitive Intelligence Automation | D449: Market Research | E449: Competitive Intelligence | F449: Research & Information Retrieval, Data Analysis, Content Creation | G449: Medium | H449: Q3 | I449: 2.4e-06 | J449: 2.5e-06 | K449: 0 | L449: 0 | M449: 3.1e-06 | N449: 0.75 | O449: 9 | P449: 3 | Q449: 3 | R449: 3 | S449: 2400 | T449: 5.184 | U449: 8,200 hours research time × $165/hour × 70% automation × 0.90 × 0.75 = $0.6M | V449: 3% revenue lift from faster insights × $118M insight-driven revenue × 0.95 × 0.75 = $2.5M | W449: No risk mitigation impact | X449: No cash flow impact | Y449: Strategy leads validate all competitive claims and strategic interpretations before inclusion in cli | Z449: =I449*'Dynamic Analysis Dashboard'!$B$8*'Dynamic Analysis Dashboard'!$B$9*'Dynamic Analysis Dashboard'!$B$21 -> 1.62e-06 | AA449: =J449*'Dynamic Analysis Dashboard'!$B$8*'Dynamic Analysis Dashboard'!$B$9*'Dynamic Analysis Dashboard'!$B$21 -> 1.6875e-06 | AB449: =K449*'Dynamic Analysis Dashboard'!$B$10*'Dynamic Analysis Dashboard'!$B$9*'Dynamic Analysis Dashboard'!$B$21 -> 0 | AC449: =L449*'Dynamic Analysis Dashboard'!$B$11*'Dynamic Analysis Dashboard'!$B$9*'Dynamic Analysis Dashboard'!$B$21 -> 0 | AD449: =SUM(Z449:AC449) -> 3.3075e-06 | AE449: =AD449*N449 -> 2.480625e-06
A450: ThreeSixty Group | B450: UC-07 | C450: Milestone-Triggered Invoicing Engine | D450: Finance | E450: Revenue Recognition | F450: Workflow Automation, Data Analysis | G450: Medium | H450: Q3 | I450: 1.7e-06 | J450: 0 | K450: 0 | L450: 2.9e-06 | M450: 1.5e-06 | N450: 0.8 | O450: 9 | P450: 3 | Q450: 3 | R450: 3 | S450: 1472 | T450: 3.177 | U450: 4,800 hours invoice processing × $95/hour × 0.90 × 0.75 = $0.3M | V450: No revenue impact | W450: No risk mitigation impact | X450: 5 days DSO reduction × $495K daily revenue × 8% WACC × 0.85 × 0.75 = $1.2M | Y450: Finance manager approves all auto-generated invoices before client transmission and validates revenu | Z450: =I450*'Dynamic Analysis Dashboard'!$B$8*'Dynamic Analysis Dashboard'!$B$9*'Dynamic Analysis Dashboard'!$B$21 -> 1.1475e-06 | AA450: =J450*'Dynamic Analysis Dashboard'!$B$8*'Dynamic Analysis Dashboard'!$B$9*'Dynamic Analysis Dashboard'!$B$21 -> 0 | AB450: =K450*'Dynamic Analysis Dashboard'!$B$10*'Dynamic Analysis Dashboard'!$B$9*'Dynamic Analysis Dashboard'!$B$21 -> 0 | AC450: =L450*'Dynamic Analysis Dashboard'!$B$11*'Dynamic Analysis Dashboard'!$B$9*'Dynamic Analysis Dashboard'!$B$21 -> 1.84875e-06 | AD450: =SUM(Z450:AC450) -> 2.99625e-06 | AE450: =AD450*N450 -> 2.397e-06
A451: ThreeSixty Group | B451: UC-09 | C451: Predictive Resource Allocation System | D451: Operations | E451: Resource Allocation | F451: Data Analysis, Workflow Automation | G451: Medium | H451: Q4 | I451: 0 | J451: 6.1e-06 | K451: 0 | L451: 0 | M451: 5.4e-06 | N451: 0.65 | O451: 15 | P451: 4 | Q451: 2 | R451: 4 | S451: 2400 | T451: 5.184 | U451: No cost reduction impact | V451: 5% bench time reduction × $122M billable capacity × 0.95 × 0.75 = $5.4M | W451: No risk mitigation impact | X451: No cash flow impact | Y451: Operations directors approve all resource assignments and validate demand forecasts against business | Z451: =I451*'Dynamic Analysis Dashboard'!$B$8*'Dynamic Analysis Dashboard'!$B$9*'Dynamic Analysis Dashboard'!$B$21 -> 0 | AA451: =J451*'Dynamic Analysis Dashboard'!$B$8*'Dynamic Analysis Dashboard'!$B$9*'Dynamic Analysis Dashboard'!$B$21 -> 4.1175e-06 | AB451: =K451*'Dynamic Analysis Dashboard'!$B$10*'Dynamic Analysis Dashboard'!$B$9*'Dynamic Analysis Dashboard'!$B$21 -> 0 | AC451: =L451*'Dynamic Analysis Dashboard'!$B$11*'Dynamic Analysis Dashboard'!$B$9*'Dynamic Analysis Dashboard'!$B$21 -> 0 | AD451: =SUM(Z451:AC451) -> 4.1175e-06 | AE451: =AD451*N451 -> 2.676375e-06
... A526: Window Nation | B526: UC-10 | C526: Safety Training Compliance Tracker | D526: Human Resources | E526: Crew Onboarding | F526: Workflow Automation, Content Creation | G526: High | H526: Q2 | I526: 5e-07 | J526: 0 | K526: 1.9e-06 | L526: 0 | M526: 2.4e-06 | N526: 0.8 | O526: 6 | P526: 2 | Q526: 2 | R526: 2 | S526: 4494 | T526: 0.0009 | U526: 4,200 hours saved × $85/hr × 0.90 × 0.75 = $0.5M | V526: No direct revenue impact | W526: 50% compliance gap reduction × $6.5M OSHA penalty exposure × 0.80 × 0.75 = $1.9M | X526: No direct cash flow impact | Y526: HR manager reviews monthly compliance reports, validates certification documentation uploaded by cre | Z526: =I526*'Dynamic Analysis Dashboard'!$B$8*'Dynamic Analysis Dashboard'!$B$9*'Dynamic Analysis Dashboard'!$B$21 -> 3.375e-07 | AA526: =J526*'Dynamic Analysis Dashboard'!$B$8*'Dynamic Analysis Dashboard'!$B$9*'Dynamic Analysis Dashboard'!$B$21 -> 0 | AB526: =K526*'Dynamic Analysis Dashboard'!$B$10*'Dynamic Analysis Dashboard'!$B$9*'Dynamic Analysis Dashboard'!$B$21 -> 1.14e-06 | AC526: =L526*'Dynamic Analysis Dashboard'!$B$11*'Dynamic Analysis Dashboard'!$B$9*'Dynamic Analysis Dashboard'!$B$21 -> 0 | AD526: =SUM(Z526:AC526) -> 1.4775e-06 | AE526: =AD526*N526 -> 1.182e-06
A527: Window Nation | B527: UC-02 | C527: AI-Assisted Proposal Generation Engine | D527: Sales Operations | E527: Proposal Development | G527: Critical | H527: Q1 | I527: 2.5e-06 | J527: 8.7e-06 | K527: 0 | L527: 0 | M527: 1.12e-05 | N527: 0.75 | O527: 6 | P527: 3 | Q527: 4 | R527: 3 | S527: 125000 | T527: 0.027 | U527: 45 min saved × 280 reps × 18 proposals/week × 50 weeks × $150/hr × 0.90 × 0.75 = $2.5M | V527: 5% conversion lift × 24% baseline × 125,000 leads × $9,200 avg value × 0.95 × 0.75 = $8.7M | W527: No direct risk impact | X527: No direct cash flow impact | Y527: Sales representative reviews generated proposal for accuracy, adjusts pricing within authorized disc | Z527: =I527*'Dynamic Analysis Dashboard'!$B$8*'Dynamic Analysis Dashboard'!$B$9*'Dynamic Analysis Dashboard'!$B$21 -> 1.6875e-06 | AA527: =J527*'Dynamic Analysis Dashboard'!$B$8*'Dynamic Analysis Dashboard'!$B$9*'Dynamic Analysis Dashboard'!$B$21 -> 5.8725e-06 | AB527: =K527*'Dynamic Analysis Dashboard'!$B$10*'Dynamic Analysis Dashboard'!$B$9*'Dynamic Analysis Dashboard'!$B$21 -> 0 | AC527: =L527*'Dynamic Analysis Dashboard'!$B$11*'Dynamic Analysis Dashboard'!$B$9*'Dynamic Analysis Dashboard'!$B$21 -> 0 | AD527: =SUM(Z527:AC527) -> 7.56e-06 | AE527: =AD527*N527 -> 5.67e-06
A528: Window Nation | B528: UC-03 | C528: Conversational Product Advisor | D528: Sales Operations | E528: Technical Support | F528: Conversational Interfaces, Research & Information Retrieval | G528: Critical | H528: Q1 | I528: 1.7e-06 | J528: 3.2e-06 | K528: 0 | L528: 0 | M528: 4.9e-06 | N528: 0.7 | O528: 6 | P528: 2 | Q528: 4 | R528: 2 | S528: 46200 | T528: 0.0092 | U528: 18,000 hours deflected × $150/hr × 0.90 × 0.75 = $1.7M | V528: 2% conversion lift × 24% baseline × 125,000 leads × $9,200 avg value × 0.95 × 0.75 = $3.2M | W528: No direct risk impact | X528: No direct cash flow impact | Y528: Sales representative receives escalation notification with conversation summary and must respond wit | Z528: =I528*'Dynamic Analysis Dashboard'!$B$8*'Dynamic Analysis Dashboard'!$B$9*'Dynamic Analysis Dashboard'!$B$21 -> 1.1475e-06 | AA528: =J528*'Dynamic Analysis Dashboard'!$B$8*'Dynamic Analysis Dashboard'!$B$9*'Dynamic Analysis Dashboard'!$B$21 -> 2.16e-06 | AB528: =K528*'Dynamic Analysis Dashboard'!$B$10*'Dynamic Analysis Dashboard'!$B$9*'Dynamic Analysis Dashboard'!$B$21 -> 0 | AC528: =L528*'Dynamic Analysis Dashboard'!$B$11*'Dynamic Analysis Dashboard'!$B$9*'Dynamic Analysis Dashboard'!$B$21 -> 0 | AD528: =SUM(Z528:AC528) -> 3.3075e-06 | AE528: =AD528*N528 -> 2.31525e-06
A529: Window Nation | B529: UC-04 | C529: Computer Vision Installation Inspector | D529: Quality Assurance | E529: Installation Inspection | F529: Data Analysis, Content Creation | G529: Medium | H529: Q3 | I529: 1.5e-06 | J529: 0 | K529: 2.8e-06 | L529: 0 | M529: 4.3e-06 | N529: 0.75 | O529: 9 | P529: 3 | Q529: 2 | R529: 3 | S529: 13250 | T529: 0.0029 | U529: 25 min saved × 30,000 inspections × $100/hr × 0.90 × 0.75 = $1.5M | V529: No direct revenue impact | W529: 30% defect reduction × $12M annual rework cost × 0.80 × 0.75 = $2.8M | X529: No direct cash flow impact | Y529: Quality inspector reviews AI-flagged defects, validates classifications against visual inspection, a | Z529: =I529*'Dynamic Analysis Dashboard'!$B$8*'Dynamic Analysis Dashboard'!$B$9*'Dynamic Analysis Dashboard'!$B$21 -> 1.0125e-06 | AA529: =J529*'Dynamic Analysis Dashboard'!$B$8*'Dynamic Analysis Dashboard'!$B$9*'Dynamic Analysis Dashboard'!$B$21 -> 0 | AB529: =K529*'Dynamic Analysis Dashboard'!$B$10*'Dynamic Analysis Dashboard'!$B$9*'Dynamic Analysis Dashboard'!$B$21 -> 1.68e-06 | AC529: =L529*'Dynamic Analysis Dashboard'!$B$11*'Dynamic Analysis Dashboard'!$B$9*'Dynamic Analysis Dashboard'!$B$21 -> 0 | AD529: =SUM(Z529:AC529) -> 2.6925e-06 | AE529: =AD529*N529 -> 2.019375e-06
A530: Window Nation | B530: UC-06 | C530: Predictive Inventory Demand Forecaster | D530: Supply Chain | E530: Inventory Management | F530: Data Analysis, Workflow Automation | G530: Medium | H530: Q3 | I530: 0 | J530: 4.1e-06 | K530: 0 | L530: 1.8e-06 | M530: 5.9e-06 | N530: 0.75 | O530: 12 | P530: 4 | Q530: 3 | R530: 4 | S530: 2278 | T530: 0.0005 | U530: No direct cost impact | V530: 7% stockout reduction × 11% baseline × $54M lost sales × 0.95 × 0.75 = $4.1M | W530: No direct risk impact | X530: $3.5M inventory reduction × 8% WACC × 0.85 × 0.75 = $1.8M | Y530: Procurement manager reviews weekly purchase recommendations, overrides for known market changes not | Z530: =I530*'Dynamic Analysis Dashboard'!$B$8*'Dynamic Analysis Dashboard'!$B$9*'Dynamic Analysis Dashboard'!$B$21 -> 0 | AA530: =J530*'Dynamic Analysis Dashboard'!$B$8*'Dynamic Analysis Dashboard'!$B$9*'Dynamic Analysis Dashboard'!$B$21 -> 2.7675e-06 | AB530: =K530*'Dynamic Analysis Dashboard'!$B$10*'Dynamic Analysis Dashboard'!$B$9*'Dynamic Analysis Dashboard'!$B$21 -> 0 | AC530: =L530*'Dynamic Analysis Dashboard'!$B$11*'Dynamic Analysis Dashboard'!$B$9*'Dynamic Analysis Dashboard'!$B$21 -> 1.1475e-06 | AD530: =SUM(Z530:AC530) -> 3.915e-06 | AE530: =AD530*N530 -> 2.93625e-06
A531: Window Nation | B531: UC-09 | C531: Lead Quality Scoring and Assignment Engine | D531: Marketing | E531: Lead Qualification | F531: Data Analysis, Workflow Automation | G531: Critical | H531: Q1 | I531: 7e-07 | J531: 6.2e-06 | K531: 0 | L531: 0 | M531: 6.9e-06 | N531: 0.7 | O531: 6 | P531: 3 | Q531: 4 | R531: 3 | S531: 12168 | T531: 0.0025 | U531: 6,200 hours saved × $85/hr × 0.90 × 0.75 = $0.7M | V531: 3% conversion lift × 24% baseline × 125,000 leads × $9,200 avg value × 0.95 × 0.75 = $6.2M | W531: No direct risk impact | X531: No direct cash flow impact | Y531: Sales manager reviews weekly routing patterns and quality score distributions, overrides territory a | Z531: =I531*'Dynamic Analysis Dashboard'!$B$8*'Dynamic Analysis Dashboard'!$B$9*'Dynamic Analysis Dashboard'!$B$21 -> 4.725e-07 | AA531: =J531*'Dynamic Analysis Dashboard'!$B$8*'Dynamic Analysis Dashboard'!$B$9*'Dynamic Analysis Dashboard'!$B$21 -> 4.185e-06 | AB531: =K531*'Dynamic Analysis Dashboard'!$B$10*'Dynamic Analysis Dashboard'!$B$9*'Dynamic Analysis Dashboard'!$B$21 -> 0 | AC531: =L531*'Dynamic Analysis Dashboard'!$B$11*'Dynamic Analysis Dashboard'!$B$9*'Dynamic Analysis Dashboard'!$B$21 -> 0 | AD531: =SUM(Z531:AC531) -> 4.6575e-06 | AE531: =AD531*N531 -> 3.26025e-06
A532: WorldWide Electric | B532: UC-01 | C532: Intelligent Cost Estimation Engine | D532: Estimating & Preconstruction | E532: Cost Estimation | F532: Data Analysis, RAG, Content Creation | G532: High | H532: Q2 | I532: 1.09e-05 | J532: 1.53e-05 | K532: 0 | L532: 0 | M532: 2.62e-05 | N532: 0.8 | O532: 9 | P532: 3 | Q532: 2 | R532: 4 | S532: 4340 | T532: 0.0349 | U532: 240 estimator hours saved per week × $150/hr × 52 weeks × 0.90 × 0.75 × 0.80 = $10.9M | V532: 140 additional bids × $2.1M avg value × 7% win lift × 0.95 × 0.75 × 0.80 = $15.3M | W532: No direct risk mitigation | X532: No direct cash flow impact | Y532: Senior estimator reviews AI-generated cost baseline, validates material quantity calculations, and a | Z532: =I532*'Dynamic Analysis Dashboard'!$B$8*'Dynamic Analysis Dashboard'!$B$9*'Dynamic Analysis Dashboard'!$B$21 -> 7.3575e-06 | AA532: =J532*'Dynamic Analysis Dashboard'!$B$8*'Dynamic Analysis Dashboard'!$B$9*'Dynamic Analysis Dashboard'!$B$21 -> 1.03275e-05 | AB532: =K532*'Dynamic Analysis Dashboard'!$B$10*'Dynamic Analysis Dashboard'!$B$9*'Dynamic Analysis Dashboard'!$B$21 -> 0 | AC532: =L532*'Dynamic Analysis Dashboard'!$B$11*'Dynamic Analysis Dashboard'!$B$9*'Dynamic Analysis Dashboard'!$B$21 -> 0 | AD532: =SUM(Z532:AC532) -> 1.7685e-05 | AE532: =AD532*N532 -> 1.4148e-05
A533: WorldWide Electric | B533: UC-04 | C533: Automated Proposal Assembly Workbench | D533: Estimating & Preconstruction | E533: Proposal Development | F533: Content Creation, RAG | G533: High | H533: Q1 | I533: 4.5e-06 | J533: 1.28e-05 | K533: 0 | L533: 0 | M533: 1.73e-05 | N533: 0.8 | O533: 6 | P533: 2 | Q533: 3 | R533: 2 | S533: 6726 | T533: 0.059 | U533: 120 hours saved per week × $150/hr × 52 weeks × 0.90 × 0.75 × 0.80 = $4.5M | V533: 100 additional bids × $1.5M avg value × 6% win lift × 0.95 × 0.75 × 0.80 = $12.8M | W533: No direct risk mitigation | X533: No direct cash flow impact | Y533: Proposal manager reviews AI-drafted content for accuracy and client alignment, adds custom value pro | Z533: =I533*'Dynamic Analysis Dashboard'!$B$8*'Dynamic Analysis Dashboard'!$B$9*'Dynamic Analysis Dashboard'!$B$21 -> 3.0375e-06 | AA533: =J533*'Dynamic Analysis Dashboard'!$B$8*'Dynamic Analysis Dashboard'!$B$9*'Dynamic Analysis Dashboard'!$B$21 -> 8.64e-06 | AB533: =K533*'Dynamic Analysis Dashboard'!$B$10*'Dynamic Analysis Dashboard'!$B$9*'Dynamic Analysis Dashboard'!$B$21 -> 0 | AC533: =L533*'Dynamic Analysis Dashboard'!$B$11*'Dynamic Analysis Dashboard'!$B$9*'Dynamic Analysis Dashboard'!$B$21 -> 0 | AD533: =SUM(Z533:AC533) -> 1.16775e-05 | AE533: =AD533*N533 -> 9.342e-06
A534: WorldWide Electric | B534: UC-08 | C534: Regulatory Code Research Assistant | D534: Safety & Compliance | E534: Regulatory Adherence | F534: RAG, Conversational Interfaces | G534: High | H534: Q1 | I534: 4.1e-06 | J534: 0 | K534: 2.8e-06 | L534: 0 | M534: 6.9e-06 | N534: 0.65 | O534: 5 | P534: 2 | Q534: 2 | R534: 2 | S534: 3920 | T534: 0.0344 | U534: 140 hours saved per week × $150/hr × 52 weeks × 0.90 × 0.75 × 0.65 = $4.1M | V534: No direct revenue impact | W534: 30% reduction × $6.2M compliance burden × 0.80 × 0.75 × 0.65 = $2.8M | X534: No direct cash flow impact | Y534: Compliance manager reviews AI-retrieved code citations for complex or ambiguous situations, validate | Z534: =I534*'Dynamic Analysis Dashboard'!$B$8*'Dynamic Analysis Dashboard'!$B$9*'Dynamic Analysis Dashboard'!$B$21 -> 2.7675e-06 | AA534: =J534*'Dynamic Analysis Dashboard'!$B$8*'Dynamic Analysis Dashboard'!$B$9*'Dynamic Analysis Dashboard'!$B$21 -> 0 | AB534: =K534*'Dynamic Analysis Dashboard'!$B$10*'Dynamic Analysis Dashboard'!$B$9*'Dynamic Analysis Dashboard'!$B$21 -> 1.68e-06 | AC534: =L534*'Dynamic Analysis Dashboard'!$B$11*'Dynamic Analysis Dashboard'!$B$9*'Dynamic Analysis Dashboard'!$B$21 -> 0 | AD534: =SUM(Z534:AC534) -> 4.4475e-06 | AE534: =AD534*N534 -> 2.890875e-06
A535: WorldWide Electric | B535: UC-02 | C535: Dynamic Workforce Optimization Platform | D535: Project Management | E535: Resource Scheduling | F535: Data Analysis, Workflow Automation | G535: Medium | H535: Q3 | I535: 1.82e-05 | J535: 0 | K535: 0 | L535: 8.7e-06 | M535: 2.69e-05 | N535: 0.75 | O535: 12 | P535: 4 | Q535: 3 | R535: 5 | S535: 7006 | T535: 0.0563 | U535: 5% utilization improvement × 6200 workers × 2000 hrs × $85/hr × 0.90 × 0.75 × 0.75 = $18.2M | V535: No direct revenue impact | W535: No direct risk mitigation | X535: 14 days project acceleration × 340 projects × $2.1M × 0.025 × 0.85 × 0.75 × 0.75 = $8.7M | Y535: Project managers review AI-recommended crew assignments, override for client relationship priorities | Z535: =I535*'Dynamic Analysis Dashboard'!$B$8*'Dynamic Analysis Dashboard'!$B$9*'Dynamic Analysis Dashboard'!$B$21 -> 1.2285e-05 | AA535: =J535*'Dynamic Analysis Dashboard'!$B$8*'Dynamic Analysis Dashboard'!$B$9*'Dynamic Analysis Dashboard'!$B$21 -> 0 | AB535: =K535*'Dynamic Analysis Dashboard'!$B$10*'Dynamic Analysis Dashboard'!$B$9*'Dynamic Analysis Dashboard'!$B$21 -> 0 | AC535: =L535*'Dynamic Analysis Dashboard'!$B$11*'Dynamic Analysis Dashboard'!$B$9*'Dynamic Analysis Dashboard'!$B$21 -> 5.54625e-06 | AD535: =SUM(Z535:AC535) -> 1.783125e-05 | AE535: =AD535*N535 -> 1.3373437e-05
A536: WorldWide Electric | B536: UC-03 | C536: Procurement Price Intelligence System | D536: Procurement | E536: Material Sourcing | F536: Data Analysis, RAG | G536: Medium | H536: Q2 | I536: 0 | J536: 0 | K536: 2e-06 | L536: 0 | M536: 2e-06 | N536: 0.75 | O536: 6 | P536: 2 | Q536: 2 | R536: 3 | S536: 2304 | T536: 0.0185 | U536: No direct labor cost reduction | V536: No direct revenue impact | W536: 40% reduction × $6.8M margin erosion × 0.80 × 0.75 × 0.75 = $2.0M | X536: No direct cash flow impact | Y536: Procurement director reviews AI price forecasts and buying recommendations, validates against suppli | Z536: =I536*'Dynamic Analysis Dashboard'!$B$8*'Dynamic Analysis Dashboard'!$B$9*'Dynamic Analysis Dashboard'!$B$21 -> 0 | AA536: =J536*'Dynamic Analysis Dashboard'!$B$8*'Dynamic Analysis Dashboard'!$B$9*'Dynamic Analysis Dashboard'!$B$21 -> 0 | AB536: =K536*'Dynamic Analysis Dashboard'!$B$10*'Dynamic Analysis Dashboard'!$B$9*'Dynamic Analysis Dashboard'!$B$21 -> 1.2e-06 | AC536: =L536*'Dynamic Analysis Dashboard'!$B$11*'Dynamic Analysis Dashboard'!$B$9*'Dynamic Analysis Dashboard'!$B$21 -> 0 | AD536: =SUM(Z536:AC536) -> 1.2e-06 | AE536: =AD536*N536 -> 9e-07
A537: WorldWide Electric | B537: UC-05 | C537: Safety Incident Intelligence Platform | D537: Safety & Compliance | E537: Incident Investigation | F537: Data Analysis, Content Creation, Conversational Interfaces | G537: Medium | H537: Q3 | I537: 3.2e-06 | J537: 0 | K537: 4.3e-06 | L537: 0 | M537: 7.5e-06 | N537: 0.7 | O537: 8 | P537: 3 | Q537: 2 | R537: 3 | S537: 3164 | T537: 0.0278 | U537: 2800 investigation hours saved × $150/hr × 0.90 × 0.75 × 0.70 = $3.2M | V537: No direct revenue impact | W537: 25% incident reduction × $12M insurance + investigation costs × 0.80 × 0.75 × 0.70 = $4.3M | X537: No direct cash flow impact | Y537: Safety director reviews AI-generated incident analysis and recommendations, conducts on-site validat | Z537: =I537*'Dynamic Analysis Dashboard'!$B$8*'Dynamic Analysis Dashboard'!$B$9*'Dynamic Analysis Dashboard'!$B$21 -> 2.16e-06 | AA537: =J537*'Dynamic Analysis Dashboard'!$B$8*'Dynamic Analysis Dashboard'!$B$9*'Dynamic Analysis Dashboard'!$B$21 -> 0 | AB537: =K537*'Dynamic Analysis Dashboard'!$B$10*'Dynamic Analysis Dashboard'!$B$9*'Dynamic Analysis Dashboard'!$B$21 -> 2.58e-06 | AC537: =L537*'Dynamic Analysis Dashboard'!$B$11*'Dynamic Analysis Dashboard'!$B$9*'Dynamic Analysis Dashboard'!$B$21 -> 0 | AD537: =SUM(Z537:AC537) -> 4.74e-06 | AE537: =AD537*N537 -> 3.318e-06
A538: WorldWide Electric | B538: UC-06 | C538: Contract Change Order Accelerator | D538: Contract Administration | E538: Change Order Processing | F538: Content Creation, Data Analysis, Conversational Interfaces | G538: Medium | H538: Q2 | I538: 2.7e-06 | J538: 0 | K538: 0 | L538: 5.4e-06 | M538: 8.1e-06 | N538: 0.75 | O538: 7 | P538: 3 | Q538: 3 | R538: 3 | S538: 2520 | T538: 0.0221 | U538: 90 hours saved per week × $100/hr × 52 weeks × 0.90 × 0.75 × 0.75 = $2.7M | V538: No direct revenue impact | W538: No direct risk mitigation | X538: 13 days acceleration × 280 change orders × $42K avg × 0.85 × 0.75 × 0.75 = $5.4M | Y538: Contract administrator reviews AI-drafted change orders for completeness and pricing accuracy, negot | Z538: =I538*'Dynamic Analysis Dashboard'!$B$8*'Dynamic Analysis Dashboard'!$B$9*'Dynamic Analysis Dashboard'!$B$21 -> 1.8225e-06 | AA538: =J538*'Dynamic Analysis Dashboard'!$B$8*'Dynamic Analysis Dashboard'!$B$9*'Dynamic Analysis Dashboard'!$B$21 -> 0 | AB538: =K538*'Dynamic Analysis Dashboard'!$B$10*'Dynamic Analysis Dashboard'!$B$9*'Dynamic Analysis Dashboard'!$B$21 -> 0 | AC538: =L538*'Dynamic Analysis Dashboard'!$B$11*'Dynamic Analysis Dashboard'!$B$9*'Dynamic Analysis Dashboard'!$B$21 -> 3.4425e-06 | AD538: =SUM(Z538:AC538) -> 5.265e-06 | AE538: =AD538*N538 -> 3.94875e-06
A539: WorldWide Electric | B539: UC-07 | C539: Real-Time Project Cost Analytics | D539: Finance & Accounting | E539: Project Cost Accounting | F539: Data Analysis, Conversational Interfaces | G539: Medium | H539: Q3 | I539: 3.5e-06 | J539: 0 | K539: 0 | L539: 6.2e-06 | M539: 9.7e-06 | N539: 0.8 | O539: 8 | P539: 3 | Q539: 3 | R539: 4 | S539: 9860 | T539: 0.0793 | U539: 110 hours saved per week × $100/hr × 52 weeks × 0.90 × 0.75 × 0.80 = $3.5M | V539: No direct revenue impact | W539: No direct risk mitigation | X539: 6 days DSO reduction × $2.8B revenue / 365 × 0.08 WACC × 0.85 × 0.75 × 0.80 = $6.2M | Y539: Project accountant reviews AI-identified cost variances, validates material allocation accuracy, and | Z539: =I539*'Dynamic Analysis Dashboard'!$B$8*'Dynamic Analysis Dashboard'!$B$9*'Dynamic Analysis Dashboard'!$B$21 -> 2.3625e-06 | AA539: =J539*'Dynamic Analysis Dashboard'!$B$8*'Dynamic Analysis Dashboard'!$B$9*'Dynamic Analysis Dashboard'!$B$21 -> 0 | AB539: =K539*'Dynamic Analysis Dashboard'!$B$10*'Dynamic Analysis Dashboard'!$B$9*'Dynamic Analysis Dashboard'!$B$21 -> 0 | AC539: =L539*'Dynamic Analysis Dashboard'!$B$11*'Dynamic Analysis Dashboard'!$B$9*'Dynamic Analysis Dashboard'!$B$21 -> 3.9525e-06 | AD539: =SUM(Z539:AC539) -> 6.315e-06 | AE539: =AD539*N539 -> 5.052e-06
... A541: WorldWide Electric | B541: UC-10 | C541: Adaptive Safety Training Platform | D541: Human Resources | E541: Training & Development | F541: Content Creation, Conversational Interfaces, Data Analysis | G541: Medium | H541: Q4 | I541: 1.9e-06 | J541: 0 | K541: 1.3e-06 | L541: 0 | M541: 3.2e-06 | N541: 0.8 | O541: 7 | P541: 3 | Q541: 3 | R541: 2 | S541: 7936 | T541: 0.0697 | U541: 8000 travel hours saved × $85/hr × 0.90 × 0.75 × 0.80 = $1.9M | V541: No direct revenue impact | W541: 15% incident reduction × $12M costs × 0.80 × 0.75 × 0.80 = $1.3M | X541: No direct cash flow impact | Y541: Training director reviews AI-generated learning content for accuracy and regulatory compliance, vali | Z541: =I541*'Dynamic Analysis Dashboard'!$B$8*'Dynamic Analysis Dashboard'!$B$9*'Dynamic Analysis Dashboard'!$B$21 -> 1.2825e-06 | AA541: =J541*'Dynamic Analysis Dashboard'!$B$8*'Dynamic Analysis Dashboard'!$B$9*'Dynamic Analysis Dashboard'!$B$21 -> 0 | AB541: =K541*'Dynamic Analysis Dashboard'!$B$10*'Dynamic Analysis Dashboard'!$B$9*'Dynamic Analysis Dashboard'!$B$21 -> 7.8e-07 | AC541: =L541*'Dynamic Analysis Dashboard'!$B$11*'Dynamic Analysis Dashboard'!$B$9*'Dynamic Analysis Dashboard'!$B$21 -> 0 | AD541: =SUM(Z541:AC541) -> 2.0625e-06 | AE541: =AD541*N541 -> 1.65e-06

Sheet 4. Benefits by Driver
A1: BENEFITS ANALYSIS BY DRIVER
A3: SUMMARY BY BENEFIT TYPE
A4: Benefit Type | B4: Total Value ($M) | C4: % of Total | D4: Use Cases with Impact
A5: Cost Savings | B5: 169.05149 | C5: 0.43458678 | D5: 482
A6: Revenue Growth | B6: 148.10122 | C6: 0.38072917 | D6: 208
A7: Risk Reduction | B7: 65.960392 | C7: 0.16956677 | D7: 225
A8: Cash Flow Acceleration | B8: 57.370511 | C8: 0.14748445 | D8: 145
A10: BY FUNCTION
A11: Function | B11: Cost ($M) | C11: Revenue ($M) | D11: Risk ($M) | E11: Cash Flow ($M) | F11: Total ($M)
A12: Account Management | B12: 0 | C12: 2.43e-05 | D12: 0.8 | E12: 0 | F12: 2.51e-05
A13: Administrative | B13: 0.4 | C13: 0 | D13: 0.4 | E13: 0 | F13: 0.8
A14: Agent Development | B14: 3.5e-06 | C14: 1.13e-05 | D14: 0 | E14: 0 | F14: 1.48e-05
A15: Asset Management | B15: 0.7 | C15: 0 | D15: 0.3000012 | E15: 1.4e-06 | F15: 0.600003
A16: Business Development | B16: 6.5000212 | C16: 3.8000753 | D16: 6e-07 | E16: 0.8 | F16: 9.8000955
A17: Business Intelligence | B17: 1.2e-06 | C17: 0 | D17: 0 | E17: 0 | F17: 1.2e-06
A18: Carrier Management | B18: 2.45e-05 | C18: 0 | D18: 6.3e-06 | E18: 2.8e-06 | F18: 3.36e-05
A19: Claims | B19: 5.8e-06 | C19: 0 | D19: 8e-07 | E19: 4.3e-06 | F19: 1.09e-05
A20: Client Communications | B20: 2.1 | C20: 0 | D20: 0 | E20: 0 | F20: 2.1
A21: Client Delivery | B21: 4.5e-06 | C21: 0 | D21: 0.9000012 | E21: 1e-06 | F21: 0.9000067
A22: Client Management | B22: 0.9000016 | C22: 0 | D22: 0.6 | E22: 1.4e-06 | F22: 4.5e-06
A23: Client Relationship Management | B23: 2.9 | C23: 11.8 | D23: 0 | E23: 0 | F23: 14.7
... A135: Utilization Management | B135: 1.6 | C135: 0.5 | D135: 0.1 | E135: 0.6 | F135: 2.8
A137: BY PRIORITY TIER
A138: Priority | B138: Use Cases | C138: Cost ($M) | D138: Revenue ($M) | E138: Risk ($M) | F138: Cash Flow ($M) | G138: Total ($M)
A139: Critical | B139: 111 | C139: 46.600397 | D139: 46.700606 | E139: 6.000089 | F139: 3.7801721 | G139: 98.70126
A140: High | B140: 247 | C140: 92.790659 | D140: 84.20038 | E140: 43.500208 | F140: 35.700194 | G140: 235.40146
A141: Medium | B141: 182 | C141: 29.66043 | D141: 17.200233 | E141: 16.460096 | F141: 17.890145 | G141: 54.890904

Sheet 5. KPI Baselines
A1: Company | B1: Function | C1: Sub-Function | D1: KPI Name | E1: Baseline Value | F1: Target Value | G1: Industry Benchmark | H1: Direction | I1: Timeframe | J1: Measurement Method
A2: 50 Floor | B2: Sales Operations | C2: In-Home Consultations | D2: Appointment Close Rate | E2: 68% | F2: 75% | G2: 72% | H2: ↑ | I2: 12 months | J2: Closed sales / qualified appointments scheduled
A3: 50 Floor | B3: Sales Operations | C3: Lead Management | D3: Customer Acquisition Cost | E3: $420 | F3: $380 | G3: $385 | H3: ↓ | I3: 12 months | J3: Total marketing spend / closed sales
A4: 50 Floor | B4: Installation Coordination | C4: Measurement Validation | D4: Material Waste Rate | E4: 8.2% | F4: 3.0% | G4: 4.5% | H4: ↓ | I4: 9 months | J4: Excess material cost / total material cost
A5: 50 Floor | B5: Installation Coordination | C5: Scheduling | D5: Average Days to Installation | E5: 6 days | F5: 2 days | G5: 3 days | H5: ↓ | I5: 9 months | J5: Calendar days from order to installation start
A6: 50 Floor | B6: Customer Service | C6: Inquiry Resolution | D6: Average Response Time (Peak) | E6: 18 hours | F6: 4 hours | G6: 6 hours | H6: ↓ | I6: 6 months | J6: Time from inquiry receipt to first response
A7: 50 Floor | B7: Customer Service | C7: Inquiry Resolution | D7: Routine Inquiry Deflection Rate | E7: 12% | F7: 60% | G7: 45% | H7: ↑ | I7: 6 months | J7: Self-service resolutions / total inquiries
A8: 50 Floor | B8: Procurement | C8: Supplier Coordination | D8: Order-to-Delivery Cycle Time | E8: 12 days | F8: 7 days | G8: 8 days | H8: ↓ | I8: 12 months | J8: Days from purchase order to material receipt
A9: 50 Floor | B9: Finance | C9: Accounts Payable | D9: Invoice Processing Time | E9: 8 days | F9: 2 days | G9: 3 days | H9: ↓ | I9: 6 months | J9: Days from invoice receipt to payment approval
A10: 50 Floor | B10: Quality Assurance | C10: Pre-Installation Review | D10: Measurement Review Hours | E10: 18,500 hours/year | F10: 5,000 hours/year | G10: Not Available | H10: ↓ | I10: 9 months | J10: Manager hours spent on measurement validation
A11: 50 Floor | B11: Marketing | C11: Content Production | D11: Product Description Creation Time | E11: 4 hours per SKU | F11: 1 hour per SKU | G11: 2 hours per SKU | H11: ↓ | I11: 6 months | J11: Hours from assignment to published content
A12: 50 Floor | B12: Human Resources | C12: Installer Training | D12: Training Material Development Time | E12: 120 hours per module | F12: 40 hours per module | G12: 60 hours per module | H12: ↓ | I12: 9 months | J12: Hours from concept to deployable training content
... A647: WorldWide Electric | B647: Quality Assurance | C647: Inspection & Testing | D647: First-Pass Inspection Success Rate | E647: 76% | F647: 87% | G647: 84% | H647: ↑ | I647: 18 months | J647: Inspections passed without rework / Total inspections

Sheet 6. Friction Points
A1: Company | B1: Function | C1: Sub-Function | D1: Severity | E1: Friction Point | F1: Primary Driver Impact | G1: Estimated Annual Cost
A2: 50 Floor | B2: Customer Service | C2: Inquiry Resolution | D2: High | E2: 72,000 hours annually answering routine questions about scheduling, product specs, and order status | F2: Reduce Cost | G2: $6.1M
A3: 50 Floor | B3: Sales Operations | C3: Proposal Generation | D3: High | E3: Manual creation of installation proposals during in-home visits extends appointment duration by 25 minutes | F3: Grow Revenue | G3: $1.8M
A4: 50 Floor | B4: Sales Operations | C4: Lead Nurture | D4: High | E4: Limited post-appointment follow-up with non-closures results in 32% abandonment of qualified leads | F4: Grow Revenue | G4: $4.2M
A5: 50 Floor | B5: Procurement | C5: Supplier Communication | D5: High | E5: Manual coordination of order changes and delivery schedules with 85 manufacturer partners | F5: Reduce Cost | G5: $1.4M
A6: 50 Floor | B6: Quality Assurance | C6: Installation Review | D6: High | E6: Post-installation quality issues require rework on 6% of jobs due to late detection of specification errors | F6: Decrease Risk | G6: $2.1M
A7: 50 Floor | B7: Operations | C7: Scheduling Optimization | D7: High | E7: Installer route planning done manually results in 15% excess drive time and delayed installations | F7: Reduce Cost | G7: $1.9M
A8: AS Software | B8: Professional Services | C8: Configuration | D8: High | E8: Custom workflow configuration requiring deep product knowledge and 19,000 annual hours on repetitive setup tasks | F8: Reduce Cost | G8: $3.5M
A9: AS Software | B9: Customer Support | C9: Escalation Queue | D9: High | E9: Product specialists spending 15,000 annual hours answering repetitive questions that could be deflected with better self-service | F9: Reduce Cost | G9: $1.9M
A10: AS Software | B10: Sales | C10: Proposal Generation | D10: High | E10: Account executives manually creating custom proposals, ROI models, and competitive analysis consuming 6,240 annual hours | F10: Grow Revenue | G10: $780K
A11: AS Software | B11: Product Management | C11: Documentation | D11: High | E11: Technical writers unable to maintain documentation currency, resulting in 23% of support tickets due to outdated or missing content | F11: Decrease Risk | G11: $3.2M
A12: AmeriVet Partners | B12: Client Services | C12: Appointment Scheduling | D12: High | E12: 18% call abandonment rate during peak hours across 2.4M annual inbound calls | F12: Grow Revenue | G12: $29M
... A645: WorldWide Electric | B645: Project Management | C645: Progress Tracking | D645: Medium | E645: Weekly manual progress reports from 340 projects consolidated in spreadsheets with 4-day lag | F645: Increase Cash Flow | G645: $3.2M

Sheet 7. Strategic Themes
A1: Company | B1: Theme # | C1: Strategic Theme | D1: Current State | E1: Target State | F1: Primary Driver | G1: Secondary Driver
A2: 50 Floor | B2: 1 | C2: Operational Excellence in Installation Coordination | D2: 18,500 hours annually reconciling measurements, 8.2% material waste, 6-day scheduling delays | E2: Automated measurement validation, <3% material waste, 2-day scheduling cycle | F2: Reduce Cost | G2: Decrease Risk
A3: 50 Floor | B3: 2 | C3: Customer Service Efficiency | D3: 72,000 hours on routine inquiries, 18-hour peak response times, limited capacity for complex issues | E3: AI-deflected routine inquiries, 4-hour response times, service team focused on escalations | F3: Reduce Cost | G3: Increase Cash Flow
A4: 50 Floor | B4: 3 | C4: Sales Effectiveness & Conversion | D4: 68% close rate, $420 CAC, limited post-appointment follow-up, manual proposal generation | E4: 75% close rate, $380 CAC, automated nurture sequences, instant proposal delivery | F4: Grow Revenue | G4: Reduce Cost
A5: 50 Floor | B5: 4 | C5: Manufacturer & Supplier Relationship Management | D5: Manual coordination with 85 partners, 12-day order-to-delivery cycle, reactive inventory management | E5: Automated supplier communication, 7-day order-to-delivery, demand-forecasted procurement | F5: Reduce Cost | G5: Increase Cash Flow
A6: 50 Floor | B6: 5 | C6: Quality Assurance & Risk Mitigation | D6: 100% manual measurement review, reactive quality control, post-installation issue resolution | E6: AI-assisted measurement validation, predictive quality flags, pre-installation issue prevention | F6: Decrease Risk | G6: Reduce Cost
A7: AS Software | B7: 1 | C7: Accelerate Professional Services Delivery | D7: 120-day average implementation cycles, 47,000 annual consulting hours on repetitive configuration work, $50K minimum viable deal size | E7: 75-day implementation cycles, 60% reduction in manual configuration hours, $25K minimum viable deal size expansion | F7: Reduce Cost | G7: Grow Revenue
A8: AS Software | B8: 2 | C8: Scale Customer Support Efficiency | D8: 42% first-contact resolution rate, 3.2-day average resolution time for escalated tickets, $14M annual support cost | E8: 68% first-contact resolution rate, 1.5-day average resolution time, $9M annual support cost | F8: Reduce Cost | G8: Decrease Risk
A9: AS Software | B9: 3 | C9: Enhance Sales Productivity | D9: 12 hours per week on non-selling activities, 2.1% cold outreach response rate, 85-day average sales cycle | E9: 6 hours per week on non-selling activities, 4.5% response rate with personalized engagement, 60-day sales cycle | F9: Grow Revenue | G9: Reduce Cost
A10: AS Software | B10: 4 | C10: Improve Product Documentation Quality | D10: 850 monthly hours on content creation, 23% of support tickets due to unclear documentation, quarterly update cadence | E10: 400 monthly hours on content creation, 12% support tickets from documentation gaps, continuous update capability | F10: Decrease Risk | G10: Reduce Cost
A11: AS Software | B11: 5 | C11: Optimize Development Velocity | D11: 35% of engineering time on maintenance and bug fixes, 6-week average feature delivery cycle, legacy code base limiting innovation | E11: 20% engineering time on maintenance, 4-week feature delivery cycle, modernized codebase enabling faster iteration | F11: Reduce Cost | G11: Grow Revenue
A12: AmeriVet Partners | B12: 1 | C12: Clinical Care Standardization | D12: 250 clinics operate on 12 different EMR platforms with inconsistent care protocols | E12: Unified clinical decision support with evidence-based protocols accessible at point of care | F12: Reduce Cost | G12: Decrease Risk
A13: AmeriVet Partners | B13: 2 | C13: Veterinarian Retention & Development | D13: 22% annual veterinarian turnover with $120K replacement cost per departure | E13: AI-assisted clinical support reduces burnout and enables rural market expansion | F13: Reduce Cost | G13: Grow Revenue
... A271: WorldWide Electric | B271: 5 | C271: Enhance Safety Compliance & Risk Management | D271: 340 annual safety incidents, $12M insurance premiums, 4,800 hours incident investigation | E271: 220 annual safety incidents, $9.2M insurance premiums, 2,900 hours incident investigation | F271: Decrease Risk | G271: Reduce Cost

Sheet 8. Priority Roadmap
A1: IMPLEMENTATION ROADMAP
A3: BY PHASE
A5: Q1 IMPLEMENTATIONS (132 use cases)
A6: Company | B6: Use Case | C6: Priority | D6: Total Value ($M) | E6: Time-to-Value (mo)
A7: The Lifetime Value Co | B7: Churn Prediction & Intervention Engine | C7: High | D7: 32.5 | E7: 12
A8: Bespoke Partners | B8: AI-Assisted Pitch Book Assembly | C8: Critical | D8: 9.8 | E8: 6
A9: Chemical Guys | B9: Multi-Format Product Content Generator | C9: Critical | D9: 9.5 | E9: 6
A10: The Lifetime Value Co | B10: Automated Client Insight Reports | C10: Critical | D10: 9 | E10: 6
A11: The Lifetime Value Co | B11: Pre-Sales ROI Calculator | C11: Critical | D11: 8.8 | E11: 6
A12: Chemical Guys | B12: Semantic Product Search & Discovery | C12: Critical | D12: 7.9 | E12: 9
A13: Splash Car Wash | B13: Failed Payment Recovery Orchestrator | C13: High | D13: 7.8 | E13: 6
A14: Splash Car Wash | B14: Interactive Employee Training Assistant | C14: High | D14: 6.4 | E14: 6
A15: Traeger Pellet Grills | B15: Competitive Intelligence Monitoring System | C15: Critical | D15: 4.6 | E15: 4
A16: Bespoke Partners | B16: Automated Market Research Synthesizer | C16: High | D16: 4.2 | E16: 4
A17: TileBar | B17: Automated Product Content Generation | C17: Critical | D17: 3.8 | E17: 6
A18: Bespoke Partners | B18: Comparable Company Screener | C18: High | D18: 3.2 | E18: 4
... A26: Cenegenics | B26: Real-Time Literature Monitoring System | C26: High | D26: 0.7 | E26: 6
A28: Q2 IMPLEMENTATIONS (169 use cases)
A29: Company | B29: Use Case | C29: Priority | D29: Total Value ($M) | E29: Time-to-Value (mo)
A30: Splash Car Wash | B30: Predictive Member Churn Intervention | C30: High | D30: 17.4 | E30: 9
A31: Bespoke Partners | B31: Due Diligence Document Analyzer | C31: Critical | D31: 17.2 | E31: 9
A32: Traeger Pellet Grills | B32: Predictive Demand Planning Engine | C32: High | D32: 12.7 | E32: 15
A33: Splash Car Wash | B33: Single-Wash Membership Conversion Assistant | C33: High | D33: 12.6 | E33: 7
A34: Traeger Pellet Grills | B34: Customer Feedback Intelligence Platform | C34: High | D34: 10.7 | E34: 12
A35: Splash Car Wash | B35: Hyper-Local Marketing Campaign Optimizer | C35: High | D35: 7.8 | E35: 7
A36: Splash Car Wash | B36: Automated Regional Performance Briefings | C36: High | D36: 7.4 | E36: 8
A37: Bespoke Partners | B37: Financial Model Template Generator | C37: High | D37: 6.9 | E37: 7
A38: Chemical Guys | B38: Predictive Demand Forecasting Engine | C38: High | D38: 6.4 | E38: 15
A39: Chemical Guys | B39: Intelligent Wholesale Quote Generator | C39: Critical | D39: 6.1 | E39: 6
A40: Chemical Guys | B40: Intelligent Product Selection Assistant | C40: High | D40: 5.3 | E40: 9
A41: The Lifetime Value Co | B41: Customer Feedback Synthesis Platform | C41: Critical | D41: 4.8 | E41: 6
... A49: Commonwealth Pain | B49: Intelligent Prior Authorization Engine | C49: High | D49: 2.1 | E49: 7
A51: Q3 IMPLEMENTATIONS (133 use cases)
A52: Company | B52: Use Case | C52: Priority | D52: Total Value ($M) | E52: Time-to-Value (mo)
A53: Bespoke Partners | B53: Intelligent CRM Relationship Mapper | C53: High | D53: 14.7 | E53: 12
A54: Splash Car Wash | B54: Equipment Predictive Maintenance Advisor | C54: Medium | D54: 11.6 | E54: 12
A55: Bespoke Partners | B55: Regulatory Compliance Intelligence System | C55: High | D55: 10.7 | E55: 10
A56: Splash Car Wash | B56: Site Selection Decision Support | C56: Medium | D56: 10 | E56: 10
A57: Bespoke Partners | B57: Quality Assurance Workflow Optimizer | C57: High | D57: 9.2 | E57: 8
A58: Splash Car Wash | B58: Dynamic Queue Management System | C58: Medium | D58: 6.7 | E58: 9
A59: Chemical Guys | B59: Real-Time Competitive Intelligence Monitor | C59: Critical | D59: 4.9 | E59: 6
A60: Chemical Guys | B60: Ingredient Compatibility Research Assistant | C60: High | D60: 4.3 | E60: 9
A61: Chemical Guys | B61: Automated Safety Data Sheet Generator | C61: High | D61: 3.4 | E61: 9
A62: TileBar | B62: Demand Forecasting & Inventory Optimization | C62: Medium | D62: 2.9 | E62: 12
A63: Traeger Pellet Grills | B63: Intelligent Warranty Claim Processor | C63: Medium | D63: 2.73 | E63: 9
A64: The Lifetime Value Co | B64: Data Quality Anomaly Detection | C64: High | D64: 2.5 | E64: 9
... A72: Cenegenics | B72: Regulatory Compliance Automation Suite | C72: Medium | D72: 0.8 | E72: 9
A74: Q4 IMPLEMENTATIONS (56 use cases)
A75: Company | B75: Use Case | C75: Priority | D75: Total Value ($M) | E75: Time-to-Value (mo)
A76: Chemical Guys | B76: Automated Collections Workflow | C76: High | D76: 2.1 | E76: 6
A77: TileBar | B77: Supplier Performance Analytics & Communication Hub | C77: Medium | D77: 1.6 | E77: 12
A78: Chemical Guys | B78: Personalized Training Content Generator | C78: Medium | D78: 1.2 | E78: 9
A79: Crane Engineering | B79: Manufacturer Data Aggregator | C79: Medium | D79: 0.9 | E79: 9
A80: P&B Intermodal | B80: Rail Detention Avoidance System | C80: Medium | D80: 0.9 | E80: 9
A81: Veseris | B81: Product Data Reconciliation Engine | C81: Medium | D81: 0.9 | E81: 12
A82: Crane Engineering | B82: Installation Documentation Assistant | C82: Medium | D82: 0.8 | E82: 5
A83: ROI CX Solutions | B83: Methodology IP Packaging Assistant | C83: Medium | D83: 0.8 | E83: 10
A84: Cimsense | B84: Engineering Candidate Pre-Screening System | C84: Medium | D84: 0.7 | E84: 3
A85: Veseris | B85: Interactive Training Companion | C85: Medium | D85: 0.5 | E85: 9
A86: Crane Engineering | B86: Safety Documentation Generator | C86: Medium | D86: 0.4 | E86: 4
A87: Verdesian Life Sciences | B87: Credit Risk Assessment Copilot | C87: Medium | D87: 0.4 | E87: 9
... A95: Scan Global Logistics | B95: Shipment Status Conversational Interface | C95: Medium | D95: 8.2e-06 | E95: 15

Sheet 9. Framework 1
A1: FRAMEWORK 1: VALUE-READINESS MATRIX
A3: This framework assesses both strategic value and implementation readiness.
A5: QUADRANT DEFINITIONS
A6: Champion (Value ≥7, Readiness ≥7): Full resources, 90-day implementation
A7: Quick Win (Value <7, Readiness ≥7): Fast-track, quick value capture
A8: Strategic (Value ≥7, Readiness <7): Invest in readiness first
A9: Foundation (Value <7, Readiness <7): Build capabilities, revisit later
A11: SCORING FORMULAS
A12: Value Score = (EBITDA Impact × 50%) + (Revenue Enable × 25%) + (Risk Reduce × 25%)
A13: Readiness Score = (Org Cap × 35%) + (Data Ready × 35%) + (Tech Infra × 20%) + (Timeline × 10%)
A15: Adjusted EBITDA = Est EBITDA × 15% × (Value Score / 7)
A16: Priority Score = Est EBITDA × ((Value × 0.5) + (Readiness × 0.5)) / 10
A18: COMPANY DISTRIBUTION (see Company Master for full data)
A19: Quadrant | B19: Companies | C19: Total Value ($M)

Sheet 10. Framework 2
A1: FRAMEWORK 2: PORTFOLIO AMPLIFICATION MODEL
A3: Identifies AI initiatives that can replicate across multiple portfolio companies.
A5: PLATFORM CLASSIFICATIONS
A6: Platform: Scalable across 10+ companies (Replication ≥7)
A7: Hybrid: Mix of platform and point solutions (Replication 5-6)
A8: Point: Single company focus (Replication <5)
A10: PORTFOLIO ADJUSTMENT FORMULA
A11: Portfolio-Adjusted Priority = Adjusted Priority × (1 + (Replication Count × 0.1))
A13: HIGH-REPLICATION OPPORTUNITIES
A14: Function | B14: Use Cases | C14: Avg Value ($M) | D14: Replication Potential

Sheet 11. Framework 3
A1: FRAMEWORK 3: HOLD PERIOD VALUE CAPTURE
A3: Maps implementation timeline to holding period and exit strategy.
A5: TRACK DEFINITIONS
A7: T1: EBITDA ACCELERATORS
A8: Timeline: 0-12 months (Year 1)
A9: Investment: 40-50% of AI budget
A10: Focus: Quick EBITDA impact, margin expansion
A11: Criteria: Readiness ≥7, PE-Native Score ≥7, TTV ≤9 months
A13: T2: GROWTH ENABLERS
A14: Timeline: 6-24 months (Years 2-3)
A15: Investment: 30-40% of AI budget
A16: Focus: Revenue scaling, capability building
... A24: TRACK DISTRIBUTION
A25: Track | B25: Use Cases | C25: Total Value ($M) | D25: Avg TTV (months)

Sheet 12. Assumptions
A1: CALCULATION ASSUMPTIONS
A2: Modify these values to update all calculations throughout the workbook
A4: PARAMETER | B4: VALUE | C4: DESCRIPTION
A5: Efficiency Factor | B5: 0.9 | C5: Implementation achievability (0-1)
A6: Adoption Factor | B6: 0.75 | C6: Level 2 data maturity adjustment (0-1)
A7: Confidence Factor | B7: 0.8 | C7: Risk confidence level (0-1)
A9: LABOR RATES
A10: Executive Rate ($/hr) | B10: 395 | C10: Physician/executive fully-loaded cost
A11: Manager Rate ($/hr) | B11: 150 | C11: Senior specialist fully-loaded cost
A12: Specialist Rate ($/hr) | B12: 100 | C12: Operations staff fully-loaded cost
A13: Analyst Rate ($/hr) | B13: 85 | C13: Back-office staff fully-loaded cost
A15: TOKEN COSTS
A16: Input Token Cost ($/M) | B16: 3 | C16: Claude API input tokens per million
A17: Output Token Cost ($/M) | B17: 15 | C17: Claude API output tokens per million
A19: FRAMEWORK THRESHOLDS
A20: Value Threshold | B20: 7 | C20: Minimum for Champion/Strategic quadrant
A21: Readiness Threshold | B21: 7 | C21: Minimum for Champion/Quick Win quadrant
A22: Replication Platform Threshold | B22: 7 | C22: Minimum for Platform classification
A23: T1 TTV Threshold (months) | B23: 9 | C23: Maximum for Track 1 assignment
A24: T2 TTV Threshold (months) | B24: 18 | C24: Maximum for Track 2 assignment

Sheet 13. Data Dictionary
A1: DATA DICTIONARY
A3: FIELD | B3: DESCRIPTION | C3: SOURCE
A5: COMPANY FIELDS
A6: Company Name | B6: Portfolio company name | C6: JSON companyName
A7: Revenue ($M) | B7: Annual revenue in millions | C7: Extracted from Step 0 overview
A8: Est. EBITDA ($M) | B8: Estimated EBITDA (10% of revenue if not stated) | C8: Step 0 or calculated
A9: Employees | B9: Number of employees | C9: Extracted from Step 0
A11: USE CASE FIELDS
A12: Use Case ID | B12: Unique identifier (UC-01 through UC-10) | C12: Step 4 ID
A13: Use Case Name | B13: Descriptive title | C13: Step 4 Use Case Name
A14: Function | B14: Business function (Sales, Procurement, etc.) | C14: Step 4 Function
A15: Sub-Function | B15: Specific operational area | C15: Step 4 Sub-Function
A16: Description | B16: Full narrative description | C16: Step 4 Description
A17: AI Primitives | B17: AI capabilities used (Research, Data Analysis, etc.) | C17: Step 4 AI Primitives
A18: Target Friction | B18: Friction point being addressed | C18: Step 4 Target Friction
A19: Human Checkpoint | B19: Required human oversight point | C19: Step 4 Human-in-the-Loop
A21: BENEFIT FIELDS
A22: Cost Formula | B22: Calculation for cost savings | C22: Step 5 Cost Formula
A23: Cost Benefit ($) | B23: Quantified annual cost savings | C23: Step 5 Cost Benefit
A24: Revenue Formula | B24: Calculation for revenue impact | C24: Step 5 Revenue Formula
A25: Revenue Benefit ($) | B25: Quantified annual revenue growth | C25: Step 5 Revenue Benefit
A26: Risk Formula | B26: Calculation for risk reduction | C26: Step 5 Risk Formula
A27: Risk Benefit ($) | B27: Quantified annual risk reduction | C27: Step 5 Risk Benefit
A28: Cash Flow Formula | B28: Calculation for cash flow acceleration | C28: Step 5 Cash Flow Formula
A29: Cash Flow Benefit ($) | B29: Quantified annual cash flow impact | C29: Step 5 Cash Flow Benefit
A30: Total Annual Value ($) | B30: Sum of all benefit types | C30: Step 5 Total Annual Value
A31: Probability of Success | B31: Estimated implementation success rate (0-1) | C31: Step 5
A33: EFFORT FIELDS
A34: Runs/Month | B34: Expected monthly execution frequency | C34: Step 6 Runs/Month
A35: Monthly Tokens | B35: Estimated monthly token consumption | C35: Step 6 Monthly Tokens
A36: Annual Token Cost ($) | B36: Yearly API expense | C36: Step 6 Annual Token Cost
A37: Time-to-Value (months) | B37: Implementation timeline | C37: Step 6 Time-to-Value
A38: Effort Score (1-5) | B38: Implementation effort rating | C38: Step 6 Effort Score
A39: Data Readiness (1-5) | B39: Current data maturity score | C39: Step 6 Data Readiness
A40: Integration Complexity (1-5) | B40: Technical complexity rating | C40: Step 6 Integration Complexity
A41: Change Mgmt (1-5) | B41: Change management complexity | C41: Step 6 Change Mgmt
A43: PRIORITY FIELDS
A44: Priority Tier | B44: Critical, High, or Medium classification | C44: Step 7 Priority Tier
A45: Priority Score (0-100) | B45: Composite score (Value + TTV + Effort) | C45: Step 7 Priority Score
A46: Value Score (0-40) | B46: Financial value component | C46: Step 7 Value Score
A47: TTV Score (0-30) | B47: Time-to-value component | C47: Step 7 TTV Score
A48: Effort Score (0-30) | B48: Implementation effort component | C48: Step 7 Effort Score
A49: Recommended Phase | B49: Q1, Q2, Q3, or Q4 deployment timing | C49: Step 7 Recommended Phase
A51: FORMULA STANDARDS
A52: Base Formula Pattern | B52: [Units] × [Rate] × [Efficiency 0.90] × [Adoption 0.75] = $Value
A53: Cost Formulas | B53: [Hours Saved] × [Hourly Rate] × 0.90 × 0.75
A54: Revenue Formulas | B54: [Revenue Base] × [Lift %] × 0.95 × 0.75
A55: Risk Formulas | B55: [Exposure] × [Reduction %] × 0.80 × 0.75
A56: Cash Flow Formulas | B56: [Days] × [Daily Value] × 0.85 × 0.75

Sheet KPI Impact Analysis
A1: 0.03
A3: SCENARIO ASSUMPTIONS | E3: FINANCIAL PARAMETERS | J3: PORTFOLIO SUMMARY | P3: IMPROVEMENT DISTRIBUTION | U3: USER GUIDE
A4: Parameter | B4: Value | C4: Description | E4: Parameter | F4: Value | G4: Unit | H4: Description | J4: Metric | K4: Value | L4: Metric | M4: Value | P4: % Improvement Range | Q4: Count | R4: % of Total | U4: How to Use This Analysis:
A5: Achievement Factor | B5: 0.85 | C5: Expected % of target improvement achieved | E5: Avg Hourly Rate - Executive | F5: 395 | G5: $/hr | H5: Physician/executive fully-loaded cost | J5: Total KPIs Analyzed | K5: =COUNTA(A17:A662) -> 646 | L5: Critical Impact KPIs | M5: =COUNTIF(Y17:Y662,"🔥 Critical") -> 216 | P5: > 75% Improvement | Q5: =COUNTIF(L17:L662,">0.75") -> 50 | R5: =IFERROR(Q5/$K$5,0) -> 0.077399381 | U5: 1️⃣ Adjust Assumptions (yellow cells) to model scenarios
A6: Timeline Acceleration | B6: 1 | C6: Multiplier for implementation speed (1.0 = on-time) | E6: Avg Hourly Rate - Manager | F6: 150 | G6: $/hr | H6: Senior specialist fully-loaded cost | J6: Companies Covered | K6: =COUNTA(_xlfn.UNIQUE(A17:A662)) -> 54 | L6: High Impact KPIs | M6: =COUNTIF(Y17:Y662,"⚠️ High") -> 203 | P6: 50% - 75% Improvement | Q6: =COUNTIFS(L17:L662,">0.5",L17:L662,"<=0.75") -> 166 | R6: =IFERROR(Q6/$K$5,0) -> 0.25696594 | U6: 2️⃣ All calculations update automatically
A7: Risk Discount | B7: 0.9 | C7: Risk-adjusted confidence factor | E7: Avg Hourly Rate - Specialist | F7: 100 | G7: $/hr | H7: Operations staff fully-loaded cost | J7: Functions Covered | K7: =COUNTA(_xlfn.UNIQUE(B17:B662)) -> 133 | L7: Medium Impact KPIs | M7: =COUNTIF(Y17:Y662,"📊 Medium") -> 101 | P7: 25% - 50% Improvement | Q7: =COUNTIFS(L17:L662,">0.25",L17:L662,"<=0.5") -> 202 | R7: =IFERROR(Q7/$K$5,0) -> 0.3126935 | U7: 3️⃣ Filter by Company/Function/Impact Category
A8: Adoption Rate | B8: 0.75 | C8: Expected user adoption level | E8: Avg Hourly Rate - Analyst | F8: 85 | G8: $/hr | H8: Back-office staff fully-loaded cost | J8: Avg % Improvement | K8: =IFERROR(AVERAGEIF(L17:L662,">0"),0) -> 0.46827835 | L8: Low Impact KPIs | M8: =COUNTIF(Y17:Y662,"📉 Low") -> 126 | P8: 10% - 25% Improvement | Q8: =COUNTIFS(L17:L662,">0.1",L17:L662,"<=0.25") -> 101 | R8: =IFERROR(Q8/$K$5,0) -> 0.15634675 | U8: 4️⃣ Sort by Impact Score (Col T) for prioritization
A9: Industry Benchmark Weight | B9: 0.5 | C9: Weight given to industry vs. target (0=target only) | E9: Blended Avg Rate | F9: =AVERAGE(F5:F8) -> 182.5 | G9: $/hr | H9: Calculated average across roles | J9: Total Est. Annual Value | K9: =SUM(V17:V662) -> 29135926 | L9: Leading vs Industry | M9: =COUNTIF(R17:R662,"🟢 Leading") -> 19 | P9: < 10% Improvement | Q9: =COUNTIFS(L17:L662,">0",L17:L662,"<=0.1") -> 33 | R9: =IFERROR(Q9/$K$5,0) -> 0.051083591 | U9: 5️⃣ Use Priority Rank (Col U) for quick wins
A10: Benefit Realization Period | B10: 3 | C10: Years to calculate cumulative benefit | E10: Annual Working Hours | F10: 2080 | G10: hrs | H10: Standard FTE hours per year | J10: Total NPV (Multi-Year) | K10: =SUM(W17:W662) -> 72456735 | L10: Lagging vs Industry | M10: =COUNTIF(R17:R662,"🔴 Lagging") -> 478 | P10: Not Calculable | Q10: =COUNTIF(L17:L662,"-")+COUNTIF(L17:L662,0) -> 93 | R10: =IFERROR(Q10/$K$5,0) -> 0.14396285
A11: Discount Rate | B11: 0.1 | C11: For NPV calculations | E11: Revenue per FTE | F11: 250000 | G11: $ | H11: Average revenue productivity | U11: Impact Categories: 🔥Critical (≥50) | ⚠️High (25-49) | 📊Medium (10-24) | 📉Low (<10)
C12: 💡 Yellow cells are editable - change values to update all calculations
A14: DETAILED KPI IMPACT ANALYSIS
A15: SOURCE DATA | K15: BASELINE → TARGET ANALYSIS | O15: INDUSTRY COMPARISON | S15: KPI IMPACT QUANTIFICATION
A16: Company | B16: Function | C16: Sub-Function | D16: KPI Name | E16: Baseline | F16: Target | G16: Industry | H16: Direction | I16: Timeframe | J16: Measurement | K16: Absolute Δ (Baseline→Target) | L16: % Improvement (Baseline→Target) | M16: Adjusted Target (w/ Achievement) | N16: Risk-Adj Δ (Achievable) | O16: Absolute Δ (Industry→Target) | P16: % vs Industry (Target Gap) | Q16: Baseline vs Industry | R16: Competitive Position | S16: Numeric Value | T16: Impact Score | U16: Priority Rank | V16: Est. Annual Value ($) | W16: NPV (Multi-Year) | X16: Months to Breakeven | Y16: Impact Category
A17: ='5. KPI Baselines'!A2 -> 50 Floor | B17: ='5. KPI Baselines'!B2 -> Sales Operations | C17: ='5. KPI Baselines'!C2 -> In-Home Consultations | D17: ='5. KPI Baselines'!D2 -> Appointment Close Rate | E17: ='5. KPI Baselines'!E2 -> 68% | F17: ='5. KPI Baselines'!F2 -> 75% | G17: ='5. KPI Baselines'!G2 -> 72% | H17: ='5. KPI Baselines'!H2 -> ↑ | ... J17: ='5. KPI Baselines'!J2 -> Closed sales / qualified appointments scheduled | K17: =IFERROR(IF(OR(E17="",F17=""),"-",IF(H17="↓",E17&" → "&F17,F17&" - "&E17)),"-") -> 75% - 68% | L17: {=IFERROR(_xlfn.LET(_xlpm.e,E17,_xlpm.f,F17,_xlpm.h,H17,_xlpm.parse,_xlfn.LAMBDA(_xlpm.txt,IFERROR(_xlfn.NUMBERVALUE(SUBSTITUTE(SUBSTITUTE(SUBSTITUTE(SUBSTITUTE(SUBSTITUTE(SUBSTITUTE(SUBSTITUTE(SUBSTITUTE(SUBSTITUTE(SUBSTITUTE(SUBSTITUTE(SUBSTITUTE(SUBSTITUTE(SUBSTITUTE(SUBSTITUTE(SUBSTITUTE(SUBSTITUTE(SUBSTITUTE(SUBSTITUTE(SUBSTITUTE(SUBSTITUTE(SUBSTITUTE(SUBSTITUTE(SUBSTITUTE(SUBSTITUTE(SUBSTITUTE(SUBSTITUTE(SUBSTITUTE(SUBSTITUTE(SUBSTITUTE(SUBSTITUTE(SUBSTITUTE(SUBSTITUTE(SUBSTITUTE(SUBSTITUTE(SUBSTITUTE(LEFT(_xlpm.txt&" ",IFERROR(FIND("(",_xlpm.txt)-1,FIND(" ",_xlpm.txt&" ")+99)),"%",""),"$",""),",","")," days","")," day","")," hours","")," hour","")," minutes","")," minute","")," weeks","")," week","")," months","")," month",""),"hours/year","")," per SKU","")," per module","")," annually","")," per 100 FTE","")," bids","")," findings","")," open items","")," variance","")," per certification",""),"x",""),"M","")," average","")," reports","")," SKUs","")," patients","")," unfavorable","")," contacts","")," monthly","")," per month","")," of available time","")," design reuse","")," ","")),0)),_xlpm.base,_xlpm.parse(_xlpm.e),_xlpm.tgt,_xlpm.parse(_xlpm.f),IF(OR(_xlpm.base=0,_xlpm.tgt=0,_xlpm.e="",_xlpm.f=""),"-",IF(_xlpm.h="↓",(_xlpm.base-_xlpm.tgt)/ABS(_xlpm.base+0.0001),(_xlpm.tgt-_xlpm.base)/ABS(_xlpm.base+0.0001)))),"-")} -> 0.10294103 | M17: {=IFERROR(_xlfn.LET(_xlpm.e,E17,_xlpm.f,F17,_xlpm.h,H17,_xlpm.achv,$B$5,_xlpm.parse,_xlfn.LAMBDA(_xlpm.txt,IFERROR(_xlfn.NUMBERVALUE(SUBSTITUTE(SUBSTITUTE(SUBSTITUTE(SUBSTITUTE(SUBSTITUTE(SUBSTITUTE(SUBSTITUTE(SUBSTITUTE(SUBSTITUTE(SUBSTITUTE(SUBSTITUTE(SUBSTITUTE(SUBSTITUTE(SUBSTITUTE(SUBSTITUTE(SUBSTITUTE(SUBSTITUTE(SUBSTITUTE(SUBSTITUTE(SUBSTITUTE(SUBSTITUTE(SUBSTITUTE(SUBSTITUTE(SUBSTITUTE(SUBSTITUTE(SUBSTITUTE(SUBSTITUTE(SUBSTITUTE(SUBSTITUTE(SUBSTITUTE(SUBSTITUTE(SUBSTITUTE(SUBSTITUTE(SUBSTITUTE(SUBSTITUTE(SUBSTITUTE(LEFT(_xlpm.txt&" ",IFERROR(FIND("(",_xlpm.txt)-1,FIND(" ",_xlpm.txt&" ")+99)),"%",""),"$",""),",","")," days","")," day","")," hours","")," hour","")," minutes","")," minute","")," weeks","")," week","")," months","")," month",""),"hours/year","")," per SKU","")," per module","")," annually","")," per 100 FTE","")," bids","")," findings","")," open items","")," variance","")," per certification",""),"x",""),"M","")," average","")," reports","")," SKUs","")," patients","")," unfavorable","")," contacts","")," monthly","")," per month","")," of available time","")," design reuse","")," ","")),0)),_xlpm.base,_xlpm.parse(_xlpm.e),_xlpm.tgt,_xlpm.parse(_xlpm.f),IF(OR(_xlpm.base=0,_xlpm.tgt=0,_xlpm.e="",_xlpm.f=""),"-",IF(_xlpm.h="↓",ROUND(_xlpm.base-(_xlpm.base-_xlpm.tgt)*_xlpm.achv,1),ROUND(_xlpm.base+(_xlpm.tgt-_xlpm.base)*_xlpm.achv,1)))),"-")} -> 74 | N17: {=IFERROR(_xlfn.LET(_xlpm.e,E17,_xlpm.f,F17,_xlpm.achv,$B$5,_xlpm.rsk,$B$7,_xlpm.parse,_xlfn.LAMBDA(_xlpm.txt,IFERROR(_xlfn.NUMBERVALUE(SUBSTITUTE(SUBSTITUTE(SUBSTITUTE(SUBSTITUTE(SUBSTITUTE(SUBSTITUTE(SUBSTITUTE(SUBSTITUTE(SUBSTITUTE(SUBSTITUTE(SUBSTITUTE(SUBSTITUTE(SUBSTITUTE(SUBSTITUTE(SUBSTITUTE(SUBSTITUTE(SUBSTITUTE(SUBSTITUTE(SUBSTITUTE(SUBSTITUTE(SUBSTITUTE(SUBSTITUTE(SUBSTITUTE(SUBSTITUTE(SUBSTITUTE(SUBSTITUTE(SUBSTITUTE(SUBSTITUTE(SUBSTITUTE(SUBSTITUTE(SUBSTITUTE(SUBSTITUTE(SUBSTITUTE(SUBSTITUTE(SUBSTITUTE(SUBSTITUTE(LEFT(_xlpm.txt&" ",IFERROR(FIND("(",_xlpm.txt)-1,FIND(" ",_xlpm.txt&" ")+99)),"%",""),"$",""),",","")," days","")," day","")," hours","")," hour","")," minutes","")," minute","")," weeks","")," week","")," months","")," month",""),"hours/year","")," per SKU","")," per module","")," annually","")," per 100 FTE","")," bids","")," findings","")," open items","")," variance","")," per certification",""),"x",""),"M","")," average","")," reports","")," SKUs","")," patients","")," unfavorable","")," contacts","")," monthly","")," per month","")," of available time","")," design reuse","")," ","")),0)),_xlpm.base,_xlpm.parse(_xlpm.e),_xlpm.tgt,_xlpm.parse(_xlpm.f),IF(OR(_xlpm.base=0,_xlpm.tgt=0,_xlpm.e="",_xlpm.f=""),"-",ROUND(ABS(_xlpm.base-_xlpm.tgt)*_xlpm.achv*_xlpm.rsk,2))),"-")} -> 5.36 | O17: =IFERROR(IF(OR(G17="",G17="Not Available",F17=""),"-",IF(H17="↓",G17&" → "&F17,F17&" - "&G17)),"-") -> 75% - 72% | P17: {=IFERROR(_xlfn.LET(_xlpm.g,G17,_xlpm.f,F17,_xlpm.h,H17,_xlpm.parse,_xlfn.LAMBDA(_xlpm.txt,IFERROR(_xlfn.NUMBERVALUE(SUBSTITUTE(SUBSTITUTE(SUBSTITUTE(SUBSTITUTE(SUBSTITUTE(SUBSTITUTE(SUBSTITUTE(SUBSTITUTE(SUBSTITUTE(SUBSTITUTE(SUBSTITUTE(SUBSTITUTE(SUBSTITUTE(SUBSTITUTE(SUBSTITUTE(SUBSTITUTE(SUBSTITUTE(SUBSTITUTE(SUBSTITUTE(SUBSTITUTE(SUBSTITUTE(SUBSTITUTE(SUBSTITUTE(SUBSTITUTE(SUBSTITUTE(SUBSTITUTE(SUBSTITUTE(SUBSTITUTE(SUBSTITUTE(SUBSTITUTE(SUBSTITUTE(SUBSTITUTE(SUBSTITUTE(SUBSTITUTE(SUBSTITUTE(SUBSTITUTE(LEFT(_xlpm.txt&" ",IFERROR(FIND("(",_xlpm.txt)-1,FIND(" ",_xlpm.txt&" ")+99)),"%",""),"$",""),",","")," days","")," day","")," hours","")," hour","")," minutes","")," minute","")," weeks","")," week","")," months","")," month",""),"hours/year","")," per SKU","")," per module","")," annually","")," per 100 FTE","")," bids","")," findings","")," open items","")," variance","")," per certification",""),"x",""),"M","")," average","")," reports","")," SKUs","")," patients","")," unfavorable","")," contacts","")," monthly","")," per month","")," of available time","")," design reuse","")," ","")),0)),_xlpm.ind,_xlpm.parse(_xlpm.g),_xlpm.tgt,_xlpm.parse(_xlpm.f),IF(OR(_xlpm.ind=0,_xlpm.tgt=0,_xlpm.g="",_xlpm.g="Not Available",_xlpm.f=""),"-",IF(_xlpm.h="↓",(_xlpm.ind-_xlpm.tgt)/ABS(_xlpm.ind+0.0001),(_xlpm.tgt-_xlpm.ind)/ABS(_xlpm.ind+0.0001)))),"-")} -> 0.041666609 | Q17: {=IFERROR(_xlfn.LET(_xlpm.e,E17,_xlpm.g,G17,_xlpm.h,H17,_xlpm.parse,_xlfn.LAMBDA(_xlpm.txt,IFERROR(_xlfn.NUMBERVALUE(SUBSTITUTE(SUBSTITUTE(SUBSTITUTE(SUBSTITUTE(SUBSTITUTE(SUBSTITUTE(SUBSTITUTE(SUBSTITUTE(SUBSTITUTE(SUBSTITUTE(SUBSTITUTE(SUBSTITUTE(SUBSTITUTE(SUBSTITUTE(SUBSTITUTE(SUBSTITUTE(SUBSTITUTE(SUBSTITUTE(SUBSTITUTE(SUBSTITUTE(SUBSTITUTE(SUBSTITUTE(SUBSTITUTE(SUBSTITUTE(SUBSTITUTE(SUBSTITUTE(SUBSTITUTE(SUBSTITUTE(SUBSTITUTE(SUBSTITUTE(SUBSTITUTE(SUBSTITUTE(SUBSTITUTE(SUBSTITUTE(SUBSTITUTE(SUBSTITUTE(LEFT(_xlpm.txt&" ",IFERROR(FIND("(",_xlpm.txt)-1,FIND(" ",_xlpm.txt&" ")+99)),"%",""),"$",""),",","")," days","")," day","")," hours","")," hour","")," minutes","")," minute","")," weeks","")," week","")," months","")," month",""),"hours/year","")," per SKU","")," per module","")," annually","")," per 100 FTE","")," bids","")," findings","")," open items","")," variance","")," per certification",""),"x",""),"M","")," average","")," reports","")," SKUs","")," patients","")," unfavorable","")," contacts","")," monthly","")," per month","")," of available time","")," design reuse","")," ","")),0)),_xlpm.base,_xlpm.parse(_xlpm.e),_xlpm.ind,_xlpm.parse(_xlpm.g),IF(OR(_xlpm.ind=0,_xlpm.base=0,_xlpm.g="",_xlpm.g="Not Available",_xlpm.e=""),"-",IF(_xlpm.h="↓",IF(_xlpm.base>_xlpm.ind,"Below Industry","Above Industry"),IF(_xlpm.base<_xlpm.ind,"Below Industry","Above Industry")))),"-")} -> Below Industry | R17: =IFERROR(IF(Q17="Below Industry","🔴 Lagging",IF(Q17="Above Industry","🟢 Leading","⚪ N/A")),"⚪ N/A") -> 🔴 Lagging | S17: {=IFERROR(_xlfn.LET(_xlpm.e,E17,_xlpm.parse,_xlfn.LAMBDA(_xlpm.txt,IFERROR(_xlfn.NUMBERVALUE(SUBSTITUTE(SUBSTITUTE(SUBSTITUTE(SUBSTITUTE(SUBSTITUTE(SUBSTITUTE(SUBSTITUTE(SUBSTITUTE(SUBSTITUTE(SUBSTITUTE(SUBSTITUTE(SUBSTITUTE(SUBSTITUTE(SUBSTITUTE(SUBSTITUTE(SUBSTITUTE(SUBSTITUTE(SUBSTITUTE(SUBSTITUTE(SUBSTITUTE(SUBSTITUTE(SUBSTITUTE(SUBSTITUTE(SUBSTITUTE(SUBSTITUTE(SUBSTITUTE(SUBSTITUTE(SUBSTITUTE(SUBSTITUTE(SUBSTITUTE(SUBSTITUTE(SUBSTITUTE(SUBSTITUTE(SUBSTITUTE(SUBSTITUTE(SUBSTITUTE(LEFT(_xlpm.txt&" ",IFERROR(FIND("(",_xlpm.txt)-1,FIND(" ",_xlpm.txt&" ")+99)),"%",""),"$",""),",","")," days","")," day","")," hours","")," hour","")," minutes","")," minute","")," weeks","")," week","")," months","")," month",""),"hours/year","")," per SKU","")," per module","")," annually","")," per 100 FTE","")," bids","")," findings","")," open items","")," variance","")," per certification",""),"x",""),"M","")," average","")," reports","")," SKUs","")," patients","")," unfavorable","")," contacts","")," monthly","")," per month","")," of available time","")," design reuse","")," ","")),0)),ABS(_xlpm.parse(_xlpm.e))),0)} -> 68 | T17: =IFERROR(IF(L17="-",0,ABS(L17)*100),0) -> 10.294103 | U17: =IFERROR(RANK(T17,$T$17:$T$662,0),"-") -> 518 | V17: =IFERROR(IF(OR(L17="-",S17=0),0,S17*ABS(L17)*$F$9*$B$5*$B$7),0) -> 977.28606 | W17: =IFERROR(IF(V17=0,0,V17*(1-(1/(1+$B$11)^$B$10))/$B$11),0) -> 2430.3658 | X17: =IFERROR(IF(V17=0,"-",ROUND(12/(V17/($F$9*40)+0.001),0)),"-") -> 89 | Y17: =IF(T17>=50,"🔥 Critical",IF(T17>=25,"⚠️ High",IF(T17>=10,"📊 Medium","📉 Low"))) -> 📊 Medium
A18: ='5. KPI Baselines'!A3 -> 50 Floor | B18: ='5. KPI Baselines'!B3 -> Sales Operations | C18: ='5. KPI Baselines'!C3 -> Lead Management | D18: ='5. KPI Baselines'!D3 -> Customer Acquisition Cost | E18: ='5. KPI Baselines'!E3 -> $420 | F18: ='5. KPI Baselines'!F3 -> $380 | G18: ='5. KPI Baselines'!G3 -> $385 | H18: ='5. KPI Baselines'!H3 -> ↓ | ... J18: ='5. KPI Baselines'!J3 -> Total marketing spend / closed sales | K18: =IFERROR(IF(OR(E18="",F18=""),"-",IF(H18="↓",E18&" → "&F18,F18&" - "&E18)),"-") -> $420 → $380 | L18: {=IFERROR(_xlfn.LET(_xlpm.e,E18,_xlpm.f,F18,_xlpm.h,H18,_xlpm.parse,_xlfn.LAMBDA(_xlpm.txt,IFERROR(_xlfn.NUMBERVALUE(SUBSTITUTE(SUBSTITUTE(SUBSTITUTE(SUBSTITUTE(SUBSTITUTE(SUBSTITUTE(SUBSTITUTE(SUBSTITUTE(SUBSTITUTE(SUBSTITUTE(SUBSTITUTE(SUBSTITUTE(SUBSTITUTE(SUBSTITUTE(SUBSTITUTE(SUBSTITUTE(SUBSTITUTE(SUBSTITUTE(SUBSTITUTE(SUBSTITUTE(SUBSTITUTE(SUBSTITUTE(SUBSTITUTE(SUBSTITUTE(SUBSTITUTE(SUBSTITUTE(SUBSTITUTE(SUBSTITUTE(SUBSTITUTE(SUBSTITUTE(SUBSTITUTE(SUBSTITUTE(SUBSTITUTE(SUBSTITUTE(SUBSTITUTE(SUBSTITUTE(LEFT(_xlpm.txt&" ",IFERROR(FIND("(",_xlpm.txt)-1,FIND(" ",_xlpm.txt&" ")+99)),"%",""),"$",""),",","")," days","")," day","")," hours","")," hour","")," minutes","")," minute","")," weeks","")," week","")," months","")," month",""),"hours/year","")," per SKU","")," per module","")," annually","")," per 100 FTE","")," bids","")," findings","")," open items","")," variance","")," per certification",""),"x",""),"M","")," average","")," reports","")," SKUs","")," patients","")," unfavorable","")," contacts","")," monthly","")," per month","")," of available time","")," design reuse","")," ","")),0)),_xlpm.base,_xlpm.parse(_xlpm.e),_xlpm.tgt,_xlpm.parse(_xlpm.f),IF(OR(_xlpm.base=0,_xlpm.tgt=0,_xlpm.e="",_xlpm.f=""),"-",IF(_xlpm.h="↓",(_xlpm.base-_xlpm.tgt)/ABS(_xlpm.base+0.0001),(_xlpm.tgt-_xlpm.base)/ABS(_xlpm.base+0.0001)))),"-")} -> 0.095238073 | M18: {=IFERROR(_xlfn.LET(_xlpm.e,E18,_xlpm.f,F18,_xlpm.h,H18,_xlpm.achv,$B$5,_xlpm.parse,_xlfn.LAMBDA(_xlpm.txt,IFERROR(_xlfn.NUMBERVALUE(SUBSTITUTE(SUBSTITUTE(SUBSTITUTE(SUBSTITUTE(SUBSTITUTE(SUBSTITUTE(SUBSTITUTE(SUBSTITUTE(SUBSTITUTE(SUBSTITUTE(SUBSTITUTE(SUBSTITUTE(SUBSTITUTE(SUBSTITUTE(SUBSTITUTE(SUBSTITUTE(SUBSTITUTE(SUBSTITUTE(SUBSTITUTE(SUBSTITUTE(SUBSTITUTE(SUBSTITUTE(SUBSTITUTE(SUBSTITUTE(SUBSTITUTE(SUBSTITUTE(SUBSTITUTE(SUBSTITUTE(SUBSTITUTE(SUBSTITUTE(SUBSTITUTE(SUBSTITUTE(SUBSTITUTE(SUBSTITUTE(SUBSTITUTE(SUBSTITUTE(LEFT(_xlpm.txt&" ",IFERROR(FIND("(",_xlpm.txt)-1,FIND(" ",_xlpm.txt&" ")+99)),"%",""),"$",""),",","")," days","")," day","")," hours","")," hour","")," minutes","")," minute","")," weeks","")," week","")," months","")," month",""),"hours/year","")," per SKU","")," per module","")," annually","")," per 100 FTE","")," bids","")," findings","")," open items","")," variance","")," per certification",""),"x",""),"M","")," average","")," reports","")," SKUs","")," patients","")," unfavorable","")," contacts","")," monthly","")," per month","")," of available time","")," design reuse","")," ","")),0)),_xlpm.base,_xlpm.parse(_xlpm.e),_xlpm.tgt,_xlpm.parse(_xlpm.f),IF(OR(_xlpm.base=0,_xlpm.tgt=0,_xlpm.e="",_xlpm.f=""),"-",IF(_xlpm.h="↓",ROUND(_xlpm.base-(_xlpm.base-_xlpm.tgt)*_xlpm.achv,1),ROUND(_xlpm.base+(_xlpm.tgt-_xlpm.base)*_xlpm.achv,1)))),"-")} -> 386 | N18: {=IFERROR(_xlfn.LET(_xlpm.e,E18,_xlpm.f,F18,_xlpm.achv,$B$5,_xlpm.rsk,$B$7,_xlpm.parse,_xlfn.LAMBDA(_xlpm.txt,IFERROR(_xlfn.NUMBERVALUE(SUBSTITUTE(SUBSTITUTE(SUBSTITUTE(SUBSTITUTE(SUBSTITUTE(SUBSTITUTE(SUBSTITUTE(SUBSTITUTE(SUBSTITUTE(SUBSTITUTE(SUBSTITUTE(SUBSTITUTE(SUBSTITUTE(SUBSTITUTE(SUBSTITUTE(SUBSTITUTE(SUBSTITUTE(SUBSTITUTE(SUBSTITUTE(SUBSTITUTE(SUBSTITUTE(SUBSTITUTE(SUBSTITUTE(SUBSTITUTE(SUBSTITUTE(SUBSTITUTE(SUBSTITUTE(SUBSTITUTE(SUBSTITUTE(SUBSTITUTE(SUBSTITUTE(SUBSTITUTE(SUBSTITUTE(SUBSTITUTE(SUBSTITUTE(SUBSTITUTE(LEFT(_xlpm.txt&" ",IFERROR(FIND("(",_xlpm.txt)-1,FIND(" ",_xlpm.txt&" ")+99)),"%",""),"$",""),",","")," days","")," day","")," hours","")," hour","")," minutes","")," minute","")," weeks","")," week","")," months","")," month",""),"hours/year","")," per SKU","")," per module","")," annually","")," per 100 FTE","")," bids","")," findings","")," open items","")," variance","")," per certification",""),"x",""),"M","")," average","")," reports","")," SKUs","")," patients","")," unfavorable","")," contacts","")," monthly","")," per month","")," of available time","")," design reuse","")," ","")),0)),_xlpm.base,_xlpm.parse(_xlpm.e),_xlpm.tgt,_xlpm.parse(_xlpm.f),IF(OR(_xlpm.base=0,_xlpm.tgt=0,_xlpm.e="",_xlpm.f=""),"-",ROUND(ABS(_xlpm.base-_xlpm.tgt)*_xlpm.achv*_xlpm.rsk,2))),"-")} -> 30.6 | O18: =IFERROR(IF(OR(G18="",G18="Not Available",F18=""),"-",IF(H18="↓",G18&" → "&F18,F18&" - "&G18)),"-") -> $385 → $380 | P18: {=IFERROR(_xlfn.LET(_xlpm.g,G18,_xlpm.f,F18,_xlpm.h,H18,_xlpm.parse,_xlfn.LAMBDA(_xlpm.txt,IFERROR(_xlfn.NUMBERVALUE(SUBSTITUTE(SUBSTITUTE(SUBSTITUTE(SUBSTITUTE(SUBSTITUTE(SUBSTITUTE(SUBSTITUTE(SUBSTITUTE(SUBSTITUTE(SUBSTITUTE(SUBSTITUTE(SUBSTITUTE(SUBSTITUTE(SUBSTITUTE(SUBSTITUTE(SUBSTITUTE(SUBSTITUTE(SUBSTITUTE(SUBSTITUTE(SUBSTITUTE(SUBSTITUTE(SUBSTITUTE(SUBSTITUTE(SUBSTITUTE(SUBSTITUTE(SUBSTITUTE(SUBSTITUTE(SUBSTITUTE(SUBSTITUTE(SUBSTITUTE(SUBSTITUTE(SUBSTITUTE(SUBSTITUTE(SUBSTITUTE(SUBSTITUTE(SUBSTITUTE(LEFT(_xlpm.txt&" ",IFERROR(FIND("(",_xlpm.txt)-1,FIND(" ",_xlpm.txt&" ")+99)),"%",""),"$",""),",","")," days","")," day","")," hours","")," hour","")," minutes","")," minute","")," weeks","")," week","")," months","")," month",""),"hours/year","")," per SKU","")," per module","")," annually","")," per 100 FTE","")," bids","")," findings","")," open items","")," variance","")," per certification",""),"x",""),"M","")," average","")," reports","")," SKUs","")," patients","")," unfavorable","")," contacts","")," monthly","")," per month","")," of available time","")," design reuse","")," ","")),0)),_xlpm.ind,_xlpm.parse(_xlpm.g),_xlpm.tgt,_xlpm.parse(_xlpm.f),IF(OR(_xlpm.ind=0,_xlpm.tgt=0,_xlpm.g="",_xlpm.g="Not Available",_xlpm.f=""),"-",IF(_xlpm.h="↓",(_xlpm.ind-_xlpm.tgt)/ABS(_xlpm.ind+0.0001),(_xlpm.tgt-_xlpm.ind)/ABS(_xlpm.ind+0.0001)))),"-")} -> 0.01298701 | Q18: {=IFERROR(_xlfn.LET(_xlpm.e,E18,_xlpm.g,G18,_xlpm.h,H18,_xlpm.parse,_xlfn.LAMBDA(_xlpm.txt,IFERROR(_xlfn.NUMBERVALUE(SUBSTITUTE(SUBSTITUTE(SUBSTITUTE(SUBSTITUTE(SUBSTITUTE(SUBSTITUTE(SUBSTITUTE(SUBSTITUTE(SUBSTITUTE(SUBSTITUTE(SUBSTITUTE(SUBSTITUTE(SUBSTITUTE(SUBSTITUTE(SUBSTITUTE(SUBSTITUTE(SUBSTITUTE(SUBSTITUTE(SUBSTITUTE(SUBSTITUTE(SUBSTITUTE(SUBSTITUTE(SUBSTITUTE(SUBSTITUTE(SUBSTITUTE(SUBSTITUTE(SUBSTITUTE(SUBSTITUTE(SUBSTITUTE(SUBSTITUTE(SUBSTITUTE(SUBSTITUTE(SUBSTITUTE(SUBSTITUTE(SUBSTITUTE(SUBSTITUTE(LEFT(_xlpm.txt&" ",IFERROR(FIND("(",_xlpm.txt)-1,FIND(" ",_xlpm.txt&" ")+99)),"%",""),"$",""),",","")," days","")," day","")," hours","")," hour","")," minutes","")," minute","")," weeks","")," week","")," months","")," month",""),"hours/year","")," per SKU","")," per module","")," annually","")," per 100 FTE","")," bids","")," findings","")," open items","")," variance","")," per certification",""),"x",""),"M","")," average","")," reports","")," SKUs","")," patients","")," unfavorable","")," contacts","")," monthly","")," per month","")," of available time","")," design reuse","")," ","")),0)),_xlpm.base,_xlpm.parse(_xlpm.e),_xlpm.ind,_xlpm.parse(_xlpm.g),IF(OR(_xlpm.ind=0,_xlpm.base=0,_xlpm.g="",_xlpm.g="Not Available",_xlpm.e=""),"-",IF(_xlpm.h="↓",IF(_xlpm.base>_xlpm.ind,"Below Industry","Above Industry"),IF(_xlpm.base<_xlpm.ind,"Below Industry","Above Industry")))),"-")} -> Below Industry | R18: =IFERROR(IF(Q18="Below Industry","🔴 Lagging",IF(Q18="Above Industry","🟢 Leading","⚪ N/A")),"⚪ N/A") -> 🔴 Lagging | S18: {=IFERROR(_xlfn.LET(_xlpm.e,E18,_xlpm.parse,_xlfn.LAMBDA(_xlpm.txt,IFERROR(_xlfn.NUMBERVALUE(SUBSTITUTE(SUBSTITUTE(SUBSTITUTE(SUBSTITUTE(SUBSTITUTE(SUBSTITUTE(SUBSTITUTE(SUBSTITUTE(SUBSTITUTE(SUBSTITUTE(SUBSTITUTE(SUBSTITUTE(SUBSTITUTE(SUBSTITUTE(SUBSTITUTE(SUBSTITUTE(SUBSTITUTE(SUBSTITUTE(SUBSTITUTE(SUBSTITUTE(SUBSTITUTE(SUBSTITUTE(SUBSTITUTE(SUBSTITUTE(SUBSTITUTE(SUBSTITUTE(SUBSTITUTE(SUBSTITUTE(SUBSTITUTE(SUBSTITUTE(SUBSTITUTE(SUBSTITUTE(SUBSTITUTE(SUBSTITUTE(SUBSTITUTE(SUBSTITUTE(LEFT(_xlpm.txt&" ",IFERROR(FIND("(",_xlpm.txt)-1,FIND(" ",_xlpm.txt&" ")+99)),"%",""),"$",""),",","")," days","")," day","")," hours","")," hour","")," minutes","")," minute","")," weeks","")," week","")," months","")," month",""),"hours/year","")," per SKU","")," per module","")," annually","")," per 100 FTE","")," bids","")," findings","")," open items","")," variance","")," per certification",""),"x",""),"M","")," average","")," reports","")," SKUs","")," patients","")," unfavorable","")," contacts","")," monthly","")," per month","")," of available time","")," design reuse","")," ","")),0)),ABS(_xlpm.parse(_xlpm.e))),0)} -> 420 | T18: =IFERROR(IF(L18="-",0,ABS(L18)*100),0) -> 9.5238073 | U18: =IFERROR(RANK(T18,$T$17:$T$662,0),"-") -> 522 | V18: =IFERROR(IF(OR(L18="-",S18=0),0,S18*ABS(L18)*$F$9*$B$5*$B$7),0) -> 5584.4987 | W18: =IFERROR(IF(V18=0,0,V18*(1-(1/(1+$B$11)^$B$10))/$B$11),0) -> 13887.822 | X18: =IFERROR(IF(V18=0,"-",ROUND(12/(V18/($F$9*40)+0.001),0)),"-") -> 16 | Y18: =IF(T18>=50,"🔥 Critical",IF(T18>=25,"⚠️ High",IF(T18>=10,"📊 Medium","📉 Low"))) -> 📉 Low
A19: ='5. KPI Baselines'!A4 -> 50 Floor | B19: ='5. KPI Baselines'!B4 -> Installation Coordination | C19: ='5. KPI Baselines'!C4 -> Measurement Validation | D19: ='5. KPI Baselines'!D4 -> Material Waste Rate | E19: ='5. KPI Baselines'!E4 -> 8.2% | F19: ='5. KPI Baselines'!F4 -> 3.0% | G19: ='5. KPI Baselines'!G4 -> 4.5% | H19: ='5. KPI Baselines'!H4 -> ↓ | ... J19: ='5. KPI Baselines'!J4 -> Excess material cost / total material cost | K19: =IFERROR(IF(OR(E19="",F19=""),"-",IF(H19="↓",E19&" → "&F19,F19&" - "&E19)),"-") -> 8.2% → 3.0% | L19: {=IFERROR(_xlfn.LET(_xlpm.e,E19,_xlpm.f,F19,_xlpm.h,H19,_xlpm.parse,_xlfn.LAMBDA(_xlpm.txt,IFERROR(_xlfn.NUMBERVALUE(SUBSTITUTE(SUBSTITUTE(SUBSTITUTE(SUBSTITUTE(SUBSTITUTE(SUBSTITUTE(SUBSTITUTE(SUBSTITUTE(SUBSTITUTE(SUBSTITUTE(SUBSTITUTE(SUBSTITUTE(SUBSTITUTE(SUBSTITUTE(SUBSTITUTE(SUBSTITUTE(SUBSTITUTE(SUBSTITUTE(SUBSTITUTE(SUBSTITUTE(SUBSTITUTE(SUBSTITUTE(SUBSTITUTE(SUBSTITUTE(SUBSTITUTE(SUBSTITUTE(SUBSTITUTE(SUBSTITUTE(SUBSTITUTE(SUBSTITUTE(SUBSTITUTE(SUBSTITUTE(SUBSTITUTE(SUBSTITUTE(SUBSTITUTE(SUBSTITUTE(LEFT(_xlpm.txt&" ",IFERROR(FIND("(",_xlpm.txt)-1,FIND(" ",_xlpm.txt&" ")+99)),"%",""),"$",""),",","")," days","")," day","")," hours","")," hour","")," minutes","")," minute","")," weeks","")," week","")," months","")," month",""),"hours/year","")," per SKU","")," per module","")," annually","")," per 100 FTE","")," bids","")," findings","")," open items","")," variance","")," per certification",""),"x",""),"M","")," average","")," reports","")," SKUs","")," patients","")," unfavorable","")," contacts","")," monthly","")," per month","")," of available time","")," design reuse","")," ","")),0)),_xlpm.base,_xlpm.parse(_xlpm.e),_xlpm.tgt,_xlpm.parse(_xlpm.f),IF(OR(_xlpm.base=0,_xlpm.tgt=0,_xlpm.e="",_xlpm.f=""),"-",IF(_xlpm.h="↓",(_xlpm.base-_xlpm.tgt)/ABS(_xlpm.base+0.0001),(_xlpm.tgt-_xlpm.base)/ABS(_xlpm.base+0.0001)))),"-")} -> 0.63413861 | M19: {=IFERROR(_xlfn.LET(_xlpm.e,E19,_xlpm.f,F19,_xlpm.h,H19,_xlpm.achv,$B$5,_xlpm.parse,_xlfn.LAMBDA(_xlpm.txt,IFERROR(_xlfn.NUMBERVALUE(SUBSTITUTE(SUBSTITUTE(SUBSTITUTE(SUBSTITUTE(SUBSTITUTE(SUBSTITUTE(SUBSTITUTE(SUBSTITUTE(SUBSTITUTE(SUBSTITUTE(SUBSTITUTE(SUBSTITUTE(SUBSTITUTE(SUBSTITUTE(SUBSTITUTE(SUBSTITUTE(SUBSTITUTE(SUBSTITUTE(SUBSTITUTE(SUBSTITUTE(SUBSTITUTE(SUBSTITUTE(SUBSTITUTE(SUBSTITUTE(SUBSTITUTE(SUBSTITUTE(SUBSTITUTE(SUBSTITUTE(SUBSTITUTE(SUBSTITUTE(SUBSTITUTE(SUBSTITUTE(SUBSTITUTE(SUBSTITUTE(SUBSTITUTE(SUBSTITUTE(LEFT(_xlpm.txt&" ",IFERROR(FIND("(",_xlpm.txt)-1,FIND(" ",_xlpm.txt&" ")+99)),"%",""),"$",""),",","")," days","")," day","")," hours","")," hour","")," minutes","")," minute","")," weeks","")," week","")," months","")," month",""),"hours/year","")," per SKU","")," per module","")," annually","")," per 100 FTE","")," bids","")," findings","")," open items","")," variance","")," per certification",""),"x",""),"M","")," average","")," reports","")," SKUs","")," patients","")," unfavorable","")," contacts","")," monthly","")," per month","")," of available time","")," design reuse","")," ","")),0)),_xlpm.base,_xlpm.parse(_xlpm.e),_xlpm.tgt,_xlpm.parse(_xlpm.f),IF(OR(_xlpm.base=0,_xlpm.tgt=0,_xlpm.e="",_xlpm.f=""),"-",IF(_xlpm.h="↓",ROUND(_xlpm.base-(_xlpm.base-_xlpm.tgt)*_xlpm.achv,1),ROUND(_xlpm.base+(_xlpm.tgt-_xlpm.base)*_xlpm.achv,1)))),"-")} -> 3.8 | N19: {=IFERROR(_xlfn.LET(_xlpm.e,E19,_xlpm.f,F19,_xlpm.achv,$B$5,_xlpm.rsk,$B$7,_xlpm.parse,_xlfn.LAMBDA(_xlpm.txt,IFERROR(_xlfn.NUMBERVALUE(SUBSTITUTE(SUBSTITUTE(SUBSTITUTE(SUBSTITUTE(SUBSTITUTE(SUBSTITUTE(SUBSTITUTE(SUBSTITUTE(SUBSTITUTE(SUBSTITUTE(SUBSTITUTE(SUBSTITUTE(SUBSTITUTE(SUBSTITUTE(SUBSTITUTE(SUBSTITUTE(SUBSTITUTE(SUBSTITUTE(SUBSTITUTE(SUBSTITUTE(SUBSTITUTE(SUBSTITUTE(SUBSTITUTE(SUBSTITUTE(SUBSTITUTE(SUBSTITUTE(SUBSTITUTE(SUBSTITUTE(SUBSTITUTE(SUBSTITUTE(SUBSTITUTE(SUBSTITUTE(SUBSTITUTE(SUBSTITUTE(SUBSTITUTE(SUBSTITUTE(LEFT(_xlpm.txt&" ",IFERROR(FIND("(",_xlpm.txt)-1,FIND(" ",_xlpm.txt&" ")+99)),"%",""),"$",""),",","")," days","")," day","")," hours","")," hour","")," minutes","")," minute","")," weeks","")," week","")," months","")," month",""),"hours/year","")," per SKU","")," per module","")," annually","")," per 100 FTE","")," bids","")," findings","")," open items","")," variance","")," per certification",""),"x",""),"M","")," average","")," reports","")," SKUs","")," patients","")," unfavorable","")," contacts","")," monthly","")," per month","")," of available time","")," design reuse","")," ","")),0)),_xlpm.base,_xlpm.parse(_xlpm.e),_xlpm.tgt,_xlpm.parse(_xlpm.f),IF(OR(_xlpm.base=0,_xlpm.tgt=0,_xlpm.e="",_xlpm.f=""),"-",ROUND(ABS(_xlpm.base-_xlpm.tgt)*_xlpm.achv*_xlpm.rsk,2))),"-")} -> 3.98 | O19: =IFERROR(IF(OR(G19="",G19="Not Available",F19=""),"-",IF(H19="↓",G19&" → "&F19,F19&" - "&G19)),"-") -> 4.5% → 3.0% | P19: {=IFERROR(_xlfn.LET(_xlpm.g,G19,_xlpm.f,F19,_xlpm.h,H19,_xlpm.parse,_xlfn.LAMBDA(_xlpm.txt,IFERROR(_xlfn.NUMBERVALUE(SUBSTITUTE(SUBSTITUTE(SUBSTITUTE(SUBSTITUTE(SUBSTITUTE(SUBSTITUTE(SUBSTITUTE(SUBSTITUTE(SUBSTITUTE(SUBSTITUTE(SUBSTITUTE(SUBSTITUTE(SUBSTITUTE(SUBSTITUTE(SUBSTITUTE(SUBSTITUTE(SUBSTITUTE(SUBSTITUTE(SUBSTITUTE(SUBSTITUTE(SUBSTITUTE(SUBSTITUTE(SUBSTITUTE(SUBSTITUTE(SUBSTITUTE(SUBSTITUTE(SUBSTITUTE(SUBSTITUTE(SUBSTITUTE(SUBSTITUTE(SUBSTITUTE(SUBSTITUTE(SUBSTITUTE(SUBSTITUTE(SUBSTITUTE(SUBSTITUTE(LEFT(_xlpm.txt&" ",IFERROR(FIND("(",_xlpm.txt)-1,FIND(" ",_xlpm.txt&" ")+99)),"%",""),"$",""),",","")," days","")," day","")," hours","")," hour","")," minutes","")," minute","")," weeks","")," week","")," months","")," month",""),"hours/year","")," per SKU","")," per module","")," annually","")," per 100 FTE","")," bids","")," findings","")," open items","")," variance","")," per certification",""),"x",""),"M","")," average","")," reports","")," SKUs","")," patients","")," unfavorable","")," contacts","")," monthly","")," per month","")," of available time","")," design reuse","")," ","")),0)),_xlpm.ind,_xlpm.parse(_xlpm.g),_xlpm.tgt,_xlpm.parse(_xlpm.f),IF(OR(_xlpm.ind=0,_xlpm.tgt=0,_xlpm.g="",_xlpm.g="Not Available",_xlpm.f=""),"-",IF(_xlpm.h="↓",(_xlpm.ind-_xlpm.tgt)/ABS(_xlpm.ind+0.0001),(_xlpm.tgt-_xlpm.ind)/ABS(_xlpm.ind+0.0001)))),"-")} -> 0.33332593 | Q19: {=IFERROR(_xlfn.LET(_xlpm.e,E19,_xlpm.g,G19,_xlpm.h,H19,_xlpm.parse,_xlfn.LAMBDA(_xlpm.txt,IFERROR(_xlfn.NUMBERVALUE(SUBSTITUTE(SUBSTITUTE(SUBSTITUTE(SUBSTITUTE(SUBSTITUTE(SUBSTITUTE(SUBSTITUTE(SUBSTITUTE(SUBSTITUTE(SUBSTITUTE(SUBSTITUTE(SUBSTITUTE(SUBSTITUTE(SUBSTITUTE(SUBSTITUTE(SUBSTITUTE(SUBSTITUTE(SUBSTITUTE(SUBSTITUTE(SUBSTITUTE(SUBSTITUTE(SUBSTITUTE(SUBSTITUTE(SUBSTITUTE(SUBSTITUTE(SUBSTITUTE(SUBSTITUTE(SUBSTITUTE(SUBSTITUTE(SUBSTITUTE(SUBSTITUTE(SUBSTITUTE(SUBSTITUTE(SUBSTITUTE(SUBSTITUTE(SUBSTITUTE(LEFT(_xlpm.txt&" ",IFERROR(FIND("(",_xlpm.txt)-1,FIND(" ",_xlpm.txt&" ")+99)),"%",""),"$",""),",","")," days","")," day","")," hours","")," hour","")," minutes","")," minute","")," weeks","")," week","")," months","")," month",""),"hours/year","")," per SKU","")," per module","")," annually","")," per 100 FTE","")," bids","")," findings","")," open items","")," variance","")," per certification",""),"x",""),"M","")," average","")," reports","")," SKUs","")," patients","")," unfavorable","")," contacts","")," monthly","")," per month","")," of available time","")," design reuse","")," ","")),0)),_xlpm.base,_xlpm.parse(_xlpm.e),_xlpm.ind,_xlpm.parse(_xlpm.g),IF(OR(_xlpm.ind=0,_xlpm.base=0,_xlpm.g="",_xlpm.g="Not Available",_xlpm.e=""),"-",IF(_xlpm.h="↓",IF(_xlpm.base>_xlpm.ind,"Below Industry","Above Industry"),IF(_xlpm.base<_xlpm.ind,"Below Industry","Above Industry")))),"-")} -> Below Industry | R19: =IFERROR(IF(Q19="Below Industry","🔴 Lagging",IF(Q19="Above Industry","🟢 Leading","⚪ N/A")),"⚪ N/A") -> 🔴 Lagging | S19: {=IFERROR(_xlfn.LET(_xlpm.e,E19,_xlpm.parse,_xlfn.LAMBDA(_xlpm.txt,IFERROR(_xlfn.NUMBERVALUE(SUBSTITUTE(SUBSTITUTE(SUBSTITUTE(SUBSTITUTE(SUBSTITUTE(SUBSTITUTE(SUBSTITUTE(SUBSTITUTE(SUBSTITUTE(SUBSTITUTE(SUBSTITUTE(SUBSTITUTE(SUBSTITUTE(SUBSTITUTE(SUBSTITUTE(SUBSTITUTE(SUBSTITUTE(SUBSTITUTE(SUBSTITUTE(SUBSTITUTE(SUBSTITUTE(SUBSTITUTE(SUBSTITUTE(SUBSTITUTE(SUBSTITUTE(SUBSTITUTE(SUBSTITUTE(SUBSTITUTE(SUBSTITUTE(SUBSTITUTE(SUBSTITUTE(SUBSTITUTE(SUBSTITUTE(SUBSTITUTE(SUBSTITUTE(SUBSTITUTE(LEFT(_xlpm.txt&" ",IFERROR(FIND("(",_xlpm.txt)-1,FIND(" ",_xlpm.txt&" ")+99)),"%",""),"$",""),",","")," days","")," day","")," hours","")," hour","")," minutes","")," minute","")," weeks","")," week","")," months","")," month",""),"hours/year","")," per SKU","")," per module","")," annually","")," per 100 FTE","")," bids","")," findings","")," open items","")," variance","")," per certification",""),"x",""),"M","")," average","")," reports","")," SKUs","")," patients","")," unfavorable","")," contacts","")," monthly","")," per month","")," of available time","")," design reuse","")," ","")),0)),ABS(_xlpm.parse(_xlpm.e))),0)} -> 8.2 | T19: =IFERROR(IF(L19="-",0,ABS(L19)*100),0) -> 63.413861 | U19: =IFERROR(RANK(T19,$T$17:$T$662,0),"-") -> 124 | V19: =IFERROR(IF(OR(L19="-",S19=0),0,S19*ABS(L19)*$F$9*$B$5*$B$7),0) -> 725.97615 | W19: =IFERROR(IF(V19=0,0,V19*(1-(1/(1+$B$11)^$B$10))/$B$11),0) -> 1805.3952 | X19: =IFERROR(IF(V19=0,"-",ROUND(12/(V19/($F$9*40)+0.001),0)),"-") -> 119 | Y19: =IF(T19>=50,"🔥 Critical",IF(T19>=25,"⚠️ High",IF(T19>=10,"📊 Medium","📉 Low"))) -> 🔥 Critical
A20: ='5. KPI Baselines'!A5 -> 50 Floor | B20: ='5. KPI Baselines'!B5 -> Installation Coordination | C20: ='5. KPI Baselines'!C5 -> Scheduling | D20: ='5. KPI Baselines'!D5 -> Average Days to Installation | E20: ='5. KPI Baselines'!E5 -> 6 days | F20: ='5. KPI Baselines'!F5 -> 2 days | G20: ='5. KPI Baselines'!G5 -> 3 days | H20: ='5. KPI Baselines'!H5 -> ↓ | ... J20: ='5. KPI Baselines'!J5 -> Calendar days from order to installation start | K20: =IFERROR(IF(OR(E20="",F20=""),"-",IF(H20="↓",E20&" → "&F20,F20&" - "&E20)),"-") -> 6 days → 2 days | L20: {=IFERROR(_xlfn.LET(_xlpm.e,E20,_xlpm.f,F20,_xlpm.h,H20,_xlpm.parse,_xlfn.LAMBDA(_xlpm.txt,IFERROR(_xlfn.NUMBERVALUE(SUBSTITUTE(SUBSTITUTE(SUBSTITUTE(SUBSTITUTE(SUBSTITUTE(SUBSTITUTE(SUBSTITUTE(SUBSTITUTE(SUBSTITUTE(SUBSTITUTE(SUBSTITUTE(SUBSTITUTE(SUBSTITUTE(SUBSTITUTE(SUBSTITUTE(SUBSTITUTE(SUBSTITUTE(SUBSTITUTE(SUBSTITUTE(SUBSTITUTE(SUBSTITUTE(SUBSTITUTE(SUBSTITUTE(SUBSTITUTE(SUBSTITUTE(SUBSTITUTE(SUBSTITUTE(SUBSTITUTE(SUBSTITUTE(SUBSTITUTE(SUBSTITUTE(SUBSTITUTE(SUBSTITUTE(SUBSTITUTE(SUBSTITUTE(SUBSTITUTE(LEFT(_xlpm.txt&" ",IFERROR(FIND("(",_xlpm.txt)-1,FIND(" ",_xlpm.txt&" ")+99)),"%",""),"$",""),",","")," days","")," day","")," hours","")," hour","")," minutes","")," minute","")," weeks","")," week","")," months","")," month",""),"hours/year","")," per SKU","")," per module","")," annually","")," per 100 FTE","")," bids","")," findings","")," open items","")," variance","")," per certification",""),"x",""),"M","")," average","")," reports","")," SKUs","")," patients","")," unfavorable","")," contacts","")," monthly","")," per month","")," of available time","")," design reuse","")," ","")),0)),_xlpm.base,_xlpm.parse(_xlpm.e),_xlpm.tgt,_xlpm.parse(_xlpm.f),IF(OR(_xlpm.base=0,_xlpm.tgt=0,_xlpm.e="",_xlpm.f=""),"-",IF(_xlpm.h="↓",(_xlpm.base-_xlpm.tgt)/ABS(_xlpm.base+0.0001),(_xlpm.tgt-_xlpm.base)/ABS(_xlpm.base+0.0001)))),"-")} -> 0.66665556 | M20: {=IFERROR(_xlfn.LET(_xlpm.e,E20,_xlpm.f,F20,_xlpm.h,H20,_xlpm.achv,$B$5,_xlpm.parse,_xlfn.LAMBDA(_xlpm.txt,IFERROR(_xlfn.NUMBERVALUE(SUBSTITUTE(SUBSTITUTE(SUBSTITUTE(SUBSTITUTE(SUBSTITUTE(SUBSTITUTE(SUBSTITUTE(SUBSTITUTE(SUBSTITUTE(SUBSTITUTE(SUBSTITUTE(SUBSTITUTE(SUBSTITUTE(SUBSTITUTE(SUBSTITUTE(SUBSTITUTE(SUBSTITUTE(SUBSTITUTE(SUBSTITUTE(SUBSTITUTE(SUBSTITUTE(SUBSTITUTE(SUBSTITUTE(SUBSTITUTE(SUBSTITUTE(SUBSTITUTE(SUBSTITUTE(SUBSTITUTE(SUBSTITUTE(SUBSTITUTE(SUBSTITUTE(SUBSTITUTE(SUBSTITUTE(SUBSTITUTE(SUBSTITUTE(SUBSTITUTE(LEFT(_xlpm.txt&" ",IFERROR(FIND("(",_xlpm.txt)-1,FIND(" ",_xlpm.txt&" ")+99)),"%",""),"$",""),",","")," days","")," day","")," hours","")," hour","")," minutes","")," minute","")," weeks","")," week","")," months","")," month",""),"hours/year","")," per SKU","")," per module","")," annually","")," per 100 FTE","")," bids","")," findings","")," open items","")," variance","")," per certification",""),"x",""),"M","")," average","")," reports","")," SKUs","")," patients","")," unfavorable","")," contacts","")," monthly","")," per month","")," of available time","")," design reuse","")," ","")),0)),_xlpm.base,_xlpm.parse(_xlpm.e),_xlpm.tgt,_xlpm.parse(_xlpm.f),IF(OR(_xlpm.base=0,_xlpm.tgt=0,_xlpm.e="",_xlpm.f=""),"-",IF(_xlpm.h="↓",ROUND(_xlpm.base-(_xlpm.base-_xlpm.tgt)*_xlpm.achv,1),ROUND(_xlpm.base+(_xlpm.tgt-_xlpm.base)*_xlpm.achv,1)))),"-")} -> 2.6 | N20: {=IFERROR(_xlfn.LET(_xlpm.e,E20,_xlpm.f,F20,_xlpm.achv,$B$5,_xlpm.rsk,$B$7,_xlpm.parse,_xlfn.LAMBDA(_xlpm.txt,IFERROR(_xlfn.NUMBERVALUE(SUBSTITUTE(SUBSTITUTE(SUBSTITUTE(SUBSTITUTE(SUBSTITUTE(SUBSTITUTE(SUBSTITUTE(SUBSTITUTE(SUBSTITUTE(SUBSTITUTE(SUBSTITUTE(SUBSTITUTE(SUBSTITUTE(SUBSTITUTE(SUBSTITUTE(SUBSTITUTE(SUBSTITUTE(SUBSTITUTE(SUBSTITUTE(SUBSTITUTE(SUBSTITUTE(SUBSTITUTE(SUBSTITUTE(SUBSTITUTE(SUBSTITUTE(SUBSTITUTE(SUBSTITUTE(SUBSTITUTE(SUBSTITUTE(SUBSTITUTE(SUBSTITUTE(SUBSTITUTE(SUBSTITUTE(SUBSTITUTE(SUBSTITUTE(SUBSTITUTE(LEFT(_xlpm.txt&" ",IFERROR(FIND("(",_xlpm.txt)-1,FIND(" ",_xlpm.txt&" ")+99)),"%",""),"$",""),",","")," days","")," day","")," hours","")," hour","")," minutes","")," minute","")," weeks","")," week","")," months","")," month",""),"hours/year","")," per SKU","")," per module","")," annually","")," per 100 FTE","")," bids","")," findings","")," open items","")," variance","")," per certification",""),"x",""),"M","")," average","")," reports","")," SKUs","")," patients","")," unfavorable","")," contacts","")," monthly","")," per month","")," of available time","")," design reuse","")," ","")),0)),_xlpm.base,_xlpm.parse(_xlpm.e),_xlpm.tgt,_xlpm.parse(_xlpm.f),IF(OR(_xlpm.base=0,_xlpm.tgt=0,_xlpm.e="",_xlpm.f=""),"-",ROUND(ABS(_xlpm.base-_xlpm.tgt)*_xlpm.achv*_xlpm.rsk,2))),"-")} -> 3.06 | O20: =IFERROR(IF(OR(G20="",G20="Not Available",F20=""),"-",IF(H20="↓",G20&" → "&F20,F20&" - "&G20)),"-") -> 3 days → 2 days | P20: {=IFERROR(_xlfn.LET(_xlpm.g,G20,_xlpm.f,F20,_xlpm.h,H20,_xlpm.parse,_xlfn.LAMBDA(_xlpm.txt,IFERROR(_xlfn.NUMBERVALUE(SUBSTITUTE(SUBSTITUTE(SUBSTITUTE(SUBSTITUTE(SUBSTITUTE(SUBSTITUTE(SUBSTITUTE(SUBSTITUTE(SUBSTITUTE(SUBSTITUTE(SUBSTITUTE(SUBSTITUTE(SUBSTITUTE(SUBSTITUTE(SUBSTITUTE(SUBSTITUTE(SUBSTITUTE(SUBSTITUTE(SUBSTITUTE(SUBSTITUTE(SUBSTITUTE(SUBSTITUTE(SUBSTITUTE(SUBSTITUTE(SUBSTITUTE(SUBSTITUTE(SUBSTITUTE(SUBSTITUTE(SUBSTITUTE(SUBSTITUTE(SUBSTITUTE(SUBSTITUTE(SUBSTITUTE(SUBSTITUTE(SUBSTITUTE(SUBSTITUTE(LEFT(_xlpm.txt&" ",IFERROR(FIND("(",_xlpm.txt)-1,FIND(" ",_xlpm.txt&" ")+99)),"%",""),"$",""),",","")," days","")," day","")," hours","")," hour","")," minutes","")," minute","")," weeks","")," week","")," months","")," month",""),"hours/year","")," per SKU","")," per module","")," annually","")," per 100 FTE","")," bids","")," findings","")," open items","")," variance","")," per certification",""),"x",""),"M","")," average","")," reports","")," SKUs","")," patients","")," unfavorable","")," contacts","")," monthly","")," per month","")," of available time","")," design reuse","")," ","")),0)),_xlpm.ind,_xlpm.parse(_xlpm.g),_xlpm.tgt,_xlpm.parse(_xlpm.f),IF(OR(_xlpm.ind=0,_xlpm.tgt=0,_xlpm.g="",_xlpm.g="Not Available",_xlpm.f=""),"-",IF(_xlpm.h="↓",(_xlpm.ind-_xlpm.tgt)/ABS(_xlpm.ind+0.0001),(_xlpm.tgt-_xlpm.ind)/ABS(_xlpm.ind+0.0001)))),"-")} -> 0.33332222 | Q20: {=IFERROR(_xlfn.LET(_xlpm.e,E20,_xlpm.g,G20,_xlpm.h,H20,_xlpm.parse,_xlfn.LAMBDA(_xlpm.txt,IFERROR(_xlfn.NUMBERVALUE(SUBSTITUTE(SUBSTITUTE(SUBSTITUTE(SUBSTITUTE(SUBSTITUTE(SUBSTITUTE(SUBSTITUTE(SUBSTITUTE(SUBSTITUTE(SUBSTITUTE(SUBSTITUTE(SUBSTITUTE(SUBSTITUTE(SUBSTITUTE(SUBSTITUTE(SUBSTITUTE(SUBSTITUTE(SUBSTITUTE(SUBSTITUTE(SUBSTITUTE(SUBSTITUTE(SUBSTITUTE(SUBSTITUTE(SUBSTITUTE(SUBSTITUTE(SUBSTITUTE(SUBSTITUTE(SUBSTITUTE(SUBSTITUTE(SUBSTITUTE(SUBSTITUTE(SUBSTITUTE(SUBSTITUTE(SUBSTITUTE(SUBSTITUTE(SUBSTITUTE(LEFT(_xlpm.txt&" ",IFERROR(FIND("(",_xlpm.txt)-1,FIND(" ",_xlpm.txt&" ")+99)),"%",""),"$",""),",","")," days","")," day","")," hours","")," hour","")," minutes","")," minute","")," weeks","")," week","")," months","")," month",""),"hours/year","")," per SKU","")," per module","")," annually","")," per 100 FTE","")," bids","")," findings","")," open items","")," variance","")," per certification",""),"x",""),"M","")," average","")," reports","")," SKUs","")," patients","")," unfavorable","")," contacts","")," monthly","")," per month","")," of available time","")," design reuse","")," ","")),0)),_xlpm.base,_xlpm.parse(_xlpm.e),_xlpm.ind,_xlpm.parse(_xlpm.g),IF(OR(_xlpm.ind=0,_xlpm.base=0,_xlpm.g="",_xlpm.g="Not Available",_xlpm.e=""),"-",IF(_xlpm.h="↓",IF(_xlpm.base>_xlpm.ind,"Below Industry","Above Industry"),IF(_xlpm.base<_xlpm.ind,"Below Industry","Above Industry")))),"-")} -> Below Industry | R20: =IFERROR(IF(Q20="Below Industry","🔴 Lagging",IF(Q20="Above Industry","🟢 Leading","⚪ N/A")),"⚪ N/A") -> 🔴 Lagging | S20: {=IFERROR(_xlfn.LET(_xlpm.e,E20,_xlpm.parse,_xlfn.LAMBDA(_xlpm.txt,IFERROR(_xlfn.NUMBERVALUE(SUBSTITUTE(SUBSTITUTE(SUBSTITUTE(SUBSTITUTE(SUBSTITUTE(SUBSTITUTE(SUBSTITUTE(SUBSTITUTE(SUBSTITUTE(SUBSTITUTE(SUBSTITUTE(SUBSTITUTE(SUBSTITUTE(SUBSTITUTE(SUBSTITUTE(SUBSTITUTE(SUBSTITUTE(SUBSTITUTE(SUBSTITUTE(SUBSTITUTE(SUBSTITUTE(SUBSTITUTE(SUBSTITUTE(SUBSTITUTE(SUBSTITUTE(SUBSTITUTE(SUBSTITUTE(SUBSTITUTE(SUBSTITUTE(SUBSTITUTE(SUBSTITUTE(SUBSTITUTE(SUBSTITUTE(SUBSTITUTE(SUBSTITUTE(SUBSTITUTE(LEFT(_xlpm.txt&" ",IFERROR(FIND("(",_xlpm.txt)-1,FIND(" ",_xlpm.txt&" ")+99)),"%",""),"$",""),",","")," days","")," day","")," hours","")," hour","")," minutes","")," minute","")," weeks","")," week","")," months","")," month",""),"hours/year","")," per SKU","")," per module","")," annually","")," per 100 FTE","")," bids","")," findings","")," open items","")," variance","")," per certification",""),"x",""),"M","")," average","")," reports","")," SKUs","")," patients","")," unfavorable","")," contacts","")," monthly","")," per month","")," of available time","")," design reuse","")," ","")),0)),ABS(_xlpm.parse(_xlpm.e))),0)} -> 6 | T20: =IFERROR(IF(L20="-",0,ABS(L20)*100),0) -> 66.665556 | U20: =IFERROR(RANK(T20,$T$17:$T$662,0),"-") -> 105 | V20: =IFERROR(IF(OR(L20="-",S20=0),0,S20*ABS(L20)*$F$9*$B$5*$B$7),0) -> 558.44069 | W20: =IFERROR(IF(V20=0,0,V20*(1-(1/(1+$B$11)^$B$10))/$B$11),0) -> 1388.7593 | X20: =IFERROR(IF(V20=0,"-",ROUND(12/(V20/($F$9*40)+0.001),0)),"-") -> 155 | Y20: =IF(T20>=50,"🔥 Critical",IF(T20>=25,"⚠️ High",IF(T20>=10,"📊 Medium","📉 Low"))) -> 🔥 Critical
A21: ='5. KPI Baselines'!A6 -> 50 Floor | B21: ='5. KPI Baselines'!B6 -> Customer Service | C21: ='5. KPI Baselines'!C6 -> Inquiry Resolution | D21: ='5. KPI Baselines'!D6 -> Average Response Time (Peak) | E21: ='5. KPI Baselines'!E6 -> 18 hours | F21: ='5. KPI Baselines'!F6 -> 4 hours | G21: ='5. KPI Baselines'!G6 -> 6 hours | H21: ='5. KPI Baselines'!H6 -> ↓ | ... J21: ='5. KPI Baselines'!J6 -> Time from inquiry receipt to first response | K21: =IFERROR(IF(OR(E21="",F21=""),"-",IF(H21="↓",E21&" → "&F21,F21&" - "&E21)),"-") -> 18 hours → 4 hours | L21: {=IFERROR(_xlfn.LET(_xlpm.e,E21,_xlpm.f,F21,_xlpm.h,H21,_xlpm.parse,_xlfn.LAMBDA(_xlpm.txt,IFERROR(_xlfn.NUMBERVALUE(SUBSTITUTE(SUBSTITUTE(SUBSTITUTE(SUBSTITUTE(SUBSTITUTE(SUBSTITUTE(SUBSTITUTE(SUBSTITUTE(SUBSTITUTE(SUBSTITUTE(SUBSTITUTE(SUBSTITUTE(SUBSTITUTE(SUBSTITUTE(SUBSTITUTE(SUBSTITUTE(SUBSTITUTE(SUBSTITUTE(SUBSTITUTE(SUBSTITUTE(SUBSTITUTE(SUBSTITUTE(SUBSTITUTE(SUBSTITUTE(SUBSTITUTE(SUBSTITUTE(SUBSTITUTE(SUBSTITUTE(SUBSTITUTE(SUBSTITUTE(SUBSTITUTE(SUBSTITUTE(SUBSTITUTE(SUBSTITUTE(SUBSTITUTE(SUBSTITUTE(LEFT(_xlpm.txt&" ",IFERROR(FIND("(",_xlpm.txt)-1,FIND(" ",_xlpm.txt&" ")+99)),"%",""),"$",""),",","")," days","")," day","")," hours","")," hour","")," minutes","")," minute","")," weeks","")," week","")," months","")," month",""),"hours/year","")," per SKU","")," per module","")," annually","")," per 100 FTE","")," bids","")," findings","")," open items","")," variance","")," per certification",""),"x",""),"M","")," average","")," reports","")," SKUs","")," patients","")," unfavorable","")," contacts","")," monthly","")," per month","")," of available time","")," design reuse","")," ","")),0)),_xlpm.base,_xlpm.parse(_xlpm.e),_xlpm.tgt,_xlpm.parse(_xlpm.f),IF(OR(_xlpm.base=0,_xlpm.tgt=0,_xlpm.e="",_xlpm.f=""),"-",IF(_xlpm.h="↓",(_xlpm.base-_xlpm.tgt)/ABS(_xlpm.base+0.0001),(_xlpm.tgt-_xlpm.base)/ABS(_xlpm.base+0.0001)))),"-")} -> 0.77777346 | M21: {=IFERROR(_xlfn.LET(_xlpm.e,E21,_xlpm.f,F21,_xlpm.h,H21,_xlpm.achv,$B$5,_xlpm.parse,_xlfn.LAMBDA(_xlpm.txt,IFERROR(_xlfn.NUMBERVALUE(SUBSTITUTE(SUBSTITUTE(SUBSTITUTE(SUBSTITUTE(SUBSTITUTE(SUBSTITUTE(SUBSTITUTE(SUBSTITUTE(SUBSTITUTE(SUBSTITUTE(SUBSTITUTE(SUBSTITUTE(SUBSTITUTE(SUBSTITUTE(SUBSTITUTE(SUBSTITUTE(SUBSTITUTE(SUBSTITUTE(SUBSTITUTE(SUBSTITUTE(SUBSTITUTE(SUBSTITUTE(SUBSTITUTE(SUBSTITUTE(SUBSTITUTE(SUBSTITUTE(SUBSTITUTE(SUBSTITUTE(SUBSTITUTE(SUBSTITUTE(SUBSTITUTE(SUBSTITUTE(SUBSTITUTE(SUBSTITUTE(SUBSTITUTE(SUBSTITUTE(LEFT(_xlpm.txt&" ",IFERROR(FIND("(",_xlpm.txt)-1,FIND(" ",_xlpm.txt&" ")+99)),"%",""),"$",""),",","")," days","")," day","")," hours","")," hour","")," minutes","")," minute","")," weeks","")," week","")," months","")," month",""),"hours/year","")," per SKU","")," per module","")," annually","")," per 100 FTE","")," bids","")," findings","")," open items","")," variance","")," per certification",""),"x",""),"M","")," average","")," reports","")," SKUs","")," patients","")," unfavorable","")," contacts","")," monthly","")," per month","")," of available time","")," design reuse","")," ","")),0)),_xlpm.base,_xlpm.parse(_xlpm.e),_xlpm.tgt,_xlpm.parse(_xlpm.f),IF(OR(_xlpm.base=0,_xlpm.tgt=0,_xlpm.e="",_xlpm.f=""),"-",IF(_xlpm.h="↓",ROUND(_xlpm.base-(_xlpm.base-_xlpm.tgt)*_xlpm.achv,1),ROUND(_xlpm.base+(_xlpm.tgt-_xlpm.base)*_xlpm.achv,1)))),"-")} -> 6.1 | N21: {=IFERROR(_xlfn.LET(_xlpm.e,E21,_xlpm.f,F21,_xlpm.achv,$B$5,_xlpm.rsk,$B$7,_xlpm.parse,_xlfn.LAMBDA(_xlpm.txt,IFERROR(_xlfn.NUMBERVALUE(SUBSTITUTE(SUBSTITUTE(SUBSTITUTE(SUBSTITUTE(SUBSTITUTE(SUBSTITUTE(SUBSTITUTE(SUBSTITUTE(SUBSTITUTE(SUBSTITUTE(SUBSTITUTE(SUBSTITUTE(SUBSTITUTE(SUBSTITUTE(SUBSTITUTE(SUBSTITUTE(SUBSTITUTE(SUBSTITUTE(SUBSTITUTE(SUBSTITUTE(SUBSTITUTE(SUBSTITUTE(SUBSTITUTE(SUBSTITUTE(SUBSTITUTE(SUBSTITUTE(SUBSTITUTE(SUBSTITUTE(SUBSTITUTE(SUBSTITUTE(SUBSTITUTE(SUBSTITUTE(SUBSTITUTE(SUBSTITUTE(SUBSTITUTE(SUBSTITUTE(LEFT(_xlpm.txt&" ",IFERROR(FIND("(",_xlpm.txt)-1,FIND(" ",_xlpm.txt&" ")+99)),"%",""),"$",""),",","")," days","")," day","")," hours","")," hour","")," minutes","")," minute","")," weeks","")," week","")," months","")," month",""),"hours/year","")," per SKU","")," per module","")," annually","")," per 100 FTE","")," bids","")," findings","")," open items","")," variance","")," per certification",""),"x",""),"M","")," average","")," reports","")," SKUs","")," patients","")," unfavorable","")," contacts","")," monthly","")," per month","")," of available time","")," design reuse","")," ","")),0)),_xlpm.base,_xlpm.parse(_xlpm.e),_xlpm.tgt,_xlpm.parse(_xlpm.f),IF(OR(_xlpm.base=0,_xlpm.tgt=0,_xlpm.e="",_xlpm.f=""),"-",ROUND(ABS(_xlpm.base-_xlpm.tgt)*_xlpm.achv*_xlpm.rsk,2))),"-")} -> 10.71 | O21: =IFERROR(IF(OR(G21="",G21="Not Available",F21=""),"-",IF(H21="↓",G21&" → "&F21,F21&" - "&G21)),"-") -> 6 hours → 4 hours | P21: {=IFERROR(_xlfn.LET(_xlpm.g,G21,_xlpm.f,F21,_xlpm.h,H21,_xlpm.parse,_xlfn.LAMBDA(_xlpm.txt,IFERROR(_xlfn.NUMBERVALUE(SUBSTITUTE(SUBSTITUTE(SUBSTITUTE(SUBSTITUTE(SUBSTITUTE(SUBSTITUTE(SUBSTITUTE(SUBSTITUTE(SUBSTITUTE(SUBSTITUTE(SUBSTITUTE(SUBSTITUTE(SUBSTITUTE(SUBSTITUTE(SUBSTITUTE(SUBSTITUTE(SUBSTITUTE(SUBSTITUTE(SUBSTITUTE(SUBSTITUTE(SUBSTITUTE(SUBSTITUTE(SUBSTITUTE(SUBSTITUTE(SUBSTITUTE(SUBSTITUTE(SUBSTITUTE(SUBSTITUTE(SUBSTITUTE(SUBSTITUTE(SUBSTITUTE(SUBSTITUTE(SUBSTITUTE(SUBSTITUTE(SUBSTITUTE(SUBSTITUTE(LEFT(_xlpm.txt&" ",IFERROR(FIND("(",_xlpm.txt)-1,FIND(" ",_xlpm.txt&" ")+99)),"%",""),"$",""),",","")," days","")," day","")," hours","")," hour","")," minutes","")," minute","")," weeks","")," week","")," months","")," month",""),"hours/year","")," per SKU","")," per module","")," annually","")," per 100 FTE","")," bids","")," findings","")," open items","")," variance","")," per certification",""),"x",""),"M","")," average","")," reports","")," SKUs","")," patients","")," unfavorable","")," contacts","")," monthly","")," per month","")," of available time","")," design reuse","")," ","")),0)),_xlpm.ind,_xlpm.parse(_xlpm.g),_xlpm.tgt,_xlpm.parse(_xlpm.f),IF(OR(_xlpm.ind=0,_xlpm.tgt=0,_xlpm.g="",_xlpm.g="Not Available",_xlpm.f=""),"-",IF(_xlpm.h="↓",(_xlpm.ind-_xlpm.tgt)/ABS(_xlpm.ind+0.0001),(_xlpm.tgt-_xlpm.ind)/ABS(_xlpm.ind+0.0001)))),"-")} -> 0.33332778 | Q21: {=IFERROR(_xlfn.LET(_xlpm.e,E21,_xlpm.g,G21,_xlpm.h,H21,_xlpm.parse,_xlfn.LAMBDA(_xlpm.txt,IFERROR(_xlfn.NUMBERVALUE(SUBSTITUTE(SUBSTITUTE(SUBSTITUTE(SUBSTITUTE(SUBSTITUTE(SUBSTITUTE(SUBSTITUTE(SUBSTITUTE(SUBSTITUTE(SUBSTITUTE(SUBSTITUTE(SUBSTITUTE(SUBSTITUTE(SUBSTITUTE(SUBSTITUTE(SUBSTITUTE(SUBSTITUTE(SUBSTITUTE(SUBSTITUTE(SUBSTITUTE(SUBSTITUTE(SUBSTITUTE(SUBSTITUTE(SUBSTITUTE(SUBSTITUTE(SUBSTITUTE(SUBSTITUTE(SUBSTITUTE(SUBSTITUTE(SUBSTITUTE(SUBSTITUTE(SUBSTITUTE(SUBSTITUTE(SUBSTITUTE(SUBSTITUTE(SUBSTITUTE(LEFT(_xlpm.txt&" ",IFERROR(FIND("(",_xlpm.txt)-1,FIND(" ",_xlpm.txt&" ")+99)),"%",""),"$",""),",","")," days","")," day","")," hours","")," hour","")," minutes","")," minute","")," weeks","")," week","")," months","")," month",""),"hours/year","")," per SKU","")," per module","")," annually","")," per 100 FTE","")," bids","")," findings","")," open items","")," variance","")," per certification",""),"x",""),"M","")," average","")," reports","")," SKUs","")," patients","")," unfavorable","")," contacts","")," monthly","")," per month","")," of available time","")," design reuse","")," ","")),0)),_xlpm.base,_xlpm.parse(_xlpm.e),_xlpm.ind,_xlpm.parse(_xlpm.g),IF(OR(_xlpm.ind=0,_xlpm.base=0,_xlpm.g="",_xlpm.g="Not Available",_xlpm.e=""),"-",IF(_xlpm.h="↓",IF(_xlpm.base>_xlpm.ind,"Below Industry","Above Industry"),IF(_xlpm.base<_xlpm.ind,"Below Industry","Above Industry")))),"-")} -> Below Industry | R21: =IFERROR(IF(Q21="Below Industry","🔴 Lagging",IF(Q21="Above Industry","🟢 Leading","⚪ N/A")),"⚪ N/A") -> 🔴 Lagging | S21: {=IFERROR(_xlfn.LET(_xlpm.e,E21,_xlpm.parse,_xlfn.LAMBDA(_xlpm.txt,IFERROR(_xlfn.NUMBERVALUE(SUBSTITUTE(SUBSTITUTE(SUBSTITUTE(SUBSTITUTE(SUBSTITUTE(SUBSTITUTE(SUBSTITUTE(SUBSTITUTE(SUBSTITUTE(SUBSTITUTE(SUBSTITUTE(SUBSTITUTE(SUBSTITUTE(SUBSTITUTE(SUBSTITUTE(SUBSTITUTE(SUBSTITUTE(SUBSTITUTE(SUBSTITUTE(SUBSTITUTE(SUBSTITUTE(SUBSTITUTE(SUBSTITUTE(SUBSTITUTE(SUBSTITUTE(SUBSTITUTE(SUBSTITUTE(SUBSTITUTE(SUBSTITUTE(SUBSTITUTE(SUBSTITUTE(SUBSTITUTE(SUBSTITUTE(SUBSTITUTE(SUBSTITUTE(SUBSTITUTE(LEFT(_xlpm.txt&" ",IFERROR(FIND("(",_xlpm.txt)-1,FIND(" ",_xlpm.txt&" ")+99)),"%",""),"$",""),",","")," days","")," day","")," hours","")," hour","")," minutes","")," minute","")," weeks","")," week","")," months","")," month",""),"hours/year","")," per SKU","")," per module","")," annually","")," per 100 FTE","")," bids","")," findings","")," open items","")," variance","")," per certification",""),"x",""),"M","")," average","")," reports","")," SKUs","")," patients","")," unfavorable","")," contacts","")," monthly","")," per month","")," of available time","")," design reuse","")," ","")),0)),ABS(_xlpm.parse(_xlpm.e))),0)} -> 18 | T21: =IFERROR(IF(L21="-",0,ABS(L21)*100),0) -> 77.777346 | U21: =IFERROR(RANK(T21,$T$17:$T$662,0),"-") -> 45 | V21: =IFERROR(IF(OR(L21="-",S21=0),0,S21*ABS(L21)*$F$9*$B$5*$B$7),0) -> 1954.5641 | W21: =IFERROR(IF(V21=0,0,V21*(1-(1/(1+$B$11)^$B$10))/$B$11),0) -> 4860.7117 | X21: =IFERROR(IF(V21=0,"-",ROUND(12/(V21/($F$9*40)+0.001),0)),"-") -> 45 | Y21: =IF(T21>=50,"🔥 Critical",IF(T21>=25,"⚠️ High",IF(T21>=10,"📊 Medium","📉 Low"))) -> 🔥 Critical
A22: ='5. KPI Baselines'!A7 -> 50 Floor | B22: ='5. KPI Baselines'!B7 -> Customer Service | C22: ='5. KPI Baselines'!C7 -> Inquiry Resolution | D22: ='5. KPI Baselines'!D7 -> Routine Inquiry Deflection Rate | E22: ='5. KPI Baselines'!E7 -> 12% | F22: ='5. KPI Baselines'!F7 -> 60% | G22: ='5. KPI Baselines'!G7 -> 45% | H22: ='5. KPI Baselines'!H7 -> ↑ | ... J22: ='5. KPI Baselines'!J7 -> Self-service resolutions / total inquiries | K22: =IFERROR(IF(OR(E22="",F22=""),"-",IF(H22="↓",E22&" → "&F22,F22&" - "&E22)),"-") -> 60% - 12% | L22: {=IFERROR(_xlfn.LET(_xlpm.e,E22,_xlpm.f,F22,_xlpm.h,H22,_xlpm.parse,_xlfn.LAMBDA(_xlpm.txt,IFERROR(_xlfn.NUMBERVALUE(SUBSTITUTE(SUBSTITUTE(SUBSTITUTE(SUBSTITUTE(SUBSTITUTE(SUBSTITUTE(SUBSTITUTE(SUBSTITUTE(SUBSTITUTE(SUBSTITUTE(SUBSTITUTE(SUBSTITUTE(SUBSTITUTE(SUBSTITUTE(SUBSTITUTE(SUBSTITUTE(SUBSTITUTE(SUBSTITUTE(SUBSTITUTE(SUBSTITUTE(SUBSTITUTE(SUBSTITUTE(SUBSTITUTE(SUBSTITUTE(SUBSTITUTE(SUBSTITUTE(SUBSTITUTE(SUBSTITUTE(SUBSTITUTE(SUBSTITUTE(SUBSTITUTE(SUBSTITUTE(SUBSTITUTE(SUBSTITUTE(SUBSTITUTE(SUBSTITUTE(LEFT(_xlpm.txt&" ",IFERROR(FIND("(",_xlpm.txt)-1,FIND(" ",_xlpm.txt&" ")+99)),"%",""),"$",""),",","")," days","")," day","")," hours","")," hour","")," minutes","")," minute","")," weeks","")," week","")," months","")," month",""),"hours/year","")," per SKU","")," per module","")," annually","")," per 100 FTE","")," bids","")," findings","")," open items","")," variance","")," per certification",""),"x",""),"M","")," average","")," reports","")," SKUs","")," patients","")," unfavorable","")," contacts","")," monthly","")," per month","")," of available time","")," design reuse","")," ","")),0)),_xlpm.base,_xlpm.parse(_xlpm.e),_xlpm.tgt,_xlpm.parse(_xlpm.f),IF(OR(_xlpm.base=0,_xlpm.tgt=0,_xlpm.e="",_xlpm.f=""),"-",IF(_xlpm.h="↓",(_xlpm.base-_xlpm.tgt)/ABS(_xlpm.base+0.0001),(_xlpm.tgt-_xlpm.base)/ABS(_xlpm.base+0.0001)))),"-")} -> 3.9999667 | M22: {=IFERROR(_xlfn.LET(_xlpm.e,E22,_xlpm.f,F22,_xlpm.h,H22,_xlpm.achv,$B$5,_xlpm.parse,_xlfn.LAMBDA(_xlpm.txt,IFERROR(_xlfn.NUMBERVALUE(SUBSTITUTE(SUBSTITUTE(SUBSTITUTE(SUBSTITUTE(SUBSTITUTE(SUBSTITUTE(SUBSTITUTE(SUBSTITUTE(SUBSTITUTE(SUBSTITUTE(SUBSTITUTE(SUBSTITUTE(SUBSTITUTE(SUBSTITUTE(SUBSTITUTE(SUBSTITUTE(SUBSTITUTE(SUBSTITUTE(SUBSTITUTE(SUBSTITUTE(SUBSTITUTE(SUBSTITUTE(SUBSTITUTE(SUBSTITUTE(SUBSTITUTE(SUBSTITUTE(SUBSTITUTE(SUBSTITUTE(SUBSTITUTE(SUBSTITUTE(SUBSTITUTE(SUBSTITUTE(SUBSTITUTE(SUBSTITUTE(SUBSTITUTE(SUBSTITUTE(LEFT(_xlpm.txt&" ",IFERROR(FIND("(",_xlpm.txt)-1,FIND(" ",_xlpm.txt&" ")+99)),"%",""),"$",""),",","")," days","")," day","")," hours","")," hour","")," minutes","")," minute","")," weeks","")," week","")," months","")," month",""),"hours/year","")," per SKU","")," per module","")," annually","")," per 100 FTE","")," bids","")," findings","")," open items","")," variance","")," per certification",""),"x",""),"M","")," average","")," reports","")," SKUs","")," patients","")," unfavorable","")," contacts","")," monthly","")," per month","")," of available time","")," design reuse","")," ","")),0)),_xlpm.base,_xlpm.parse(_xlpm.e),_xlpm.tgt,_xlpm.parse(_xlpm.f),IF(OR(_xlpm.base=0,_xlpm.tgt=0,_xlpm.e="",_xlpm.f=""),"-",IF(_xlpm.h="↓",ROUND(_xlpm.base-(_xlpm.base-_xlpm.tgt)*_xlpm.achv,1),ROUND(_xlpm.base+(_xlpm.tgt-_xlpm.base)*_xlpm.achv,1)))),"-")} -> 52.8 | N22: {=IFERROR(_xlfn.LET(_xlpm.e,E22,_xlpm.f,F22,_xlpm.achv,$B$5,_xlpm.rsk,$B$7,_xlpm.parse,_xlfn.LAMBDA(_xlpm.txt,IFERROR(_xlfn.NUMBERVALUE(SUBSTITUTE(SUBSTITUTE(SUBSTITUTE(SUBSTITUTE(SUBSTITUTE(SUBSTITUTE(SUBSTITUTE(SUBSTITUTE(SUBSTITUTE(SUBSTITUTE(SUBSTITUTE(SUBSTITUTE(SUBSTITUTE(SUBSTITUTE(SUBSTITUTE(SUBSTITUTE(SUBSTITUTE(SUBSTITUTE(SUBSTITUTE(SUBSTITUTE(SUBSTITUTE(SUBSTITUTE(SUBSTITUTE(SUBSTITUTE(SUBSTITUTE(SUBSTITUTE(SUBSTITUTE(SUBSTITUTE(SUBSTITUTE(SUBSTITUTE(SUBSTITUTE(SUBSTITUTE(SUBSTITUTE(SUBSTITUTE(SUBSTITUTE(SUBSTITUTE(LEFT(_xlpm.txt&" ",IFERROR(FIND("(",_xlpm.txt)-1,FIND(" ",_xlpm.txt&" ")+99)),"%",""),"$",""),",","")," days","")," day","")," hours","")," hour","")," minutes","")," minute","")," weeks","")," week","")," months","")," month",""),"hours/year","")," per SKU","")," per module","")," annually","")," per 100 FTE","")," bids","")," findings","")," open items","")," variance","")," per certification",""),"x",""),"M","")," average","")," reports","")," SKUs","")," patients","")," unfavorable","")," contacts","")," monthly","")," per month","")," of available time","")," design reuse","")," ","")),0)),_xlpm.base,_xlpm.parse(_xlpm.e),_xlpm.tgt,_xlpm.parse(_xlpm.f),IF(OR(_xlpm.base=0,_xlpm.tgt=0,_xlpm.e="",_xlpm.f=""),"-",ROUND(ABS(_xlpm.base-_xlpm.tgt)*_xlpm.achv*_xlpm.rsk,2))),"-")} -> 36.72 | O22: =IFERROR(IF(OR(G22="",G22="Not Available",F22=""),"-",IF(H22="↓",G22&" → "&F22,F22&" - "&G22)),"-") -> 60% - 45% | P22: {=IFERROR(_xlfn.LET(_xlpm.g,G22,_xlpm.f,F22,_xlpm.h,H22,_xlpm.parse,_xlfn.LAMBDA(_xlpm.txt,IFERROR(_xlfn.NUMBERVALUE(SUBSTITUTE(SUBSTITUTE(SUBSTITUTE(SUBSTITUTE(SUBSTITUTE(SUBSTITUTE(SUBSTITUTE(SUBSTITUTE(SUBSTITUTE(SUBSTITUTE(SUBSTITUTE(SUBSTITUTE(SUBSTITUTE(SUBSTITUTE(SUBSTITUTE(SUBSTITUTE(SUBSTITUTE(SUBSTITUTE(SUBSTITUTE(SUBSTITUTE(SUBSTITUTE(SUBSTITUTE(SUBSTITUTE(SUBSTITUTE(SUBSTITUTE(SUBSTITUTE(SUBSTITUTE(SUBSTITUTE(SUBSTITUTE(SUBSTITUTE(SUBSTITUTE(SUBSTITUTE(SUBSTITUTE(SUBSTITUTE(SUBSTITUTE(SUBSTITUTE(LEFT(_xlpm.txt&" ",IFERROR(FIND("(",_xlpm.txt)-1,FIND(" ",_xlpm.txt&" ")+99)),"%",""),"$",""),",","")," days","")," day","")," hours","")," hour","")," minutes","")," minute","")," weeks","")," week","")," months","")," month",""),"hours/year","")," per SKU","")," per module","")," annually","")," per 100 FTE","")," bids","")," findings","")," open items","")," variance","")," per certification",""),"x",""),"M","")," average","")," reports","")," SKUs","")," patients","")," unfavorable","")," contacts","")," monthly","")," per month","")," of available time","")," design reuse","")," ","")),0)),_xlpm.ind,_xlpm.parse(_xlpm.g),_xlpm.tgt,_xlpm.parse(_xlpm.f),IF(OR(_xlpm.ind=0,_xlpm.tgt=0,_xlpm.g="",_xlpm.g="Not Available",_xlpm.f=""),"-",IF(_xlpm.h="↓",(_xlpm.ind-_xlpm.tgt)/ABS(_xlpm.ind+0.0001),(_xlpm.tgt-_xlpm.ind)/ABS(_xlpm.ind+0.0001)))),"-")} -> 0.33333259 | Q22: {=IFERROR(_xlfn.LET(_xlpm.e,E22,_xlpm.g,G22,_xlpm.h,H22,_xlpm.parse,_xlfn.LAMBDA(_xlpm.txt,IFERROR(_xlfn.NUMBERVALUE(SUBSTITUTE(SUBSTITUTE(SUBSTITUTE(SUBSTITUTE(SUBSTITUTE(SUBSTITUTE(SUBSTITUTE(SUBSTITUTE(SUBSTITUTE(SUBSTITUTE(SUBSTITUTE(SUBSTITUTE(SUBSTITUTE(SUBSTITUTE(SUBSTITUTE(SUBSTITUTE(SUBSTITUTE(SUBSTITUTE(SUBSTITUTE(SUBSTITUTE(SUBSTITUTE(SUBSTITUTE(SUBSTITUTE(SUBSTITUTE(SUBSTITUTE(SUBSTITUTE(SUBSTITUTE(SUBSTITUTE(SUBSTITUTE(SUBSTITUTE(SUBSTITUTE(SUBSTITUTE(SUBSTITUTE(SUBSTITUTE(SUBSTITUTE(SUBSTITUTE(LEFT(_xlpm.txt&" ",IFERROR(FIND("(",_xlpm.txt)-1,FIND(" ",_xlpm.txt&" ")+99)),"%",""),"$",""),",","")," days","")," day","")," hours","")," hour","")," minutes","")," minute","")," weeks","")," week","")," months","")," month",""),"hours/year","")," per SKU","")," per module","")," annually","")," per 100 FTE","")," bids","")," findings","")," open items","")," variance","")," per certification",""),"x",""),"M","")," average","")," reports","")," SKUs","")," patients","")," unfavorable","")," contacts","")," monthly","")," per month","")," of available time","")," design reuse","")," ","")),0)),_xlpm.base,_xlpm.parse(_xlpm.e),_xlpm.ind,_xlpm.parse(_xlpm.g),IF(OR(_xlpm.ind=0,_xlpm.base=0,_xlpm.g="",_xlpm.g="Not Available",_xlpm.e=""),"-",IF(_xlpm.h="↓",IF(_xlpm.base>_xlpm.ind,"Below Industry","Above Industry"),IF(_xlpm.base<_xlpm.ind,"Below Industry","Above Industry")))),"-")} -> Below Industry | R22: =IFERROR(IF(Q22="Below Industry","🔴 Lagging",IF(Q22="Above Industry","🟢 Leading","⚪ N/A")),"⚪ N/A") -> 🔴 Lagging | S22: {=IFERROR(_xlfn.LET(_xlpm.e,E22,_xlpm.parse,_xlfn.LAMBDA(_xlpm.txt,IFERROR(_xlfn.NUMBERVALUE(SUBSTITUTE(SUBSTITUTE(SUBSTITUTE(SUBSTITUTE(SUBSTITUTE(SUBSTITUTE(SUBSTITUTE(SUBSTITUTE(SUBSTITUTE(SUBSTITUTE(SUBSTITUTE(SUBSTITUTE(SUBSTITUTE(SUBSTITUTE(SUBSTITUTE(SUBSTITUTE(SUBSTITUTE(SUBSTITUTE(SUBSTITUTE(SUBSTITUTE(SUBSTITUTE(SUBSTITUTE(SUBSTITUTE(SUBSTITUTE(SUBSTITUTE(SUBSTITUTE(SUBSTITUTE(SUBSTITUTE(SUBSTITUTE(SUBSTITUTE(SUBSTITUTE(SUBSTITUTE(SUBSTITUTE(SUBSTITUTE(SUBSTITUTE(SUBSTITUTE(LEFT(_xlpm.txt&" ",IFERROR(FIND("(",_xlpm.txt)-1,FIND(" ",_xlpm.txt&" ")+99)),"%",""),"$",""),",","")," days","")," day","")," hours","")," hour","")," minutes","")," minute","")," weeks","")," week","")," months","")," month",""),"hours/year","")," per SKU","")," per module","")," annually","")," per 100 FTE","")," bids","")," findings","")," open items","")," variance","")," per certification",""),"x",""),"M","")," average","")," reports","")," SKUs","")," patients","")," unfavorable","")," contacts","")," monthly","")," per month","")," of available time","")," design reuse","")," ","")),0)),ABS(_xlpm.parse(_xlpm.e))),0)} -> 12 | T22: =IFERROR(IF(L22="-",0,ABS(L22)*100),0) -> 399.99667 | U22: =IFERROR(RANK(T22,$T$17:$T$662,0),"-") -> 1 | V22: =IFERROR(IF(OR(L22="-",S22=0),0,S22*ABS(L22)*$F$9*$B$5*$B$7),0) -> 6701.3442 | W22: =IFERROR(IF(V22=0,0,V22*(1-(1/(1+$B$11)^$B$10))/$B$11),0) -> 16665.251 | X22: =IFERROR(IF(V22=0,"-",ROUND(12/(V22/($F$9*40)+0.001),0)),"-") -> 13 | Y22: =IF(T22>=50,"🔥 Critical",IF(T22>=25,"⚠️ High",IF(T22>=10,"📊 Medium","📉 Low"))) -> 🔥 Critical
A23: ='5. KPI Baselines'!A8 -> 50 Floor | B23: ='5. KPI Baselines'!B8 -> Procurement | C23: ='5. KPI Baselines'!C8 -> Supplier Coordination | D23: ='5. KPI Baselines'!D8 -> Order-to-Delivery Cycle Time | E23: ='5. KPI Baselines'!E8 -> 12 days | F23: ='5. KPI Baselines'!F8 -> 7 days | G23: ='5. KPI Baselines'!G8 -> 8 days | H23: ='5. KPI Baselines'!H8 -> ↓ | ... J23: ='5. KPI Baselines'!J8 -> Days from purchase order to material receipt | K23: =IFERROR(IF(OR(E23="",F23=""),"-",IF(H23="↓",E23&" → "&F23,F23&" - "&E23)),"-") -> 12 days → 7 days | L23: {=IFERROR(_xlfn.LET(_xlpm.e,E23,_xlpm.f,F23,_xlpm.h,H23,_xlpm.parse,_xlfn.LAMBDA(_xlpm.txt,IFERROR(_xlfn.NUMBERVALUE(SUBSTITUTE(SUBSTITUTE(SUBSTITUTE(SUBSTITUTE(SUBSTITUTE(SUBSTITUTE(SUBSTITUTE(SUBSTITUTE(SUBSTITUTE(SUBSTITUTE(SUBSTITUTE(SUBSTITUTE(SUBSTITUTE(SUBSTITUTE(SUBSTITUTE(SUBSTITUTE(SUBSTITUTE(SUBSTITUTE(SUBSTITUTE(SUBSTITUTE(SUBSTITUTE(SUBSTITUTE(SUBSTITUTE(SUBSTITUTE(SUBSTITUTE(SUBSTITUTE(SUBSTITUTE(SUBSTITUTE(SUBSTITUTE(SUBSTITUTE(SUBSTITUTE(SUBSTITUTE(SUBSTITUTE(SUBSTITUTE(SUBSTITUTE(SUBSTITUTE(LEFT(_xlpm.txt&" ",IFERROR(FIND("(",_xlpm.txt)-1,FIND(" ",_xlpm.txt&" ")+99)),"%",""),"$",""),",","")," days","")," day","")," hours","")," hour","")," minutes","")," minute","")," weeks","")," week","")," months","")," month",""),"hours/year","")," per SKU","")," per module","")," annually","")," per 100 FTE","")," bids","")," findings","")," open items","")," variance","")," per certification",""),"x",""),"M","")," average","")," reports","")," SKUs","")," patients","")," unfavorable","")," contacts","")," monthly","")," per month","")," of available time","")," design reuse","")," ","")),0)),_xlpm.base,_xlpm.parse(_xlpm.e),_xlpm.tgt,_xlpm.parse(_xlpm.f),IF(OR(_xlpm.base=0,_xlpm.tgt=0,_xlpm.e="",_xlpm.f=""),"-",IF(_xlpm.h="↓",(_xlpm.base-_xlpm.tgt)/ABS(_xlpm.base+0.0001),(_xlpm.tgt-_xlpm.base)/ABS(_xlpm.base+0.0001)))),"-")} -> 0.41666319 | M23: {=IFERROR(_xlfn.LET(_xlpm.e,E23,_xlpm.f,F23,_xlpm.h,H23,_xlpm.achv,$B$5,_xlpm.parse,_xlfn.LAMBDA(_xlpm.txt,IFERROR(_xlfn.NUMBERVALUE(SUBSTITUTE(SUBSTITUTE(SUBSTITUTE(SUBSTITUTE(SUBSTITUTE(SUBSTITUTE(SUBSTITUTE(SUBSTITUTE(SUBSTITUTE(SUBSTITUTE(SUBSTITUTE(SUBSTITUTE(SUBSTITUTE(SUBSTITUTE(SUBSTITUTE(SUBSTITUTE(SUBSTITUTE(SUBSTITUTE(SUBSTITUTE(SUBSTITUTE(SUBSTITUTE(SUBSTITUTE(SUBSTITUTE(SUBSTITUTE(SUBSTITUTE(SUBSTITUTE(SUBSTITUTE(SUBSTITUTE(SUBSTITUTE(SUBSTITUTE(SUBSTITUTE(SUBSTITUTE(SUBSTITUTE(SUBSTITUTE(SUBSTITUTE(SUBSTITUTE(LEFT(_xlpm.txt&" ",IFERROR(FIND("(",_xlpm.txt)-1,FIND(" ",_xlpm.txt&" ")+99)),"%",""),"$",""),",","")," days","")," day","")," hours","")," hour","")," minutes","")," minute","")," weeks","")," week","")," months","")," month",""),"hours/year","")," per SKU","")," per module","")," annually","")," per 100 FTE","")," bids","")," findings","")," open items","")," variance","")," per certification",""),"x",""),"M","")," average","")," reports","")," SKUs","")," patients","")," unfavorable","")," contacts","")," monthly","")," per month","")," of available time","")," design reuse","")," ","")),0)),_xlpm.base,_xlpm.parse(_xlpm.e),_xlpm.tgt,_xlpm.parse(_xlpm.f),IF(OR(_xlpm.base=0,_xlpm.tgt=0,_xlpm.e="",_xlpm.f=""),"-",IF(_xlpm.h="↓",ROUND(_xlpm.base-(_xlpm.base-_xlpm.tgt)*_xlpm.achv,1),ROUND(_xlpm.base+(_xlpm.tgt-_xlpm.base)*_xlpm.achv,1)))),"-")} -> 7.8 | N23: {=IFERROR(_xlfn.LET(_xlpm.e,E23,_xlpm.f,F23,_xlpm.achv,$B$5,_xlpm.rsk,$B$7,_xlpm.parse,_xlfn.LAMBDA(_xlpm.txt,IFERROR(_xlfn.NUMBERVALUE(SUBSTITUTE(SUBSTITUTE(SUBSTITUTE(SUBSTITUTE(SUBSTITUTE(SUBSTITUTE(SUBSTITUTE(SUBSTITUTE(SUBSTITUTE(SUBSTITUTE(SUBSTITUTE(SUBSTITUTE(SUBSTITUTE(SUBSTITUTE(SUBSTITUTE(SUBSTITUTE(SUBSTITUTE(SUBSTITUTE(SUBSTITUTE(SUBSTITUTE(SUBSTITUTE(SUBSTITUTE(SUBSTITUTE(SUBSTITUTE(SUBSTITUTE(SUBSTITUTE(SUBSTITUTE(SUBSTITUTE(SUBSTITUTE(SUBSTITUTE(SUBSTITUTE(SUBSTITUTE(SUBSTITUTE(SUBSTITUTE(SUBSTITUTE(SUBSTITUTE(LEFT(_xlpm.txt&" ",IFERROR(FIND("(",_xlpm.txt)-1,FIND(" ",_xlpm.txt&" ")+99)),"%",""),"$",""),",","")," days","")," day","")," hours","")," hour","")," minutes","")," minute","")," weeks","")," week","")," months","")," month",""),"hours/year","")," per SKU","")," per module","")," annually","")," per 100 FTE","")," bids","")," findings","")," open items","")," variance","")," per certification",""),"x",""),"M","")," average","")," reports","")," SKUs","")," patients","")," unfavorable","")," contacts","")," monthly","")," per month","")," of available time","")," design reuse","")," ","")),0)),_xlpm.base,_xlpm.parse(_xlpm.e),_xlpm.tgt,_xlpm.parse(_xlpm.f),IF(OR(_xlpm.base=0,_xlpm.tgt=0,_xlpm.e="",_xlpm.f=""),"-",ROUND(ABS(_xlpm.base-_xlpm.tgt)*_xlpm.achv*_xlpm.rsk,2))),"-")} -> 3.83 | O23: =IFERROR(IF(OR(G23="",G23="Not Available",F23=""),"-",IF(H23="↓",G23&" → "&F23,F23&" - "&G23)),"-") -> 8 days → 7 days | P23: {=IFERROR(_xlfn.LET(_xlpm.g,G23,_xlpm.f,F23,_xlpm.h,H23,_xlpm.parse,_xlfn.LAMBDA(_xlpm.txt,IFERROR(_xlfn.NUMBERVALUE(SUBSTITUTE(SUBSTITUTE(SUBSTITUTE(SUBSTITUTE(SUBSTITUTE(SUBSTITUTE(SUBSTITUTE(SUBSTITUTE(SUBSTITUTE(SUBSTITUTE(SUBSTITUTE(SUBSTITUTE(SUBSTITUTE(SUBSTITUTE(SUBSTITUTE(SUBSTITUTE(SUBSTITUTE(SUBSTITUTE(SUBSTITUTE(SUBSTITUTE(SUBSTITUTE(SUBSTITUTE(SUBSTITUTE(SUBSTITUTE(SUBSTITUTE(SUBSTITUTE(SUBSTITUTE(SUBSTITUTE(SUBSTITUTE(SUBSTITUTE(SUBSTITUTE(SUBSTITUTE(SUBSTITUTE(SUBSTITUTE(SUBSTITUTE(SUBSTITUTE(LEFT(_xlpm.txt&" ",IFERROR(FIND("(",_xlpm.txt)-1,FIND(" ",_xlpm.txt&" ")+99)),"%",""),"$",""),",","")," days","")," day","")," hours","")," hour","")," minutes","")," minute","")," weeks","")," week","")," months","")," month",""),"hours/year","")," per SKU","")," per module","")," annually","")," per 100 FTE","")," bids","")," findings","")," open items","")," variance","")," per certification",""),"x",""),"M","")," average","")," reports","")," SKUs","")," patients","")," unfavorable","")," contacts","")," monthly","")," per month","")," of available time","")," design reuse","")," ","")),0)),_xlpm.ind,_xlpm.parse(_xlpm.g),_xlpm.tgt,_xlpm.parse(_xlpm.f),IF(OR(_xlpm.ind=0,_xlpm.tgt=0,_xlpm.g="",_xlpm.g="Not Available",_xlpm.f=""),"-",IF(_xlpm.h="↓",(_xlpm.ind-_xlpm.tgt)/ABS(_xlpm.ind+0.0001),(_xlpm.tgt-_xlpm.ind)/ABS(_xlpm.ind+0.0001)))),"-")} -> 0.12499844 | Q23: {=IFERROR(_xlfn.LET(_xlpm.e,E23,_xlpm.g,G23,_xlpm.h,H23,_xlpm.parse,_xlfn.LAMBDA(_xlpm.txt,IFERROR(_xlfn.NUMBERVALUE(SUBSTITUTE(SUBSTITUTE(SUBSTITUTE(SUBSTITUTE(SUBSTITUTE(SUBSTITUTE(SUBSTITUTE(SUBSTITUTE(SUBSTITUTE(SUBSTITUTE(SUBSTITUTE(SUBSTITUTE(SUBSTITUTE(SUBSTITUTE(SUBSTITUTE(SUBSTITUTE(SUBSTITUTE(SUBSTITUTE(SUBSTITUTE(SUBSTITUTE(SUBSTITUTE(SUBSTITUTE(SUBSTITUTE(SUBSTITUTE(SUBSTITUTE(SUBSTITUTE(SUBSTITUTE(SUBSTITUTE(SUBSTITUTE(SUBSTITUTE(SUBSTITUTE(SUBSTITUTE(SUBSTITUTE(SUBSTITUTE(SUBSTITUTE(SUBSTITUTE(LEFT(_xlpm.txt&" ",IFERROR(FIND("(",_xlpm.txt)-1,FIND(" ",_xlpm.txt&" ")+99)),"%",""),"$",""),",","")," days","")," day","")," hours","")," hour","")," minutes","")," minute","")," weeks","")," week","")," months","")," month",""),"hours/year","")," per SKU","")," per module","")," annually","")," per 100 FTE","")," bids","")," findings","")," open items","")," variance","")," per certification",""),"x",""),"M","")," average","")," reports","")," SKUs","")," patients","")," unfavorable","")," contacts","")," monthly","")," per month","")," of available time","")," design reuse","")," ","")),0)),_xlpm.base,_xlpm.parse(_xlpm.e),_xlpm.ind,_xlpm.parse(_xlpm.g),IF(OR(_xlpm.ind=0,_xlpm.base=0,_xlpm.g="",_xlpm.g="Not Available",_xlpm.e=""),"-",IF(_xlpm.h="↓",IF(_xlpm.base>_xlpm.ind,"Below Industry","Above Industry"),IF(_xlpm.base<_xlpm.ind,"Below Industry","Above Industry")))),"-")} -> Below Industry | R23: =IFERROR(IF(Q23="Below Industry","🔴 Lagging",IF(Q23="Above Industry","🟢 Leading","⚪ N/A")),"⚪ N/A") -> 🔴 Lagging | S23: {=IFERROR(_xlfn.LET(_xlpm.e,E23,_xlpm.parse,_xlfn.LAMBDA(_xlpm.txt,IFERROR(_xlfn.NUMBERVALUE(SUBSTITUTE(SUBSTITUTE(SUBSTITUTE(SUBSTITUTE(SUBSTITUTE(SUBSTITUTE(SUBSTITUTE(SUBSTITUTE(SUBSTITUTE(SUBSTITUTE(SUBSTITUTE(SUBSTITUTE(SUBSTITUTE(SUBSTITUTE(SUBSTITUTE(SUBSTITUTE(SUBSTITUTE(SUBSTITUTE(SUBSTITUTE(SUBSTITUTE(SUBSTITUTE(SUBSTITUTE(SUBSTITUTE(SUBSTITUTE(SUBSTITUTE(SUBSTITUTE(SUBSTITUTE(SUBSTITUTE(SUBSTITUTE(SUBSTITUTE(SUBSTITUTE(SUBSTITUTE(SUBSTITUTE(SUBSTITUTE(SUBSTITUTE(SUBSTITUTE(LEFT(_xlpm.txt&" ",IFERROR(FIND("(",_xlpm.txt)-1,FIND(" ",_xlpm.txt&" ")+99)),"%",""),"$",""),",","")," days","")," day","")," hours","")," hour","")," minutes","")," minute","")," weeks","")," week","")," months","")," month",""),"hours/year","")," per SKU","")," per module","")," annually","")," per 100 FTE","")," bids","")," findings","")," open items","")," variance","")," per certification",""),"x",""),"M","")," average","")," reports","")," SKUs","")," patients","")," unfavorable","")," contacts","")," monthly","")," per month","")," of available time","")," design reuse","")," ","")),0)),ABS(_xlpm.parse(_xlpm.e))),0)} -> 12 | T23: =IFERROR(IF(L23="-",0,ABS(L23)*100),0) -> 41.666319 | U23: =IFERROR(RANK(T23,$T$17:$T$662,0),"-") -> 292 | V23: =IFERROR(IF(OR(L23="-",S23=0),0,S23*ABS(L23)*$F$9*$B$5*$B$7),0) -> 698.05668 | W23: =IFERROR(IF(V23=0,0,V23*(1-(1/(1+$B$11)^$B$10))/$B$11),0) -> 1735.9637 | X23: =IFERROR(IF(V23=0,"-",ROUND(12/(V23/($F$9*40)+0.001),0)),"-") -> 124 | Y23: =IF(T23>=50,"🔥 Critical",IF(T23>=25,"⚠️ High",IF(T23>=10,"📊 Medium","📉 Low"))) -> ⚠️ High
